Workbook
Name Africa: 表格8[[#All],[Africa]]
Name Africa: 表格8[[#All],[Africa]]
Name America: #REF!
Name Americas: 表格5[[#All],[Americas]]
Name Americas: 表格5[[#All],[Americas]]
Name Asia: 表格1[[#All],[Asia]]
Name Asia: 表格1[[#All],[Asia]]
Name CHINA: #REF!
Name CO2係數: 表格2[[#Headers],[CO2係數]]
Name CO2係數: 表格2[[#Headers],[CO2係數]]
Name EMEA: #REF!
Name Europe: 表格9[[#All],[Europe]]
Name Europe: 表格9[[#All],[Europe]]
Name India: #REF!
Name NEA: #REF!
Name Oceania: 表格10[[#All],[Oceania]]
Name Oceania: 表格10[[#All],[Oceania]]
Name region: 'Other Emission Factor'!$M$3:$Q$3
Name SEA: #REF!
Name TAIWAN: #REF!
Name title: 'Other Emission Factor'!$B$4:$C$4
Name title2: 'Other Emission Factor'!$B$10:$C$10
Name 國家: 表格13[[#All],[國家/市場]]
Name 國家: 表格13[[#All],[國家/市場]]
Name 國家電網: 表格13[[#All],[國家&電網]]
Name 國家電網: 表格13[[#All],[國家&電網]]
Name 溫室氣體種類: '6.GWP'!$B$1:$B$173
Name 溫室氣體種類: '6.GWP'!$B$1:$B$173
Name 電力係數: 表格13[[#All],[電力係數]]
Name 電力係數: 表格13[[#All],[電力係數]]
Name 電力係數年度: 表格13[[#All],[電力係數年度]]
Name 電力係數年度: 表格13[[#All],[電力係數年度]]
Name 電力係數來源: 表格13[[#All],[電力係數來源]]
Name 電力係數來源: 表格13[[#All],[電力係數來源]]
Name 電網: 表格13[[#All],[電網]]
Name 電網: 表格13[[#All],[電網]]
Name 預設值Default: '4.Default Emission Factor'!$D:$D
Name 預設逸散率: 表格12[[#All],[冷媒設備Factor in Equation]]
Name 預設逸散率Default: 表格12[[#All],[冷媒設備Factor in Equation]]

Sheet 1.GHG Inventory Form
B1: 組織及盤查概況Organization Overview
B3: 填表日期 Date of Form | D3: 區域 Region
B4: 公司名稱： Company Name | D4: 國家/市場： Country or Market
B5: 廠區名稱： Site Name | C5: Soest, DE00 | D5: 盤查年份（西元）： Inventory Year | E5: 2023
B6: 盤查單位： Inventory Dept. | D6: IPCC選擇年度 IPCC Report Year | E6: IPCC AR6 Report(2021)
B7: 填表人： Form Filler | C7: Jan Birkenfeld | D7: 電話： Phone Number
B8: 郵箱： Email | C8: Jan.birkenfeld@deltaww.com
B9: 填表人地址 / 盤查地址 Filler/site Address | C9: Coesterweg 45, D-59494 Soest, Germany
B10: 廠區內排除： Excluded Areas | C10: 0
B12: 報告邊界 Reporting boundaries
B13: 類別 1: 直接溫室氣體排放和移除 Category1: Direct GHG emissions and removals
B14: 主類別 Category | C14: 子類別 Sub-Category | D14: 項目名稱 Emission Source Type | G14: 活動數據Activity Data | P14: 自訂溫室氣體排放係數 Custom GHG Emission Factors | Y14: 可能產生之溫室氣體種類 (GHG Species) | AF14: 排放係數 Default Emission Factors | AN14: Global Warming Potentials (GWP) | AU14: 溫室氣體排放量 (Individual GHG Emissions) | BB14: 合計Sum (t-CO2e) | BC14: 類別1、2佔比 Percentage of Category 1, 2 | BD14: 總碳排放量佔比 Percentage of Total Emissions
G15: 是否有此排放源 Applicability (Yes/No) | H15: 設備 Emission Source (Operation or Process) | I15: 自訂/預設係數 Custom/Default Emission Factor | J15: 預設排放源名稱 Default Fuel (Combustion Emissions), or Greenhouse Gas (Process Direct Emissions or Fugitive Emissions) | K15: 自訂排放源名稱 Custom Fuel (Combustion Emissions), or Greenhouse Gas (Process Direct Emissions or Fugitive Emissions) | L15: 活動數據(使用量/填充量) Usage or Consumption | M15: 活動數據單位 Unit | N15: 自訂活動數據單位 Custom Unit (if different from default) | O15: 活動數據佐證 Data Evidence / Reference | P15: CO2 | Q15: CH4 | R15: N2O | S15: HFCs | T15: PFCs | U15: SF6 | V15: NF3 | W15: 係數單位 Emission Factor Unit | X15: 係數來源 Emission Factor Reference | Y15: CO2 | Z15: CH4 | AA15: N2O | AB15: HFCs | AC15: PFCs | AD15: SF6 | AE15: NF3 | AF15: CO2 | AG15: CH4 | AH15: N2O | AI15: HFCs | AJ15: PFCs | AK15: SF6 | AL15: NF3 | AM15: 排放係數來源 Emission Factor Reference | AN15: CO2 | AO15: CH4 | AP15: N2O | AQ15: HFCs | AR15: PFCs | AS15: SF6 | AT15: NF3 | AU15: CO2 | AV15: CH4 | AW15: N2O | AX15: HFCs | AY15: PFCs | AZ15: SF6 | BA15: NF3 | BI15: 排放源名稱 | BJ15: 活動數據來源 | BK15: 排放係數來源
A16: 1 | B16: 類別1 Category 1 | C16: 1.1 | D16: 固定燃燒直接排放 Stationary Combustion | G16: Y | H16: 鍋爐-發電機 Boiler-Generator | I16: 預設值Default | J16: 天然氣Natural Gas | L16: 265.97722 | M16: =IFERROR(IF(I16="預設值Default",VLOOKUP($J16,'4.Default Emission Factor'!$D:$V,16,FALSE),"請填寫自訂活動數據單位Please fill in Custom Unit"),"請選擇預設排放係數名稱Please Choose Default Fuel or Greenhouse Gas") -> KM3 | Y16: =IF(AF16>0.0000000001,"V","") -> V | Z16: =IF(AG16>0.0000000001,"V","") -> V | AA16: =IF(AH16>0.0000000001,"V","") -> V | AB16: =IF(AI16>0.0000000001,"V","") | AC16: =IF(AJ16>0.0000000001,"V","") | AD16: =IF(AK16>0.0000000001,"V","") | AE16: =IF(AL16>0.0000000001,"V","") | AF16: =IFERROR(IF($I16="預設值Default",ROUND(VLOOKUP($J16,'4.Default Emission Factor'!$D:$V,2,FALSE),10),IF($I16="自訂值Custom Value",P16,0)),0) -> 1.8790358 | AG16: =IFERROR(IF($I16="預設值Default",ROUND(VLOOKUP($J16,'4.Default Emission Factor'!$D:$V,4,FALSE),10),IF($I16="自訂值Custom Value",Q16,0)),0) -> 3.34944e-05 | AH16: =IFERROR(IF($I16="預設值Default",ROUND(VLOOKUP($J16,'4.Default Emission Factor'!$D:$V,6,FALSE),10),IF($I16="自訂值Custom Value",R16,0)),0) -> 3.3494e-06 | AI16: =IFERROR(IF($I16="預設值Default",ROUND(VLOOKUP($J16,'4.Default Emission Factor'!$D:$V,8,FALSE),10),IF($I16="自訂值Custom Value",S16,0)),0) -> 0 | AJ16: =IFERROR(IF($I16="預設值Default",ROUND(VLOOKUP($J16,'4.Default Emission Factor'!$D:$V,10,FALSE),10),IF($I16="自訂值Custom Value",T16,0)),0) -> 0 | AK16: =IFERROR(IF($I16="預設值Default",ROUND(VLOOKUP($J16,'4.Default Emission Factor'!$D:$V,12,FALSE),10),IF($I16="自訂值Custom Value",U16,0)),0) -> 0 | AL16: =IFERROR(IF($I16="預設值Default",ROUND(VLOOKUP($J16,'4.Default Emission Factor'!$D:$V,14,FALSE),10),IF($I16="自訂值Custom Value",V16,0)),0) -> 0 | AM16: =IFERROR(IF(I16="預設值Default",VLOOKUP($J16,'4.Default Emission Factor'!$D:$V,17,FALSE),IF(I16="自訂值Custom Value",X16,"")),"") -> 環保署排放係管理表6.0.4Taiwan EPA GHG coefficient table 6.0.4 | AN16: =IF(Y16="V",1,0) -> 1 | AO16: =IF(Z16="V",IF('1.GHG Inventory Form'!$E$6="IPCC AR2 Report(1995)",'6.GWP'!$C$2,IF('1.GHG Inventory Form'!$E$6="IPCC AR3 Report(2001)",'6.GWP'!$D$2,IF('1.GHG Inventory Form'!$E$6="IPCC AR4 Report(2007)",'6.GWP'!$E$2,IF('1.GHG Inventory Form'!$E$6="IPCC AR5 Report(2013)",'6.GWP'!$F$2,IF('1.GHG Inventory Form'!$E$6="IPCC AR6 Report(2021)",'6.GWP'!$G$2,0))))),0) -> 27.9 | AP16: =IF(AA16="V",IF('1.GHG Inventory Form'!$E$6="IPCC AR2 Report(1995)",'6.GWP'!$C$3,IF('1.GHG Inventory Form'!$E$6="IPCC AR3 Report(2001)",'6.GWP'!$D$3,IF('1.GHG Inventory Form'!$E$6="IPCC AR4 Report(2007)",'6.GWP'!$E$3,IF('1.GHG Inventory Form'!$E$6="IPCC AR5 Report(2013)",'6.GWP'!$F$3,IF('1.GHG Inventory Form'!$E$6="IPCC AR6 Report(2021)",'6.GWP'!$G$3,0))))),0) -> 273 | AQ16: =IFERROR(IF(AND(AB16="V",$I16="預設值"),IF('1.GHG Inventory Form'!$E$6="IPCC AR2 Report(1995)",VLOOKUP($J16,'6.GWP'!$B$1:$G$173,2,FALSE),IF('1.GHG Inventory Form'!$E$6="IPCC AR3 Report(2001)",VLOOKUP($J16,'6.GWP'!$B$1:$G$173,3,FALSE),IF('1.GHG Inventory Form'!$E$6="IPCC AR4 Report(2007)",VLOOKUP($J16,'6.GWP'!$B$1:$G$173,4,FALSE),IF('1.GHG Inventory Form'!$E$6="IPCC AR5 Report(2013)",VLOOKUP($J16,'6.GWP'!$B$1:$G$173,5,FALSE),IF('1.GHG Inventory Form'!$E$6="IPCC AR6 Report(2021)",VLOOKUP($J16,'6.GWP'!$B$2:$G$173,6,FALSE),0))))),IF(AND(AB16="V",$I16="自訂值"),IF('1.GHG Inventory Form'!$E$6="IPCC AR2 Report(1995)",VLOOKUP($K16,'6.GWP'!$B$1:$G$173,2,FALSE),IF('1.GHG Inventory Form'!$E$6="IPCC AR3 Report(2001)",VLOOKUP($K16,'6.GWP'!$B$1:$G$173,3,FALSE),IF('1.GHG Inventory Form'!$E$6="IPCC AR4 Report(2007)",VLOOKUP($K16,'6.GWP'!$B$1:$G$173,4,FALSE),IF('1.GHG Inventory Form'!$E$6="IPCC AR5 Report(2013)",VLOOKUP($K16,'6.GWP'!$B$1:$G$173,5,FALSE),IF('1.GHG Inventory Form'!$E$6="IPCC AR6 Report(2021)",VLOOKUP($K16,'6.GWP'!$B$2:$G$173,6,FALSE),0))))),0)),0) -> 0 | AR16: =IFERROR(IF(AND(AC16="V",$I16="預設值"),IF('1.GHG Inventory Form'!$E$6="IPCC AR2 Report(1995)",VLOOKUP($J16,'6.GWP'!$B$1:$G$173,2,FALSE),IF('1.GHG Inventory Form'!$E$6="IPCC AR3 Report(2001)",VLOOKUP($J16,'6.GWP'!$B$1:$G$173,3,FALSE),IF('1.GHG Inventory Form'!$E$6="IPCC AR4 Report(2007)",VLOOKUP($J16,'6.GWP'!$B$1:$G$173,4,FALSE),IF('1.GHG Inventory Form'!$E$6="IPCC AR5 Report(2013)",VLOOKUP($J16,'6.GWP'!$B$1:$G$173,5,FALSE),IF('1.GHG Inventory Form'!$E$6="IPCC AR6 Report(2021)",VLOOKUP($J16,'6.GWP'!$B$2:$G$173,6,FALSE),0))))),IF(AND(AC16="V",$I16="自訂值"),IF('1.GHG Inventory Form'!$E$6="IPCC AR2 Report(1995)",VLOOKUP($K16,'6.GWP'!$B$1:$G$173,2,FALSE),IF('1.GHG Inventory Form'!$E$6="IPCC AR3 Report(2001)",VLOOKUP($K16,'6.GWP'!$B$1:$G$173,3,FALSE),IF('1.GHG Inventory Form'!$E$6="IPCC AR4 Report(2007)",VLOOKUP($K16,'6.GWP'!$B$1:$G$173,4,FALSE),IF('1.GHG Inventory Form'!$E$6="IPCC AR5 Report(2013)",VLOOKUP($K16,'6.GWP'!$B$1:$G$173,5,FALSE),IF('1.GHG Inventory Form'!$E$6="IPCC AR6 Report(2021)",VLOOKUP($K16,'6.GWP'!$B$2:$G$173,6,FALSE),0))))),0)),0) -> 0 | AS16: =IF(AD16="V",IF('1.GHG Inventory Form'!$E$6="IPCC AR2 Report(1995)",'6.GWP'!$C$5,IF('1.GHG Inventory Form'!$E$6="IPCC AR3 Report(2001)",'6.GWP'!$D$5,IF('1.GHG Inventory Form'!$E$6="IPCC AR4 Report(2007)",'6.GWP'!$E$5,IF('1.GHG Inventory Form'!$E$6="IPCC AR5 Report(2013)",'6.GWP'!$F$5,IF('1.GHG Inventory Form'!$E$6="IPCC AR6 Report(2021)",'6.GWP'!$G$5,0))))),0) -> 0 | AT16: =IF(AE16="V",IF('1.GHG Inventory Form'!$E$6="IPCC AR2 Report(1995)",'6.GWP'!$C$4,IF('1.GHG Inventory Form'!$E$6="IPCC AR3 Report(2001)",'6.GWP'!$D$4,IF('1.GHG Inventory Form'!$E$6="IPCC AR4 Report(2007)",'6.GWP'!$E$4,IF('1.GHG Inventory Form'!$E$6="IPCC AR5 Report(2013)",'6.GWP'!$F$4,IF('1.GHG Inventory Form'!$E$6="IPCC AR6 Report(2021)",'6.GWP'!$G$4,0))))),0) -> 0 | AU16: =IFERROR($L16*AF16*AN16,"") -> 499.78072 | AV16: =IFERROR($L16*AG16*AO16,"") -> 0.24855405 | AW16: =IFERROR($L16*AH16*AP16,"") -> 0.2432059 | AX16: =IFERROR($L16*AI16*AQ16,"") -> 0 | AY16: =IFERROR($L16*AJ16*AR16,"") -> 0 | AZ16: =IFERROR($L16*AK16*AS16,"") -> 0 | BA16: =IFERROR($L16*AL16*AT16,"") -> 0 | BB16: =ROUND(SUM(AU16:BA16),4) -> 500.2725 | BC16: =BB16/SUM($BB$16:$BB$99) -> 0.35001281 | BD16: =BB16/$BB$169 -> 0.31544819 | BI16: =IF(H16="","",IF(I16="預設值Default",H16&J16,IF(I16="自訂值Custom Value",H16&K16,""))) -> 鍋爐-發電機 Boiler-Generator天然氣Natural Gas | BJ16: =IF(H16="其它設備，請說明","",IF(O16=0,"",O16)) | BK16: =IF(H16="","",IF(I16="預設值Default",AM16,IF(I16="自訂值Custom Value",X16,""))) -> 環保署排放係管理表6.0.4Taiwan EPA GHG coefficient table 6.0.4
A17: 2 | I17: 預設值Default | M17: =IFERROR(IF(I17="預設值Default",VLOOKUP($J17,'4.Default Emission Factor'!$D:$V,16,FALSE),"請填寫自訂活動數據單位Please fill in Custom Unit"),"請選擇預設排放係數名稱Please Choose Default Fuel or Greenhouse Gas") -> 請選擇預設排放係數名稱Please Choose Default Fuel or Greenhouse Gas | Y17: =IF(AF17>0.0000000001,"V","") | Z17: =IF(AG17>0.0000000001,"V","") | AA17: =IF(AH17>0.0000000001,"V","") | AB17: =IF(AI17>0.0000000001,"V","") | AC17: =IF(AJ17>0.0000000001,"V","") | AD17: =IF(AK17>0.0000000001,"V","") | AE17: =IF(AL17>0.0000000001,"V","") | AF17: =IFERROR(IF($I17="預設值Default",ROUND(VLOOKUP($J17,'4.Default Emission Factor'!$D:$V,2,FALSE),10),IF($I17="自訂值Custom Value",P17,0)),0) -> 0 | AG17: =IFERROR(IF($I17="預設值Default",ROUND(VLOOKUP($J17,'4.Default Emission Factor'!$D:$V,4,FALSE),10),IF($I17="自訂值Custom Value",Q17,0)),0) -> 0 | AH17: =IFERROR(IF($I17="預設值Default",ROUND(VLOOKUP($J17,'4.Default Emission Factor'!$D:$V,6,FALSE),10),IF($I17="自訂值Custom Value",R17,0)),0) -> 0 | AI17: =IFERROR(IF($I17="預設值Default",ROUND(VLOOKUP($J17,'4.Default Emission Factor'!$D:$V,8,FALSE),10),IF($I17="自訂值Custom Value",S17,0)),0) -> 0 | AJ17: =IFERROR(IF($I17="預設值Default",ROUND(VLOOKUP($J17,'4.Default Emission Factor'!$D:$V,10,FALSE),10),IF($I17="自訂值Custom Value",T17,0)),0) -> 0 | AK17: =IFERROR(IF($I17="預設值Default",ROUND(VLOOKUP($J17,'4.Default Emission Factor'!$D:$V,12,FALSE),10),IF($I17="自訂值Custom Value",U17,0)),0) -> 0 | AL17: =IFERROR(IF($I17="預設值Default",ROUND(VLOOKUP($J17,'4.Default Emission Factor'!$D:$V,14,FALSE),10),IF($I17="自訂值Custom Value",V17,0)),0) -> 0 | AM17: =IFERROR(IF(I17="預設值Default",VLOOKUP($J17,'4.Default Emission Factor'!$D:$V,17,FALSE),IF(I17="自訂值Custom Value",X17,"")),"") | AN17: =IF(Y17="V",1,0) -> 0 | AO17: =IF(Z17="V",IF('1.GHG Inventory Form'!$E$6="IPCC AR2 Report(1995)",'6.GWP'!$C$2,IF('1.GHG Inventory Form'!$E$6="IPCC AR3 Report(2001)",'6.GWP'!$D$2,IF('1.GHG Inventory Form'!$E$6="IPCC AR4 Report(2007)",'6.GWP'!$E$2,IF('1.GHG Inventory Form'!$E$6="IPCC AR5 Report(2013)",'6.GWP'!$F$2,IF('1.GHG Inventory Form'!$E$6="IPCC AR6 Report(2021)",'6.GWP'!$G$2,0))))),0) -> 0 | AP17: =IF(AA17="V",IF('1.GHG Inventory Form'!$E$6="IPCC AR2 Report(1995)",'6.GWP'!$C$3,IF('1.GHG Inventory Form'!$E$6="IPCC AR3 Report(2001)",'6.GWP'!$D$3,IF('1.GHG Inventory Form'!$E$6="IPCC AR4 Report(2007)",'6.GWP'!$E$3,IF('1.GHG Inventory Form'!$E$6="IPCC AR5 Report(2013)",'6.GWP'!$F$3,IF('1.GHG Inventory Form'!$E$6="IPCC AR6 Report(2021)",'6.GWP'!$G$3,0))))),0) -> 0 | AQ17: =IFERROR(IF(AND(AB17="V",$I17="預設值"),IF('1.GHG Inventory Form'!$E$6="IPCC AR2 Report(1995)",VLOOKUP($J17,'6.GWP'!$B$1:$G$173,2,FALSE),IF('1.GHG Inventory Form'!$E$6="IPCC AR3 Report(2001)",VLOOKUP($J17,'6.GWP'!$B$1:$G$173,3,FALSE),IF('1.GHG Inventory Form'!$E$6="IPCC AR4 Report(2007)",VLOOKUP($J17,'6.GWP'!$B$1:$G$173,4,FALSE),IF('1.GHG Inventory Form'!$E$6="IPCC AR5 Report(2013)",VLOOKUP($J17,'6.GWP'!$B$1:$G$173,5,FALSE),IF('1.GHG Inventory Form'!$E$6="IPCC AR6 Report(2021)",VLOOKUP($J17,'6.GWP'!$B$2:$G$173,6,FALSE),0))))),IF(AND(AB17="V",$I17="自訂值"),IF('1.GHG Inventory Form'!$E$6="IPCC AR2 Report(1995)",VLOOKUP($K17,'6.GWP'!$B$1:$G$173,2,FALSE),IF('1.GHG Inventory Form'!$E$6="IPCC AR3 Report(2001)",VLOOKUP($K17,'6.GWP'!$B$1:$G$173,3,FALSE),IF('1.GHG Inventory Form'!$E$6="IPCC AR4 Report(2007)",VLOOKUP($K17,'6.GWP'!$B$1:$G$173,4,FALSE),IF('1.GHG Inventory Form'!$E$6="IPCC AR5 Report(2013)",VLOOKUP($K17,'6.GWP'!$B$1:$G$173,5,FALSE),IF('1.GHG Inventory Form'!$E$6="IPCC AR6 Report(2021)",VLOOKUP($K17,'6.GWP'!$B$2:$G$173,6,FALSE),0))))),0)),0) -> 0 | AR17: =IFERROR(IF(AND(AC17="V",$I17="預設值"),IF('1.GHG Inventory Form'!$E$6="IPCC AR2 Report(1995)",VLOOKUP($J17,'6.GWP'!$B$1:$G$173,2,FALSE),IF('1.GHG Inventory Form'!$E$6="IPCC AR3 Report(2001)",VLOOKUP($J17,'6.GWP'!$B$1:$G$173,3,FALSE),IF('1.GHG Inventory Form'!$E$6="IPCC AR4 Report(2007)",VLOOKUP($J17,'6.GWP'!$B$1:$G$173,4,FALSE),IF('1.GHG Inventory Form'!$E$6="IPCC AR5 Report(2013)",VLOOKUP($J17,'6.GWP'!$B$1:$G$173,5,FALSE),IF('1.GHG Inventory Form'!$E$6="IPCC AR6 Report(2021)",VLOOKUP($J17,'6.GWP'!$B$2:$G$173,6,FALSE),0))))),IF(AND(AC17="V",$I17="自訂值"),IF('1.GHG Inventory Form'!$E$6="IPCC AR2 Report(1995)",VLOOKUP($K17,'6.GWP'!$B$1:$G$173,2,FALSE),IF('1.GHG Inventory Form'!$E$6="IPCC AR3 Report(2001)",VLOOKUP($K17,'6.GWP'!$B$1:$G$173,3,FALSE),IF('1.GHG Inventory Form'!$E$6="IPCC AR4 Report(2007)",VLOOKUP($K17,'6.GWP'!$B$1:$G$173,4,FALSE),IF('1.GHG Inventory Form'!$E$6="IPCC AR5 Report(2013)",VLOOKUP($K17,'6.GWP'!$B$1:$G$173,5,FALSE),IF('1.GHG Inventory Form'!$E$6="IPCC AR6 Report(2021)",VLOOKUP($K17,'6.GWP'!$B$2:$G$173,6,FALSE),0))))),0)),0) -> 0 | AS17: =IF(AD17="V",IF('1.GHG Inventory Form'!$E$6="IPCC AR2 Report(1995)",'6.GWP'!$C$5,IF('1.GHG Inventory Form'!$E$6="IPCC AR3 Report(2001)",'6.GWP'!$D$5,IF('1.GHG Inventory Form'!$E$6="IPCC AR4 Report(2007)",'6.GWP'!$E$5,IF('1.GHG Inventory Form'!$E$6="IPCC AR5 Report(2013)",'6.GWP'!$F$5,IF('1.GHG Inventory Form'!$E$6="IPCC AR6 Report(2021)",'6.GWP'!$G$5,0))))),0) -> 0 | AT17: =IF(AE17="V",IF('1.GHG Inventory Form'!$E$6="IPCC AR2 Report(1995)",'6.GWP'!$C$4,IF('1.GHG Inventory Form'!$E$6="IPCC AR3 Report(2001)",'6.GWP'!$D$4,IF('1.GHG Inventory Form'!$E$6="IPCC AR4 Report(2007)",'6.GWP'!$E$4,IF('1.GHG Inventory Form'!$E$6="IPCC AR5 Report(2013)",'6.GWP'!$F$4,IF('1.GHG Inventory Form'!$E$6="IPCC AR6 Report(2021)",'6.GWP'!$G$4,0))))),0) -> 0 | AU17: =IFERROR($L17*AF17*AN17,"") | AV17: =IFERROR($L17*AG17*AO17,"") | AW17: =IFERROR($L17*AH17*AP17,"") | AX17: =IFERROR($L17*AI17*AQ17,"") | AY17: =IFERROR($L17*AJ17*AR17,"") | AZ17: =IFERROR($L17*AK17*AS17,"") | BA17: =IFERROR($L17*AL17*AT17,"") | BB17: =ROUND(SUM(AU17:BA17),4) -> 0 | BC17: =BB17/SUM($BB$16:$BB$99) -> 0 | BD17: =BB17/$BB$169 -> 0 | BI17: =IF(H17="","",IF(I17="預設值Default",H17&J17,IF(I17="自訂值Custom Value",H17&K17,""))) | BJ17: =IF(H17="其它設備，請說明","",IF(O17=0,"",O17)) | BK17: =IF(H17="","",IF(I17="預設值Default",AM17,IF(I17="自訂值Custom Value",X17,"")))
A18: 3 | I18: 預設值Default | M18: =IFERROR(IF(I18="預設值Default",VLOOKUP($J18,'4.Default Emission Factor'!$D:$V,16,FALSE),"請填寫自訂活動數據單位Please fill in Custom Unit"),"請選擇預設排放係數名稱Please Choose Default Fuel or Greenhouse Gas") -> 請選擇預設排放係數名稱Please Choose Default Fuel or Greenhouse Gas | Y18: =IF(AF18>0.0000000001,"V","") | Z18: =IF(AG18>0.0000000001,"V","") | AA18: =IF(AH18>0.0000000001,"V","") | AB18: =IF(AI18>0.0000000001,"V","") | AC18: =IF(AJ18>0.0000000001,"V","") | AD18: =IF(AK18>0.0000000001,"V","") | AE18: =IF(AL18>0.0000000001,"V","") | AF18: =IFERROR(IF($I18="預設值Default",ROUND(VLOOKUP($J18,'4.Default Emission Factor'!$D:$V,2,FALSE),10),IF($I18="自訂值Custom Value",P18,0)),0) -> 0 | AG18: =IFERROR(IF($I18="預設值Default",ROUND(VLOOKUP($J18,'4.Default Emission Factor'!$D:$V,4,FALSE),10),IF($I18="自訂值Custom Value",Q18,0)),0) -> 0 | AH18: =IFERROR(IF($I18="預設值Default",ROUND(VLOOKUP($J18,'4.Default Emission Factor'!$D:$V,6,FALSE),10),IF($I18="自訂值Custom Value",R18,0)),0) -> 0 | AI18: =IFERROR(IF($I18="預設值Default",ROUND(VLOOKUP($J18,'4.Default Emission Factor'!$D:$V,8,FALSE),10),IF($I18="自訂值Custom Value",S18,0)),0) -> 0 | AJ18: =IFERROR(IF($I18="預設值Default",ROUND(VLOOKUP($J18,'4.Default Emission Factor'!$D:$V,10,FALSE),10),IF($I18="自訂值Custom Value",T18,0)),0) -> 0 | AK18: =IFERROR(IF($I18="預設值Default",ROUND(VLOOKUP($J18,'4.Default Emission Factor'!$D:$V,12,FALSE),10),IF($I18="自訂值Custom Value",U18,0)),0) -> 0 | AL18: =IFERROR(IF($I18="預設值Default",ROUND(VLOOKUP($J18,'4.Default Emission Factor'!$D:$V,14,FALSE),10),IF($I18="自訂值Custom Value",V18,0)),0) -> 0 | AM18: =IFERROR(IF(I18="預設值Default",VLOOKUP($J18,'4.Default Emission Factor'!$D:$V,17,FALSE),IF(I18="自訂值Custom Value",X18,"")),"") | AN18: =IF(Y18="V",1,0) -> 0 | AO18: =IF(Z18="V",IF('1.GHG Inventory Form'!$E$6="IPCC AR2 Report(1995)",'6.GWP'!$C$2,IF('1.GHG Inventory Form'!$E$6="IPCC AR3 Report(2001)",'6.GWP'!$D$2,IF('1.GHG Inventory Form'!$E$6="IPCC AR4 Report(2007)",'6.GWP'!$E$2,IF('1.GHG Inventory Form'!$E$6="IPCC AR5 Report(2013)",'6.GWP'!$F$2,IF('1.GHG Inventory Form'!$E$6="IPCC AR6 Report(2021)",'6.GWP'!$G$2,0))))),0) -> 0 | AP18: =IF(AA18="V",IF('1.GHG Inventory Form'!$E$6="IPCC AR2 Report(1995)",'6.GWP'!$C$3,IF('1.GHG Inventory Form'!$E$6="IPCC AR3 Report(2001)",'6.GWP'!$D$3,IF('1.GHG Inventory Form'!$E$6="IPCC AR4 Report(2007)",'6.GWP'!$E$3,IF('1.GHG Inventory Form'!$E$6="IPCC AR5 Report(2013)",'6.GWP'!$F$3,IF('1.GHG Inventory Form'!$E$6="IPCC AR6 Report(2021)",'6.GWP'!$G$3,0))))),0) -> 0 | AQ18: =IFERROR(IF(AND(AB18="V",$I18="預設值"),IF('1.GHG Inventory Form'!$E$6="IPCC AR2 Report(1995)",VLOOKUP($J18,'6.GWP'!$B$1:$G$173,2,FALSE),IF('1.GHG Inventory Form'!$E$6="IPCC AR3 Report(2001)",VLOOKUP($J18,'6.GWP'!$B$1:$G$173,3,FALSE),IF('1.GHG Inventory Form'!$E$6="IPCC AR4 Report(2007)",VLOOKUP($J18,'6.GWP'!$B$1:$G$173,4,FALSE),IF('1.GHG Inventory Form'!$E$6="IPCC AR5 Report(2013)",VLOOKUP($J18,'6.GWP'!$B$1:$G$173,5,FALSE),IF('1.GHG Inventory Form'!$E$6="IPCC AR6 Report(2021)",VLOOKUP($J18,'6.GWP'!$B$2:$G$173,6,FALSE),0))))),IF(AND(AB18="V",$I18="自訂值"),IF('1.GHG Inventory Form'!$E$6="IPCC AR2 Report(1995)",VLOOKUP($K18,'6.GWP'!$B$1:$G$173,2,FALSE),IF('1.GHG Inventory Form'!$E$6="IPCC AR3 Report(2001)",VLOOKUP($K18,'6.GWP'!$B$1:$G$173,3,FALSE),IF('1.GHG Inventory Form'!$E$6="IPCC AR4 Report(2007)",VLOOKUP($K18,'6.GWP'!$B$1:$G$173,4,FALSE),IF('1.GHG Inventory Form'!$E$6="IPCC AR5 Report(2013)",VLOOKUP($K18,'6.GWP'!$B$1:$G$173,5,FALSE),IF('1.GHG Inventory Form'!$E$6="IPCC AR6 Report(2021)",VLOOKUP($K18,'6.GWP'!$B$2:$G$173,6,FALSE),0))))),0)),0) -> 0 | AR18: =IFERROR(IF(AND(AC18="V",$I18="預設值"),IF('1.GHG Inventory Form'!$E$6="IPCC AR2 Report(1995)",VLOOKUP($J18,'6.GWP'!$B$1:$G$173,2,FALSE),IF('1.GHG Inventory Form'!$E$6="IPCC AR3 Report(2001)",VLOOKUP($J18,'6.GWP'!$B$1:$G$173,3,FALSE),IF('1.GHG Inventory Form'!$E$6="IPCC AR4 Report(2007)",VLOOKUP($J18,'6.GWP'!$B$1:$G$173,4,FALSE),IF('1.GHG Inventory Form'!$E$6="IPCC AR5 Report(2013)",VLOOKUP($J18,'6.GWP'!$B$1:$G$173,5,FALSE),IF('1.GHG Inventory Form'!$E$6="IPCC AR6 Report(2021)",VLOOKUP($J18,'6.GWP'!$B$2:$G$173,6,FALSE),0))))),IF(AND(AC18="V",$I18="自訂值"),IF('1.GHG Inventory Form'!$E$6="IPCC AR2 Report(1995)",VLOOKUP($K18,'6.GWP'!$B$1:$G$173,2,FALSE),IF('1.GHG Inventory Form'!$E$6="IPCC AR3 Report(2001)",VLOOKUP($K18,'6.GWP'!$B$1:$G$173,3,FALSE),IF('1.GHG Inventory Form'!$E$6="IPCC AR4 Report(2007)",VLOOKUP($K18,'6.GWP'!$B$1:$G$173,4,FALSE),IF('1.GHG Inventory Form'!$E$6="IPCC AR5 Report(2013)",VLOOKUP($K18,'6.GWP'!$B$1:$G$173,5,FALSE),IF('1.GHG Inventory Form'!$E$6="IPCC AR6 Report(2021)",VLOOKUP($K18,'6.GWP'!$B$2:$G$173,6,FALSE),0))))),0)),0) -> 0 | AS18: =IF(AD18="V",IF('1.GHG Inventory Form'!$E$6="IPCC AR2 Report(1995)",'6.GWP'!$C$5,IF('1.GHG Inventory Form'!$E$6="IPCC AR3 Report(2001)",'6.GWP'!$D$5,IF('1.GHG Inventory Form'!$E$6="IPCC AR4 Report(2007)",'6.GWP'!$E$5,IF('1.GHG Inventory Form'!$E$6="IPCC AR5 Report(2013)",'6.GWP'!$F$5,IF('1.GHG Inventory Form'!$E$6="IPCC AR6 Report(2021)",'6.GWP'!$G$5,0))))),0) -> 0 | AT18: =IF(AE18="V",IF('1.GHG Inventory Form'!$E$6="IPCC AR2 Report(1995)",'6.GWP'!$C$4,IF('1.GHG Inventory Form'!$E$6="IPCC AR3 Report(2001)",'6.GWP'!$D$4,IF('1.GHG Inventory Form'!$E$6="IPCC AR4 Report(2007)",'6.GWP'!$E$4,IF('1.GHG Inventory Form'!$E$6="IPCC AR5 Report(2013)",'6.GWP'!$F$4,IF('1.GHG Inventory Form'!$E$6="IPCC AR6 Report(2021)",'6.GWP'!$G$4,0))))),0) -> 0 | AU18: =IFERROR($L18*AF18*AN18,"") | AV18: =IFERROR($L18*AG18*AO18,"") | AW18: =IFERROR($L18*AH18*AP18,"") | AX18: =IFERROR($L18*AI18*AQ18,"") | AY18: =IFERROR($L18*AJ18*AR18,"") | AZ18: =IFERROR($L18*AK18*AS18,"") | BA18: =IFERROR($L18*AL18*AT18,"") | BB18: =ROUND(SUM(AU18:BA18),4) -> 0 | BC18: =BB18/SUM($BB$16:$BB$99) -> 0 | BD18: =BB18/$BB$169 -> 0 | BI18: =IF(H18="","",IF(I18="預設值Default",H18&J18,IF(I18="自訂值Custom Value",H18&K18,""))) | BJ18: =IF(H18="其它設備，請說明","",IF(O18=0,"",O18)) | BK18: =IF(H18="","",IF(I18="預設值Default",AM18,IF(I18="自訂值Custom Value",X18,"")))
A19: 4 | I19: 預設值Default | M19: =IFERROR(IF(I19="預設值Default",VLOOKUP($J19,'4.Default Emission Factor'!$D:$V,16,FALSE),"請填寫自訂活動數據單位Please fill in Custom Unit"),"請選擇預設排放係數名稱Please Choose Default Fuel or Greenhouse Gas") -> 請選擇預設排放係數名稱Please Choose Default Fuel or Greenhouse Gas | Y19: =IF(AF19>0.0000000001,"V","") | Z19: =IF(AG19>0.0000000001,"V","") | AA19: =IF(AH19>0.0000000001,"V","") | AB19: =IF(AI19>0.0000000001,"V","") | AC19: =IF(AJ19>0.0000000001,"V","") | AD19: =IF(AK19>0.0000000001,"V","") | AE19: =IF(AL19>0.0000000001,"V","") | AF19: =IFERROR(IF($I19="預設值Default",ROUND(VLOOKUP($J19,'4.Default Emission Factor'!$D:$V,2,FALSE),10),IF($I19="自訂值Custom Value",P19,0)),0) -> 0 | AG19: =IFERROR(IF($I19="預設值Default",ROUND(VLOOKUP($J19,'4.Default Emission Factor'!$D:$V,4,FALSE),10),IF($I19="自訂值Custom Value",Q19,0)),0) -> 0 | AH19: =IFERROR(IF($I19="預設值Default",ROUND(VLOOKUP($J19,'4.Default Emission Factor'!$D:$V,6,FALSE),10),IF($I19="自訂值Custom Value",R19,0)),0) -> 0 | AI19: =IFERROR(IF($I19="預設值Default",ROUND(VLOOKUP($J19,'4.Default Emission Factor'!$D:$V,8,FALSE),10),IF($I19="自訂值Custom Value",S19,0)),0) -> 0 | AJ19: =IFERROR(IF($I19="預設值Default",ROUND(VLOOKUP($J19,'4.Default Emission Factor'!$D:$V,10,FALSE),10),IF($I19="自訂值Custom Value",T19,0)),0) -> 0 | AK19: =IFERROR(IF($I19="預設值Default",ROUND(VLOOKUP($J19,'4.Default Emission Factor'!$D:$V,12,FALSE),10),IF($I19="自訂值Custom Value",U19,0)),0) -> 0 | AL19: =IFERROR(IF($I19="預設值Default",ROUND(VLOOKUP($J19,'4.Default Emission Factor'!$D:$V,14,FALSE),10),IF($I19="自訂值Custom Value",V19,0)),0) -> 0 | AM19: =IFERROR(IF(I19="預設值Default",VLOOKUP($J19,'4.Default Emission Factor'!$D:$V,17,FALSE),IF(I19="自訂值Custom Value",X19,"")),"") | AN19: =IF(Y19="V",1,0) -> 0 | AO19: =IF(Z19="V",IF('1.GHG Inventory Form'!$E$6="IPCC AR2 Report(1995)",'6.GWP'!$C$2,IF('1.GHG Inventory Form'!$E$6="IPCC AR3 Report(2001)",'6.GWP'!$D$2,IF('1.GHG Inventory Form'!$E$6="IPCC AR4 Report(2007)",'6.GWP'!$E$2,IF('1.GHG Inventory Form'!$E$6="IPCC AR5 Report(2013)",'6.GWP'!$F$2,IF('1.GHG Inventory Form'!$E$6="IPCC AR6 Report(2021)",'6.GWP'!$G$2,0))))),0) -> 0 | AP19: =IF(AA19="V",IF('1.GHG Inventory Form'!$E$6="IPCC AR2 Report(1995)",'6.GWP'!$C$3,IF('1.GHG Inventory Form'!$E$6="IPCC AR3 Report(2001)",'6.GWP'!$D$3,IF('1.GHG Inventory Form'!$E$6="IPCC AR4 Report(2007)",'6.GWP'!$E$3,IF('1.GHG Inventory Form'!$E$6="IPCC AR5 Report(2013)",'6.GWP'!$F$3,IF('1.GHG Inventory Form'!$E$6="IPCC AR6 Report(2021)",'6.GWP'!$G$3,0))))),0) -> 0 | AQ19: =IFERROR(IF(AND(AB19="V",$I19="預設值"),IF('1.GHG Inventory Form'!$E$6="IPCC AR2 Report(1995)",VLOOKUP($J19,'6.GWP'!$B$1:$G$173,2,FALSE),IF('1.GHG Inventory Form'!$E$6="IPCC AR3 Report(2001)",VLOOKUP($J19,'6.GWP'!$B$1:$G$173,3,FALSE),IF('1.GHG Inventory Form'!$E$6="IPCC AR4 Report(2007)",VLOOKUP($J19,'6.GWP'!$B$1:$G$173,4,FALSE),IF('1.GHG Inventory Form'!$E$6="IPCC AR5 Report(2013)",VLOOKUP($J19,'6.GWP'!$B$1:$G$173,5,FALSE),IF('1.GHG Inventory Form'!$E$6="IPCC AR6 Report(2021)",VLOOKUP($J19,'6.GWP'!$B$2:$G$173,6,FALSE),0))))),IF(AND(AB19="V",$I19="自訂值"),IF('1.GHG Inventory Form'!$E$6="IPCC AR2 Report(1995)",VLOOKUP($K19,'6.GWP'!$B$1:$G$173,2,FALSE),IF('1.GHG Inventory Form'!$E$6="IPCC AR3 Report(2001)",VLOOKUP($K19,'6.GWP'!$B$1:$G$173,3,FALSE),IF('1.GHG Inventory Form'!$E$6="IPCC AR4 Report(2007)",VLOOKUP($K19,'6.GWP'!$B$1:$G$173,4,FALSE),IF('1.GHG Inventory Form'!$E$6="IPCC AR5 Report(2013)",VLOOKUP($K19,'6.GWP'!$B$1:$G$173,5,FALSE),IF('1.GHG Inventory Form'!$E$6="IPCC AR6 Report(2021)",VLOOKUP($K19,'6.GWP'!$B$2:$G$173,6,FALSE),0))))),0)),0) -> 0 | AR19: =IFERROR(IF(AND(AC19="V",$I19="預設值"),IF('1.GHG Inventory Form'!$E$6="IPCC AR2 Report(1995)",VLOOKUP($J19,'6.GWP'!$B$1:$G$173,2,FALSE),IF('1.GHG Inventory Form'!$E$6="IPCC AR3 Report(2001)",VLOOKUP($J19,'6.GWP'!$B$1:$G$173,3,FALSE),IF('1.GHG Inventory Form'!$E$6="IPCC AR4 Report(2007)",VLOOKUP($J19,'6.GWP'!$B$1:$G$173,4,FALSE),IF('1.GHG Inventory Form'!$E$6="IPCC AR5 Report(2013)",VLOOKUP($J19,'6.GWP'!$B$1:$G$173,5,FALSE),IF('1.GHG Inventory Form'!$E$6="IPCC AR6 Report(2021)",VLOOKUP($J19,'6.GWP'!$B$2:$G$173,6,FALSE),0))))),IF(AND(AC19="V",$I19="自訂值"),IF('1.GHG Inventory Form'!$E$6="IPCC AR2 Report(1995)",VLOOKUP($K19,'6.GWP'!$B$1:$G$173,2,FALSE),IF('1.GHG Inventory Form'!$E$6="IPCC AR3 Report(2001)",VLOOKUP($K19,'6.GWP'!$B$1:$G$173,3,FALSE),IF('1.GHG Inventory Form'!$E$6="IPCC AR4 Report(2007)",VLOOKUP($K19,'6.GWP'!$B$1:$G$173,4,FALSE),IF('1.GHG Inventory Form'!$E$6="IPCC AR5 Report(2013)",VLOOKUP($K19,'6.GWP'!$B$1:$G$173,5,FALSE),IF('1.GHG Inventory Form'!$E$6="IPCC AR6 Report(2021)",VLOOKUP($K19,'6.GWP'!$B$2:$G$173,6,FALSE),0))))),0)),0) -> 0 | AS19: =IF(AD19="V",IF('1.GHG Inventory Form'!$E$6="IPCC AR2 Report(1995)",'6.GWP'!$C$5,IF('1.GHG Inventory Form'!$E$6="IPCC AR3 Report(2001)",'6.GWP'!$D$5,IF('1.GHG Inventory Form'!$E$6="IPCC AR4 Report(2007)",'6.GWP'!$E$5,IF('1.GHG Inventory Form'!$E$6="IPCC AR5 Report(2013)",'6.GWP'!$F$5,IF('1.GHG Inventory Form'!$E$6="IPCC AR6 Report(2021)",'6.GWP'!$G$5,0))))),0) -> 0 | AT19: =IF(AE19="V",IF('1.GHG Inventory Form'!$E$6="IPCC AR2 Report(1995)",'6.GWP'!$C$4,IF('1.GHG Inventory Form'!$E$6="IPCC AR3 Report(2001)",'6.GWP'!$D$4,IF('1.GHG Inventory Form'!$E$6="IPCC AR4 Report(2007)",'6.GWP'!$E$4,IF('1.GHG Inventory Form'!$E$6="IPCC AR5 Report(2013)",'6.GWP'!$F$4,IF('1.GHG Inventory Form'!$E$6="IPCC AR6 Report(2021)",'6.GWP'!$G$4,0))))),0) -> 0 | AU19: =IFERROR($L19*AF19*AN19,"") | AV19: =IFERROR($L19*AG19*AO19,"") | AW19: =IFERROR($L19*AH19*AP19,"") | AX19: =IFERROR($L19*AI19*AQ19,"") | AY19: =IFERROR($L19*AJ19*AR19,"") | AZ19: =IFERROR($L19*AK19*AS19,"") | BA19: =IFERROR($L19*AL19*AT19,"") | BB19: =ROUND(SUM(AU19:BA19),4) -> 0 | BC19: =BB19/SUM($BB$16:$BB$99) -> 0 | BD19: =BB19/$BB$169 -> 0 | BI19: =IF(H19="","",IF(I19="預設值Default",H19&J19,IF(I19="自訂值Custom Value",H19&K19,""))) | BJ19: =IF(H19="其它設備，請說明","",IF(O19=0,"",O19)) | BK19: =IF(H19="","",IF(I19="預設值Default",AM19,IF(I19="自訂值Custom Value",X19,"")))
A20: 5 | I20: 預設值Default | M20: =IFERROR(IF(I20="預設值Default",VLOOKUP($J20,'4.Default Emission Factor'!$D:$V,16,FALSE),"請填寫自訂活動數據單位Please fill in Custom Unit"),"請選擇預設排放係數名稱Please Choose Default Fuel or Greenhouse Gas") -> 請選擇預設排放係數名稱Please Choose Default Fuel or Greenhouse Gas | Y20: =IF(AF20>0.0000000001,"V","") | Z20: =IF(AG20>0.0000000001,"V","") | AA20: =IF(AH20>0.0000000001,"V","") | AB20: =IF(AI20>0.0000000001,"V","") | AC20: =IF(AJ20>0.0000000001,"V","") | AD20: =IF(AK20>0.0000000001,"V","") | AE20: =IF(AL20>0.0000000001,"V","") | AF20: =IFERROR(IF($I20="預設值Default",ROUND(VLOOKUP($J20,'4.Default Emission Factor'!$D:$V,2,FALSE),10),IF($I20="自訂值Custom Value",P20,0)),0) -> 0 | AG20: =IFERROR(IF($I20="預設值Default",ROUND(VLOOKUP($J20,'4.Default Emission Factor'!$D:$V,4,FALSE),10),IF($I20="自訂值Custom Value",Q20,0)),0) -> 0 | AH20: =IFERROR(IF($I20="預設值Default",ROUND(VLOOKUP($J20,'4.Default Emission Factor'!$D:$V,6,FALSE),10),IF($I20="自訂值Custom Value",R20,0)),0) -> 0 | AI20: =IFERROR(IF($I20="預設值Default",ROUND(VLOOKUP($J20,'4.Default Emission Factor'!$D:$V,8,FALSE),10),IF($I20="自訂值Custom Value",S20,0)),0) -> 0 | AJ20: =IFERROR(IF($I20="預設值Default",ROUND(VLOOKUP($J20,'4.Default Emission Factor'!$D:$V,10,FALSE),10),IF($I20="自訂值Custom Value",T20,0)),0) -> 0 | AK20: =IFERROR(IF($I20="預設值Default",ROUND(VLOOKUP($J20,'4.Default Emission Factor'!$D:$V,12,FALSE),10),IF($I20="自訂值Custom Value",U20,0)),0) -> 0 | AL20: =IFERROR(IF($I20="預設值Default",ROUND(VLOOKUP($J20,'4.Default Emission Factor'!$D:$V,14,FALSE),10),IF($I20="自訂值Custom Value",V20,0)),0) -> 0 | AM20: =IFERROR(IF(I20="預設值Default",VLOOKUP($J20,'4.Default Emission Factor'!$D:$V,17,FALSE),IF(I20="自訂值Custom Value",X20,"")),"") | AN20: =IF(Y20="V",1,0) -> 0 | AO20: =IF(Z20="V",IF('1.GHG Inventory Form'!$E$6="IPCC AR2 Report(1995)",'6.GWP'!$C$2,IF('1.GHG Inventory Form'!$E$6="IPCC AR3 Report(2001)",'6.GWP'!$D$2,IF('1.GHG Inventory Form'!$E$6="IPCC AR4 Report(2007)",'6.GWP'!$E$2,IF('1.GHG Inventory Form'!$E$6="IPCC AR5 Report(2013)",'6.GWP'!$F$2,IF('1.GHG Inventory Form'!$E$6="IPCC AR6 Report(2021)",'6.GWP'!$G$2,0))))),0) -> 0 | AP20: =IF(AA20="V",IF('1.GHG Inventory Form'!$E$6="IPCC AR2 Report(1995)",'6.GWP'!$C$3,IF('1.GHG Inventory Form'!$E$6="IPCC AR3 Report(2001)",'6.GWP'!$D$3,IF('1.GHG Inventory Form'!$E$6="IPCC AR4 Report(2007)",'6.GWP'!$E$3,IF('1.GHG Inventory Form'!$E$6="IPCC AR5 Report(2013)",'6.GWP'!$F$3,IF('1.GHG Inventory Form'!$E$6="IPCC AR6 Report(2021)",'6.GWP'!$G$3,0))))),0) -> 0 | AQ20: =IFERROR(IF(AND(AB20="V",$I20="預設值"),IF('1.GHG Inventory Form'!$E$6="IPCC AR2 Report(1995)",VLOOKUP($J20,'6.GWP'!$B$1:$G$173,2,FALSE),IF('1.GHG Inventory Form'!$E$6="IPCC AR3 Report(2001)",VLOOKUP($J20,'6.GWP'!$B$1:$G$173,3,FALSE),IF('1.GHG Inventory Form'!$E$6="IPCC AR4 Report(2007)",VLOOKUP($J20,'6.GWP'!$B$1:$G$173,4,FALSE),IF('1.GHG Inventory Form'!$E$6="IPCC AR5 Report(2013)",VLOOKUP($J20,'6.GWP'!$B$1:$G$173,5,FALSE),IF('1.GHG Inventory Form'!$E$6="IPCC AR6 Report(2021)",VLOOKUP($J20,'6.GWP'!$B$2:$G$173,6,FALSE),0))))),IF(AND(AB20="V",$I20="自訂值"),IF('1.GHG Inventory Form'!$E$6="IPCC AR2 Report(1995)",VLOOKUP($K20,'6.GWP'!$B$1:$G$173,2,FALSE),IF('1.GHG Inventory Form'!$E$6="IPCC AR3 Report(2001)",VLOOKUP($K20,'6.GWP'!$B$1:$G$173,3,FALSE),IF('1.GHG Inventory Form'!$E$6="IPCC AR4 Report(2007)",VLOOKUP($K20,'6.GWP'!$B$1:$G$173,4,FALSE),IF('1.GHG Inventory Form'!$E$6="IPCC AR5 Report(2013)",VLOOKUP($K20,'6.GWP'!$B$1:$G$173,5,FALSE),IF('1.GHG Inventory Form'!$E$6="IPCC AR6 Report(2021)",VLOOKUP($K20,'6.GWP'!$B$2:$G$173,6,FALSE),0))))),0)),0) -> 0 | AR20: =IFERROR(IF(AND(AC20="V",$I20="預設值"),IF('1.GHG Inventory Form'!$E$6="IPCC AR2 Report(1995)",VLOOKUP($J20,'6.GWP'!$B$1:$G$173,2,FALSE),IF('1.GHG Inventory Form'!$E$6="IPCC AR3 Report(2001)",VLOOKUP($J20,'6.GWP'!$B$1:$G$173,3,FALSE),IF('1.GHG Inventory Form'!$E$6="IPCC AR4 Report(2007)",VLOOKUP($J20,'6.GWP'!$B$1:$G$173,4,FALSE),IF('1.GHG Inventory Form'!$E$6="IPCC AR5 Report(2013)",VLOOKUP($J20,'6.GWP'!$B$1:$G$173,5,FALSE),IF('1.GHG Inventory Form'!$E$6="IPCC AR6 Report(2021)",VLOOKUP($J20,'6.GWP'!$B$2:$G$173,6,FALSE),0))))),IF(AND(AC20="V",$I20="自訂值"),IF('1.GHG Inventory Form'!$E$6="IPCC AR2 Report(1995)",VLOOKUP($K20,'6.GWP'!$B$1:$G$173,2,FALSE),IF('1.GHG Inventory Form'!$E$6="IPCC AR3 Report(2001)",VLOOKUP($K20,'6.GWP'!$B$1:$G$173,3,FALSE),IF('1.GHG Inventory Form'!$E$6="IPCC AR4 Report(2007)",VLOOKUP($K20,'6.GWP'!$B$1:$G$173,4,FALSE),IF('1.GHG Inventory Form'!$E$6="IPCC AR5 Report(2013)",VLOOKUP($K20,'6.GWP'!$B$1:$G$173,5,FALSE),IF('1.GHG Inventory Form'!$E$6="IPCC AR6 Report(2021)",VLOOKUP($K20,'6.GWP'!$B$2:$G$173,6,FALSE),0))))),0)),0) -> 0 | AS20: =IF(AD20="V",IF('1.GHG Inventory Form'!$E$6="IPCC AR2 Report(1995)",'6.GWP'!$C$5,IF('1.GHG Inventory Form'!$E$6="IPCC AR3 Report(2001)",'6.GWP'!$D$5,IF('1.GHG Inventory Form'!$E$6="IPCC AR4 Report(2007)",'6.GWP'!$E$5,IF('1.GHG Inventory Form'!$E$6="IPCC AR5 Report(2013)",'6.GWP'!$F$5,IF('1.GHG Inventory Form'!$E$6="IPCC AR6 Report(2021)",'6.GWP'!$G$5,0))))),0) -> 0 | AT20: =IF(AE20="V",IF('1.GHG Inventory Form'!$E$6="IPCC AR2 Report(1995)",'6.GWP'!$C$4,IF('1.GHG Inventory Form'!$E$6="IPCC AR3 Report(2001)",'6.GWP'!$D$4,IF('1.GHG Inventory Form'!$E$6="IPCC AR4 Report(2007)",'6.GWP'!$E$4,IF('1.GHG Inventory Form'!$E$6="IPCC AR5 Report(2013)",'6.GWP'!$F$4,IF('1.GHG Inventory Form'!$E$6="IPCC AR6 Report(2021)",'6.GWP'!$G$4,0))))),0) -> 0 | AU20: =IFERROR($L20*AF20*AN20,"") | AV20: =IFERROR($L20*AG20*AO20,"") | AW20: =IFERROR($L20*AH20*AP20,"") | AX20: =IFERROR($L20*AI20*AQ20,"") | AY20: =IFERROR($L20*AJ20*AR20,"") | AZ20: =IFERROR($L20*AK20*AS20,"") | BA20: =IFERROR($L20*AL20*AT20,"") | BB20: =ROUND(SUM(AU20:BA20),4) -> 0 | BC20: =BB20/SUM($BB$16:$BB$99) -> 0 | BD20: =BB20/$BB$169 -> 0 | BI20: =IF(H20="","",IF(I20="預設值Default",H20&J20,IF(I20="自訂值Custom Value",H20&K20,""))) | BJ20: =IF(H20="其它設備，請說明","",IF(O20=0,"",O20)) | BK20: =IF(H20="","",IF(I20="預設值Default",AM20,IF(I20="自訂值Custom Value",X20,"")))
A21: 6 | I21: 預設值Default | M21: =IFERROR(IF(I21="預設值Default",VLOOKUP($J21,'4.Default Emission Factor'!$D:$V,16,FALSE),"請填寫自訂活動數據單位Please fill in Custom Unit"),"請選擇預設排放係數名稱Please Choose Default Fuel or Greenhouse Gas") -> 請選擇預設排放係數名稱Please Choose Default Fuel or Greenhouse Gas | Y21: =IF(AF21>0.0000000001,"V","") | Z21: =IF(AG21>0.0000000001,"V","") | AA21: =IF(AH21>0.0000000001,"V","") | AB21: =IF(AI21>0.0000000001,"V","") | AC21: =IF(AJ21>0.0000000001,"V","") | AD21: =IF(AK21>0.0000000001,"V","") | AE21: =IF(AL21>0.0000000001,"V","") | AF21: =IFERROR(IF($I21="預設值Default",ROUND(VLOOKUP($J21,'4.Default Emission Factor'!$D:$V,2,FALSE),10),IF($I21="自訂值Custom Value",P21,0)),0) -> 0 | AG21: =IFERROR(IF($I21="預設值Default",ROUND(VLOOKUP($J21,'4.Default Emission Factor'!$D:$V,4,FALSE),10),IF($I21="自訂值Custom Value",Q21,0)),0) -> 0 | AH21: =IFERROR(IF($I21="預設值Default",ROUND(VLOOKUP($J21,'4.Default Emission Factor'!$D:$V,6,FALSE),10),IF($I21="自訂值Custom Value",R21,0)),0) -> 0 | AI21: =IFERROR(IF($I21="預設值Default",ROUND(VLOOKUP($J21,'4.Default Emission Factor'!$D:$V,8,FALSE),10),IF($I21="自訂值Custom Value",S21,0)),0) -> 0 | AJ21: =IFERROR(IF($I21="預設值Default",ROUND(VLOOKUP($J21,'4.Default Emission Factor'!$D:$V,10,FALSE),10),IF($I21="自訂值Custom Value",T21,0)),0) -> 0 | AK21: =IFERROR(IF($I21="預設值Default",ROUND(VLOOKUP($J21,'4.Default Emission Factor'!$D:$V,12,FALSE),10),IF($I21="自訂值Custom Value",U21,0)),0) -> 0 | AL21: =IFERROR(IF($I21="預設值Default",ROUND(VLOOKUP($J21,'4.Default Emission Factor'!$D:$V,14,FALSE),10),IF($I21="自訂值Custom Value",V21,0)),0) -> 0 | AM21: =IFERROR(IF(I21="預設值Default",VLOOKUP($J21,'4.Default Emission Factor'!$D:$V,17,FALSE),IF(I21="自訂值Custom Value",X21,"")),"") | AN21: =IF(Y21="V",1,0) -> 0 | AO21: =IF(Z21="V",IF('1.GHG Inventory Form'!$E$6="IPCC AR2 Report(1995)",'6.GWP'!$C$2,IF('1.GHG Inventory Form'!$E$6="IPCC AR3 Report(2001)",'6.GWP'!$D$2,IF('1.GHG Inventory Form'!$E$6="IPCC AR4 Report(2007)",'6.GWP'!$E$2,IF('1.GHG Inventory Form'!$E$6="IPCC AR5 Report(2013)",'6.GWP'!$F$2,IF('1.GHG Inventory Form'!$E$6="IPCC AR6 Report(2021)",'6.GWP'!$G$2,0))))),0) -> 0 | AP21: =IF(AA21="V",IF('1.GHG Inventory Form'!$E$6="IPCC AR2 Report(1995)",'6.GWP'!$C$3,IF('1.GHG Inventory Form'!$E$6="IPCC AR3 Report(2001)",'6.GWP'!$D$3,IF('1.GHG Inventory Form'!$E$6="IPCC AR4 Report(2007)",'6.GWP'!$E$3,IF('1.GHG Inventory Form'!$E$6="IPCC AR5 Report(2013)",'6.GWP'!$F$3,IF('1.GHG Inventory Form'!$E$6="IPCC AR6 Report(2021)",'6.GWP'!$G$3,0))))),0) -> 0 | AQ21: =IFERROR(IF(AND(AB21="V",$I21="預設值"),IF('1.GHG Inventory Form'!$E$6="IPCC AR2 Report(1995)",VLOOKUP($J21,'6.GWP'!$B$1:$G$173,2,FALSE),IF('1.GHG Inventory Form'!$E$6="IPCC AR3 Report(2001)",VLOOKUP($J21,'6.GWP'!$B$1:$G$173,3,FALSE),IF('1.GHG Inventory Form'!$E$6="IPCC AR4 Report(2007)",VLOOKUP($J21,'6.GWP'!$B$1:$G$173,4,FALSE),IF('1.GHG Inventory Form'!$E$6="IPCC AR5 Report(2013)",VLOOKUP($J21,'6.GWP'!$B$1:$G$173,5,FALSE),IF('1.GHG Inventory Form'!$E$6="IPCC AR6 Report(2021)",VLOOKUP($J21,'6.GWP'!$B$2:$G$173,6,FALSE),0))))),IF(AND(AB21="V",$I21="自訂值"),IF('1.GHG Inventory Form'!$E$6="IPCC AR2 Report(1995)",VLOOKUP($K21,'6.GWP'!$B$1:$G$173,2,FALSE),IF('1.GHG Inventory Form'!$E$6="IPCC AR3 Report(2001)",VLOOKUP($K21,'6.GWP'!$B$1:$G$173,3,FALSE),IF('1.GHG Inventory Form'!$E$6="IPCC AR4 Report(2007)",VLOOKUP($K21,'6.GWP'!$B$1:$G$173,4,FALSE),IF('1.GHG Inventory Form'!$E$6="IPCC AR5 Report(2013)",VLOOKUP($K21,'6.GWP'!$B$1:$G$173,5,FALSE),IF('1.GHG Inventory Form'!$E$6="IPCC AR6 Report(2021)",VLOOKUP($K21,'6.GWP'!$B$2:$G$173,6,FALSE),0))))),0)),0) -> 0 | AR21: =IFERROR(IF(AND(AC21="V",$I21="預設值"),IF('1.GHG Inventory Form'!$E$6="IPCC AR2 Report(1995)",VLOOKUP($J21,'6.GWP'!$B$1:$G$173,2,FALSE),IF('1.GHG Inventory Form'!$E$6="IPCC AR3 Report(2001)",VLOOKUP($J21,'6.GWP'!$B$1:$G$173,3,FALSE),IF('1.GHG Inventory Form'!$E$6="IPCC AR4 Report(2007)",VLOOKUP($J21,'6.GWP'!$B$1:$G$173,4,FALSE),IF('1.GHG Inventory Form'!$E$6="IPCC AR5 Report(2013)",VLOOKUP($J21,'6.GWP'!$B$1:$G$173,5,FALSE),IF('1.GHG Inventory Form'!$E$6="IPCC AR6 Report(2021)",VLOOKUP($J21,'6.GWP'!$B$2:$G$173,6,FALSE),0))))),IF(AND(AC21="V",$I21="自訂值"),IF('1.GHG Inventory Form'!$E$6="IPCC AR2 Report(1995)",VLOOKUP($K21,'6.GWP'!$B$1:$G$173,2,FALSE),IF('1.GHG Inventory Form'!$E$6="IPCC AR3 Report(2001)",VLOOKUP($K21,'6.GWP'!$B$1:$G$173,3,FALSE),IF('1.GHG Inventory Form'!$E$6="IPCC AR4 Report(2007)",VLOOKUP($K21,'6.GWP'!$B$1:$G$173,4,FALSE),IF('1.GHG Inventory Form'!$E$6="IPCC AR5 Report(2013)",VLOOKUP($K21,'6.GWP'!$B$1:$G$173,5,FALSE),IF('1.GHG Inventory Form'!$E$6="IPCC AR6 Report(2021)",VLOOKUP($K21,'6.GWP'!$B$2:$G$173,6,FALSE),0))))),0)),0) -> 0 | AS21: =IF(AD21="V",IF('1.GHG Inventory Form'!$E$6="IPCC AR2 Report(1995)",'6.GWP'!$C$5,IF('1.GHG Inventory Form'!$E$6="IPCC AR3 Report(2001)",'6.GWP'!$D$5,IF('1.GHG Inventory Form'!$E$6="IPCC AR4 Report(2007)",'6.GWP'!$E$5,IF('1.GHG Inventory Form'!$E$6="IPCC AR5 Report(2013)",'6.GWP'!$F$5,IF('1.GHG Inventory Form'!$E$6="IPCC AR6 Report(2021)",'6.GWP'!$G$5,0))))),0) -> 0 | AT21: =IF(AE21="V",IF('1.GHG Inventory Form'!$E$6="IPCC AR2 Report(1995)",'6.GWP'!$C$4,IF('1.GHG Inventory Form'!$E$6="IPCC AR3 Report(2001)",'6.GWP'!$D$4,IF('1.GHG Inventory Form'!$E$6="IPCC AR4 Report(2007)",'6.GWP'!$E$4,IF('1.GHG Inventory Form'!$E$6="IPCC AR5 Report(2013)",'6.GWP'!$F$4,IF('1.GHG Inventory Form'!$E$6="IPCC AR6 Report(2021)",'6.GWP'!$G$4,0))))),0) -> 0 | AU21: =IFERROR($L21*AF21*AN21,"") | AV21: =IFERROR($L21*AG21*AO21,"") | AW21: =IFERROR($L21*AH21*AP21,"") | AX21: =IFERROR($L21*AI21*AQ21,"") | AY21: =IFERROR($L21*AJ21*AR21,"") | AZ21: =IFERROR($L21*AK21*AS21,"") | BA21: =IFERROR($L21*AL21*AT21,"") | BB21: =ROUND(SUM(AU21:BA21),4) -> 0 | BC21: =BB21/SUM($BB$16:$BB$99) -> 0 | BD21: =BB21/$BB$169 -> 0 | BI21: =IF(H21="","",IF(I21="預設值Default",H21&J21,IF(I21="自訂值Custom Value",H21&K21,""))) | BJ21: =IF(H21="其它設備，請說明","",IF(O21=0,"",O21)) | BK21: =IF(H21="","",IF(I21="預設值Default",AM21,IF(I21="自訂值Custom Value",X21,"")))
A22: 7 | I22: 預設值Default | M22: =IFERROR(IF(I22="預設值Default",VLOOKUP($J22,'4.Default Emission Factor'!$D:$V,16,FALSE),"請填寫自訂活動數據單位Please fill in Custom Unit"),"請選擇預設排放係數名稱Please Choose Default Fuel or Greenhouse Gas") -> 請選擇預設排放係數名稱Please Choose Default Fuel or Greenhouse Gas | Y22: =IF(AF22>0.0000000001,"V","") | Z22: =IF(AG22>0.0000000001,"V","") | AA22: =IF(AH22>0.0000000001,"V","") | AB22: =IF(AI22>0.0000000001,"V","") | AC22: =IF(AJ22>0.0000000001,"V","") | AD22: =IF(AK22>0.0000000001,"V","") | AE22: =IF(AL22>0.0000000001,"V","") | AF22: =IFERROR(IF($I22="預設值Default",ROUND(VLOOKUP($J22,'4.Default Emission Factor'!$D:$V,2,FALSE),10),IF($I22="自訂值Custom Value",P22,0)),0) -> 0 | AG22: =IFERROR(IF($I22="預設值Default",ROUND(VLOOKUP($J22,'4.Default Emission Factor'!$D:$V,4,FALSE),10),IF($I22="自訂值Custom Value",Q22,0)),0) -> 0 | AH22: =IFERROR(IF($I22="預設值Default",ROUND(VLOOKUP($J22,'4.Default Emission Factor'!$D:$V,6,FALSE),10),IF($I22="自訂值Custom Value",R22,0)),0) -> 0 | AI22: =IFERROR(IF($I22="預設值Default",ROUND(VLOOKUP($J22,'4.Default Emission Factor'!$D:$V,8,FALSE),10),IF($I22="自訂值Custom Value",S22,0)),0) -> 0 | AJ22: =IFERROR(IF($I22="預設值Default",ROUND(VLOOKUP($J22,'4.Default Emission Factor'!$D:$V,10,FALSE),10),IF($I22="自訂值Custom Value",T22,0)),0) -> 0 | AK22: =IFERROR(IF($I22="預設值Default",ROUND(VLOOKUP($J22,'4.Default Emission Factor'!$D:$V,12,FALSE),10),IF($I22="自訂值Custom Value",U22,0)),0) -> 0 | AL22: =IFERROR(IF($I22="預設值Default",ROUND(VLOOKUP($J22,'4.Default Emission Factor'!$D:$V,14,FALSE),10),IF($I22="自訂值Custom Value",V22,0)),0) -> 0 | AM22: =IFERROR(IF(I22="預設值Default",VLOOKUP($J22,'4.Default Emission Factor'!$D:$V,17,FALSE),IF(I22="自訂值Custom Value",X22,"")),"") | AN22: =IF(Y22="V",1,0) -> 0 | AO22: =IF(Z22="V",IF('1.GHG Inventory Form'!$E$6="IPCC AR2 Report(1995)",'6.GWP'!$C$2,IF('1.GHG Inventory Form'!$E$6="IPCC AR3 Report(2001)",'6.GWP'!$D$2,IF('1.GHG Inventory Form'!$E$6="IPCC AR4 Report(2007)",'6.GWP'!$E$2,IF('1.GHG Inventory Form'!$E$6="IPCC AR5 Report(2013)",'6.GWP'!$F$2,IF('1.GHG Inventory Form'!$E$6="IPCC AR6 Report(2021)",'6.GWP'!$G$2,0))))),0) -> 0 | AP22: =IF(AA22="V",IF('1.GHG Inventory Form'!$E$6="IPCC AR2 Report(1995)",'6.GWP'!$C$3,IF('1.GHG Inventory Form'!$E$6="IPCC AR3 Report(2001)",'6.GWP'!$D$3,IF('1.GHG Inventory Form'!$E$6="IPCC AR4 Report(2007)",'6.GWP'!$E$3,IF('1.GHG Inventory Form'!$E$6="IPCC AR5 Report(2013)",'6.GWP'!$F$3,IF('1.GHG Inventory Form'!$E$6="IPCC AR6 Report(2021)",'6.GWP'!$G$3,0))))),0) -> 0 | AQ22: =IFERROR(IF(AND(AB22="V",$I22="預設值"),IF('1.GHG Inventory Form'!$E$6="IPCC AR2 Report(1995)",VLOOKUP($J22,'6.GWP'!$B$1:$G$173,2,FALSE),IF('1.GHG Inventory Form'!$E$6="IPCC AR3 Report(2001)",VLOOKUP($J22,'6.GWP'!$B$1:$G$173,3,FALSE),IF('1.GHG Inventory Form'!$E$6="IPCC AR4 Report(2007)",VLOOKUP($J22,'6.GWP'!$B$1:$G$173,4,FALSE),IF('1.GHG Inventory Form'!$E$6="IPCC AR5 Report(2013)",VLOOKUP($J22,'6.GWP'!$B$1:$G$173,5,FALSE),IF('1.GHG Inventory Form'!$E$6="IPCC AR6 Report(2021)",VLOOKUP($J22,'6.GWP'!$B$2:$G$173,6,FALSE),0))))),IF(AND(AB22="V",$I22="自訂值"),IF('1.GHG Inventory Form'!$E$6="IPCC AR2 Report(1995)",VLOOKUP($K22,'6.GWP'!$B$1:$G$173,2,FALSE),IF('1.GHG Inventory Form'!$E$6="IPCC AR3 Report(2001)",VLOOKUP($K22,'6.GWP'!$B$1:$G$173,3,FALSE),IF('1.GHG Inventory Form'!$E$6="IPCC AR4 Report(2007)",VLOOKUP($K22,'6.GWP'!$B$1:$G$173,4,FALSE),IF('1.GHG Inventory Form'!$E$6="IPCC AR5 Report(2013)",VLOOKUP($K22,'6.GWP'!$B$1:$G$173,5,FALSE),IF('1.GHG Inventory Form'!$E$6="IPCC AR6 Report(2021)",VLOOKUP($K22,'6.GWP'!$B$2:$G$173,6,FALSE),0))))),0)),0) -> 0 | AR22: =IFERROR(IF(AND(AC22="V",$I22="預設值"),IF('1.GHG Inventory Form'!$E$6="IPCC AR2 Report(1995)",VLOOKUP($J22,'6.GWP'!$B$1:$G$173,2,FALSE),IF('1.GHG Inventory Form'!$E$6="IPCC AR3 Report(2001)",VLOOKUP($J22,'6.GWP'!$B$1:$G$173,3,FALSE),IF('1.GHG Inventory Form'!$E$6="IPCC AR4 Report(2007)",VLOOKUP($J22,'6.GWP'!$B$1:$G$173,4,FALSE),IF('1.GHG Inventory Form'!$E$6="IPCC AR5 Report(2013)",VLOOKUP($J22,'6.GWP'!$B$1:$G$173,5,FALSE),IF('1.GHG Inventory Form'!$E$6="IPCC AR6 Report(2021)",VLOOKUP($J22,'6.GWP'!$B$2:$G$173,6,FALSE),0))))),IF(AND(AC22="V",$I22="自訂值"),IF('1.GHG Inventory Form'!$E$6="IPCC AR2 Report(1995)",VLOOKUP($K22,'6.GWP'!$B$1:$G$173,2,FALSE),IF('1.GHG Inventory Form'!$E$6="IPCC AR3 Report(2001)",VLOOKUP($K22,'6.GWP'!$B$1:$G$173,3,FALSE),IF('1.GHG Inventory Form'!$E$6="IPCC AR4 Report(2007)",VLOOKUP($K22,'6.GWP'!$B$1:$G$173,4,FALSE),IF('1.GHG Inventory Form'!$E$6="IPCC AR5 Report(2013)",VLOOKUP($K22,'6.GWP'!$B$1:$G$173,5,FALSE),IF('1.GHG Inventory Form'!$E$6="IPCC AR6 Report(2021)",VLOOKUP($K22,'6.GWP'!$B$2:$G$173,6,FALSE),0))))),0)),0) -> 0 | AS22: =IF(AD22="V",IF('1.GHG Inventory Form'!$E$6="IPCC AR2 Report(1995)",'6.GWP'!$C$5,IF('1.GHG Inventory Form'!$E$6="IPCC AR3 Report(2001)",'6.GWP'!$D$5,IF('1.GHG Inventory Form'!$E$6="IPCC AR4 Report(2007)",'6.GWP'!$E$5,IF('1.GHG Inventory Form'!$E$6="IPCC AR5 Report(2013)",'6.GWP'!$F$5,IF('1.GHG Inventory Form'!$E$6="IPCC AR6 Report(2021)",'6.GWP'!$G$5,0))))),0) -> 0 | AT22: =IF(AE22="V",IF('1.GHG Inventory Form'!$E$6="IPCC AR2 Report(1995)",'6.GWP'!$C$4,IF('1.GHG Inventory Form'!$E$6="IPCC AR3 Report(2001)",'6.GWP'!$D$4,IF('1.GHG Inventory Form'!$E$6="IPCC AR4 Report(2007)",'6.GWP'!$E$4,IF('1.GHG Inventory Form'!$E$6="IPCC AR5 Report(2013)",'6.GWP'!$F$4,IF('1.GHG Inventory Form'!$E$6="IPCC AR6 Report(2021)",'6.GWP'!$G$4,0))))),0) -> 0 | AU22: =IFERROR($L22*AF22*AN22,"") | AV22: =IFERROR($L22*AG22*AO22,"") | AW22: =IFERROR($L22*AH22*AP22,"") | AX22: =IFERROR($L22*AI22*AQ22,"") | AY22: =IFERROR($L22*AJ22*AR22,"") | AZ22: =IFERROR($L22*AK22*AS22,"") | BA22: =IFERROR($L22*AL22*AT22,"") | BB22: =ROUND(SUM(AU22:BA22),4) -> 0 | BC22: =BB22/SUM($BB$16:$BB$99) -> 0 | BD22: =BB22/$BB$169 -> 0 | BI22: =IF(H22="","",IF(I22="預設值Default",H22&J22,IF(I22="自訂值Custom Value",H22&K22,""))) | BJ22: =IF(H22="其它設備，請說明","",IF(O22=0,"",O22)) | BK22: =IF(H22="","",IF(I22="預設值Default",AM22,IF(I22="自訂值Custom Value",X22,"")))
A23: 8 | I23: 預設值Default | M23: =IFERROR(IF(I23="預設值Default",VLOOKUP($J23,'4.Default Emission Factor'!$D:$V,16,FALSE),"請填寫自訂活動數據單位Please fill in Custom Unit"),"請選擇預設排放係數名稱Please Choose Default Fuel or Greenhouse Gas") -> 請選擇預設排放係數名稱Please Choose Default Fuel or Greenhouse Gas | Y23: =IF(AF23>0.0000000001,"V","") | Z23: =IF(AG23>0.0000000001,"V","") | AA23: =IF(AH23>0.0000000001,"V","") | AB23: =IF(AI23>0.0000000001,"V","") | AC23: =IF(AJ23>0.0000000001,"V","") | AD23: =IF(AK23>0.0000000001,"V","") | AE23: =IF(AL23>0.0000000001,"V","") | AF23: =IFERROR(IF($I23="預設值Default",ROUND(VLOOKUP($J23,'4.Default Emission Factor'!$D:$V,2,FALSE),10),IF($I23="自訂值Custom Value",P23,0)),0) -> 0 | AG23: =IFERROR(IF($I23="預設值Default",ROUND(VLOOKUP($J23,'4.Default Emission Factor'!$D:$V,4,FALSE),10),IF($I23="自訂值Custom Value",Q23,0)),0) -> 0 | AH23: =IFERROR(IF($I23="預設值Default",ROUND(VLOOKUP($J23,'4.Default Emission Factor'!$D:$V,6,FALSE),10),IF($I23="自訂值Custom Value",R23,0)),0) -> 0 | AI23: =IFERROR(IF($I23="預設值Default",ROUND(VLOOKUP($J23,'4.Default Emission Factor'!$D:$V,8,FALSE),10),IF($I23="自訂值Custom Value",S23,0)),0) -> 0 | AJ23: =IFERROR(IF($I23="預設值Default",ROUND(VLOOKUP($J23,'4.Default Emission Factor'!$D:$V,10,FALSE),10),IF($I23="自訂值Custom Value",T23,0)),0) -> 0 | AK23: =IFERROR(IF($I23="預設值Default",ROUND(VLOOKUP($J23,'4.Default Emission Factor'!$D:$V,12,FALSE),10),IF($I23="自訂值Custom Value",U23,0)),0) -> 0 | AL23: =IFERROR(IF($I23="預設值Default",ROUND(VLOOKUP($J23,'4.Default Emission Factor'!$D:$V,14,FALSE),10),IF($I23="自訂值Custom Value",V23,0)),0) -> 0 | AM23: =IFERROR(IF(I23="預設值Default",VLOOKUP($J23,'4.Default Emission Factor'!$D:$V,17,FALSE),IF(I23="自訂值Custom Value",X23,"")),"") | AN23: =IF(Y23="V",1,0) -> 0 | AO23: =IF(Z23="V",IF('1.GHG Inventory Form'!$E$6="IPCC AR2 Report(1995)",'6.GWP'!$C$2,IF('1.GHG Inventory Form'!$E$6="IPCC AR3 Report(2001)",'6.GWP'!$D$2,IF('1.GHG Inventory Form'!$E$6="IPCC AR4 Report(2007)",'6.GWP'!$E$2,IF('1.GHG Inventory Form'!$E$6="IPCC AR5 Report(2013)",'6.GWP'!$F$2,IF('1.GHG Inventory Form'!$E$6="IPCC AR6 Report(2021)",'6.GWP'!$G$2,0))))),0) -> 0 | AP23: =IF(AA23="V",IF('1.GHG Inventory Form'!$E$6="IPCC AR2 Report(1995)",'6.GWP'!$C$3,IF('1.GHG Inventory Form'!$E$6="IPCC AR3 Report(2001)",'6.GWP'!$D$3,IF('1.GHG Inventory Form'!$E$6="IPCC AR4 Report(2007)",'6.GWP'!$E$3,IF('1.GHG Inventory Form'!$E$6="IPCC AR5 Report(2013)",'6.GWP'!$F$3,IF('1.GHG Inventory Form'!$E$6="IPCC AR6 Report(2021)",'6.GWP'!$G$3,0))))),0) -> 0 | AQ23: =IFERROR(IF(AND(AB23="V",$I23="預設值"),IF('1.GHG Inventory Form'!$E$6="IPCC AR2 Report(1995)",VLOOKUP($J23,'6.GWP'!$B$1:$G$173,2,FALSE),IF('1.GHG Inventory Form'!$E$6="IPCC AR3 Report(2001)",VLOOKUP($J23,'6.GWP'!$B$1:$G$173,3,FALSE),IF('1.GHG Inventory Form'!$E$6="IPCC AR4 Report(2007)",VLOOKUP($J23,'6.GWP'!$B$1:$G$173,4,FALSE),IF('1.GHG Inventory Form'!$E$6="IPCC AR5 Report(2013)",VLOOKUP($J23,'6.GWP'!$B$1:$G$173,5,FALSE),IF('1.GHG Inventory Form'!$E$6="IPCC AR6 Report(2021)",VLOOKUP($J23,'6.GWP'!$B$2:$G$173,6,FALSE),0))))),IF(AND(AB23="V",$I23="自訂值"),IF('1.GHG Inventory Form'!$E$6="IPCC AR2 Report(1995)",VLOOKUP($K23,'6.GWP'!$B$1:$G$173,2,FALSE),IF('1.GHG Inventory Form'!$E$6="IPCC AR3 Report(2001)",VLOOKUP($K23,'6.GWP'!$B$1:$G$173,3,FALSE),IF('1.GHG Inventory Form'!$E$6="IPCC AR4 Report(2007)",VLOOKUP($K23,'6.GWP'!$B$1:$G$173,4,FALSE),IF('1.GHG Inventory Form'!$E$6="IPCC AR5 Report(2013)",VLOOKUP($K23,'6.GWP'!$B$1:$G$173,5,FALSE),IF('1.GHG Inventory Form'!$E$6="IPCC AR6 Report(2021)",VLOOKUP($K23,'6.GWP'!$B$2:$G$173,6,FALSE),0))))),0)),0) -> 0 | AR23: =IFERROR(IF(AND(AC23="V",$I23="預設值"),IF('1.GHG Inventory Form'!$E$6="IPCC AR2 Report(1995)",VLOOKUP($J23,'6.GWP'!$B$1:$G$173,2,FALSE),IF('1.GHG Inventory Form'!$E$6="IPCC AR3 Report(2001)",VLOOKUP($J23,'6.GWP'!$B$1:$G$173,3,FALSE),IF('1.GHG Inventory Form'!$E$6="IPCC AR4 Report(2007)",VLOOKUP($J23,'6.GWP'!$B$1:$G$173,4,FALSE),IF('1.GHG Inventory Form'!$E$6="IPCC AR5 Report(2013)",VLOOKUP($J23,'6.GWP'!$B$1:$G$173,5,FALSE),IF('1.GHG Inventory Form'!$E$6="IPCC AR6 Report(2021)",VLOOKUP($J23,'6.GWP'!$B$2:$G$173,6,FALSE),0))))),IF(AND(AC23="V",$I23="自訂值"),IF('1.GHG Inventory Form'!$E$6="IPCC AR2 Report(1995)",VLOOKUP($K23,'6.GWP'!$B$1:$G$173,2,FALSE),IF('1.GHG Inventory Form'!$E$6="IPCC AR3 Report(2001)",VLOOKUP($K23,'6.GWP'!$B$1:$G$173,3,FALSE),IF('1.GHG Inventory Form'!$E$6="IPCC AR4 Report(2007)",VLOOKUP($K23,'6.GWP'!$B$1:$G$173,4,FALSE),IF('1.GHG Inventory Form'!$E$6="IPCC AR5 Report(2013)",VLOOKUP($K23,'6.GWP'!$B$1:$G$173,5,FALSE),IF('1.GHG Inventory Form'!$E$6="IPCC AR6 Report(2021)",VLOOKUP($K23,'6.GWP'!$B$2:$G$173,6,FALSE),0))))),0)),0) -> 0 | AS23: =IF(AD23="V",IF('1.GHG Inventory Form'!$E$6="IPCC AR2 Report(1995)",'6.GWP'!$C$5,IF('1.GHG Inventory Form'!$E$6="IPCC AR3 Report(2001)",'6.GWP'!$D$5,IF('1.GHG Inventory Form'!$E$6="IPCC AR4 Report(2007)",'6.GWP'!$E$5,IF('1.GHG Inventory Form'!$E$6="IPCC AR5 Report(2013)",'6.GWP'!$F$5,IF('1.GHG Inventory Form'!$E$6="IPCC AR6 Report(2021)",'6.GWP'!$G$5,0))))),0) -> 0 | AT23: =IF(AE23="V",IF('1.GHG Inventory Form'!$E$6="IPCC AR2 Report(1995)",'6.GWP'!$C$4,IF('1.GHG Inventory Form'!$E$6="IPCC AR3 Report(2001)",'6.GWP'!$D$4,IF('1.GHG Inventory Form'!$E$6="IPCC AR4 Report(2007)",'6.GWP'!$E$4,IF('1.GHG Inventory Form'!$E$6="IPCC AR5 Report(2013)",'6.GWP'!$F$4,IF('1.GHG Inventory Form'!$E$6="IPCC AR6 Report(2021)",'6.GWP'!$G$4,0))))),0) -> 0 | AU23: =IFERROR($L23*AF23*AN23,"") | AV23: =IFERROR($L23*AG23*AO23,"") | AW23: =IFERROR($L23*AH23*AP23,"") | AX23: =IFERROR($L23*AI23*AQ23,"") | AY23: =IFERROR($L23*AJ23*AR23,"") | AZ23: =IFERROR($L23*AK23*AS23,"") | BA23: =IFERROR($L23*AL23*AT23,"") | BB23: =ROUND(SUM(AU23:BA23),4) -> 0 | BC23: =BB23/SUM($BB$16:$BB$99) -> 0 | BD23: =BB23/$BB$169 -> 0 | BI23: =IF(H23="","",IF(I23="預設值Default",H23&J23,IF(I23="自訂值Custom Value",H23&K23,""))) | BJ23: =IF(H23="其它設備，請說明","",IF(O23=0,"",O23)) | BK23: =IF(H23="","",IF(I23="預設值Default",AM23,IF(I23="自訂值Custom Value",X23,"")))
A24: 9 | I24: 預設值Default | M24: =IFERROR(IF(I24="預設值Default",VLOOKUP($J24,'4.Default Emission Factor'!$D:$V,16,FALSE),"請填寫自訂活動數據單位Please fill in Custom Unit"),"請選擇預設排放係數名稱Please Choose Default Fuel or Greenhouse Gas") -> 請選擇預設排放係數名稱Please Choose Default Fuel or Greenhouse Gas | Y24: =IF(AF24>0.0000000001,"V","") | Z24: =IF(AG24>0.0000000001,"V","") | AA24: =IF(AH24>0.0000000001,"V","") | AB24: =IF(AI24>0.0000000001,"V","") | AC24: =IF(AJ24>0.0000000001,"V","") | AD24: =IF(AK24>0.0000000001,"V","") | AE24: =IF(AL24>0.0000000001,"V","") | AF24: =IFERROR(IF($I24="預設值Default",ROUND(VLOOKUP($J24,'4.Default Emission Factor'!$D:$V,2,FALSE),10),IF($I24="自訂值Custom Value",P24,0)),0) -> 0 | AG24: =IFERROR(IF($I24="預設值Default",ROUND(VLOOKUP($J24,'4.Default Emission Factor'!$D:$V,4,FALSE),10),IF($I24="自訂值Custom Value",Q24,0)),0) -> 0 | AH24: =IFERROR(IF($I24="預設值Default",ROUND(VLOOKUP($J24,'4.Default Emission Factor'!$D:$V,6,FALSE),10),IF($I24="自訂值Custom Value",R24,0)),0) -> 0 | AI24: =IFERROR(IF($I24="預設值Default",ROUND(VLOOKUP($J24,'4.Default Emission Factor'!$D:$V,8,FALSE),10),IF($I24="自訂值Custom Value",S24,0)),0) -> 0 | AJ24: =IFERROR(IF($I24="預設值Default",ROUND(VLOOKUP($J24,'4.Default Emission Factor'!$D:$V,10,FALSE),10),IF($I24="自訂值Custom Value",T24,0)),0) -> 0 | AK24: =IFERROR(IF($I24="預設值Default",ROUND(VLOOKUP($J24,'4.Default Emission Factor'!$D:$V,12,FALSE),10),IF($I24="自訂值Custom Value",U24,0)),0) -> 0 | AL24: =IFERROR(IF($I24="預設值Default",ROUND(VLOOKUP($J24,'4.Default Emission Factor'!$D:$V,14,FALSE),10),IF($I24="自訂值Custom Value",V24,0)),0) -> 0 | AM24: =IFERROR(IF(I24="預設值Default",VLOOKUP($J24,'4.Default Emission Factor'!$D:$V,17,FALSE),IF(I24="自訂值Custom Value",X24,"")),"") | AN24: =IF(Y24="V",1,0) -> 0 | AO24: =IF(Z24="V",IF('1.GHG Inventory Form'!$E$6="IPCC AR2 Report(1995)",'6.GWP'!$C$2,IF('1.GHG Inventory Form'!$E$6="IPCC AR3 Report(2001)",'6.GWP'!$D$2,IF('1.GHG Inventory Form'!$E$6="IPCC AR4 Report(2007)",'6.GWP'!$E$2,IF('1.GHG Inventory Form'!$E$6="IPCC AR5 Report(2013)",'6.GWP'!$F$2,IF('1.GHG Inventory Form'!$E$6="IPCC AR6 Report(2021)",'6.GWP'!$G$2,0))))),0) -> 0 | AP24: =IF(AA24="V",IF('1.GHG Inventory Form'!$E$6="IPCC AR2 Report(1995)",'6.GWP'!$C$3,IF('1.GHG Inventory Form'!$E$6="IPCC AR3 Report(2001)",'6.GWP'!$D$3,IF('1.GHG Inventory Form'!$E$6="IPCC AR4 Report(2007)",'6.GWP'!$E$3,IF('1.GHG Inventory Form'!$E$6="IPCC AR5 Report(2013)",'6.GWP'!$F$3,IF('1.GHG Inventory Form'!$E$6="IPCC AR6 Report(2021)",'6.GWP'!$G$3,0))))),0) -> 0 | AQ24: =IFERROR(IF(AND(AB24="V",$I24="預設值"),IF('1.GHG Inventory Form'!$E$6="IPCC AR2 Report(1995)",VLOOKUP($J24,'6.GWP'!$B$1:$G$173,2,FALSE),IF('1.GHG Inventory Form'!$E$6="IPCC AR3 Report(2001)",VLOOKUP($J24,'6.GWP'!$B$1:$G$173,3,FALSE),IF('1.GHG Inventory Form'!$E$6="IPCC AR4 Report(2007)",VLOOKUP($J24,'6.GWP'!$B$1:$G$173,4,FALSE),IF('1.GHG Inventory Form'!$E$6="IPCC AR5 Report(2013)",VLOOKUP($J24,'6.GWP'!$B$1:$G$173,5,FALSE),IF('1.GHG Inventory Form'!$E$6="IPCC AR6 Report(2021)",VLOOKUP($J24,'6.GWP'!$B$2:$G$173,6,FALSE),0))))),IF(AND(AB24="V",$I24="自訂值"),IF('1.GHG Inventory Form'!$E$6="IPCC AR2 Report(1995)",VLOOKUP($K24,'6.GWP'!$B$1:$G$173,2,FALSE),IF('1.GHG Inventory Form'!$E$6="IPCC AR3 Report(2001)",VLOOKUP($K24,'6.GWP'!$B$1:$G$173,3,FALSE),IF('1.GHG Inventory Form'!$E$6="IPCC AR4 Report(2007)",VLOOKUP($K24,'6.GWP'!$B$1:$G$173,4,FALSE),IF('1.GHG Inventory Form'!$E$6="IPCC AR5 Report(2013)",VLOOKUP($K24,'6.GWP'!$B$1:$G$173,5,FALSE),IF('1.GHG Inventory Form'!$E$6="IPCC AR6 Report(2021)",VLOOKUP($K24,'6.GWP'!$B$2:$G$173,6,FALSE),0))))),0)),0) -> 0 | AR24: =IFERROR(IF(AND(AC24="V",$I24="預設值"),IF('1.GHG Inventory Form'!$E$6="IPCC AR2 Report(1995)",VLOOKUP($J24,'6.GWP'!$B$1:$G$173,2,FALSE),IF('1.GHG Inventory Form'!$E$6="IPCC AR3 Report(2001)",VLOOKUP($J24,'6.GWP'!$B$1:$G$173,3,FALSE),IF('1.GHG Inventory Form'!$E$6="IPCC AR4 Report(2007)",VLOOKUP($J24,'6.GWP'!$B$1:$G$173,4,FALSE),IF('1.GHG Inventory Form'!$E$6="IPCC AR5 Report(2013)",VLOOKUP($J24,'6.GWP'!$B$1:$G$173,5,FALSE),IF('1.GHG Inventory Form'!$E$6="IPCC AR6 Report(2021)",VLOOKUP($J24,'6.GWP'!$B$2:$G$173,6,FALSE),0))))),IF(AND(AC24="V",$I24="自訂值"),IF('1.GHG Inventory Form'!$E$6="IPCC AR2 Report(1995)",VLOOKUP($K24,'6.GWP'!$B$1:$G$173,2,FALSE),IF('1.GHG Inventory Form'!$E$6="IPCC AR3 Report(2001)",VLOOKUP($K24,'6.GWP'!$B$1:$G$173,3,FALSE),IF('1.GHG Inventory Form'!$E$6="IPCC AR4 Report(2007)",VLOOKUP($K24,'6.GWP'!$B$1:$G$173,4,FALSE),IF('1.GHG Inventory Form'!$E$6="IPCC AR5 Report(2013)",VLOOKUP($K24,'6.GWP'!$B$1:$G$173,5,FALSE),IF('1.GHG Inventory Form'!$E$6="IPCC AR6 Report(2021)",VLOOKUP($K24,'6.GWP'!$B$2:$G$173,6,FALSE),0))))),0)),0) -> 0 | AS24: =IF(AD24="V",IF('1.GHG Inventory Form'!$E$6="IPCC AR2 Report(1995)",'6.GWP'!$C$5,IF('1.GHG Inventory Form'!$E$6="IPCC AR3 Report(2001)",'6.GWP'!$D$5,IF('1.GHG Inventory Form'!$E$6="IPCC AR4 Report(2007)",'6.GWP'!$E$5,IF('1.GHG Inventory Form'!$E$6="IPCC AR5 Report(2013)",'6.GWP'!$F$5,IF('1.GHG Inventory Form'!$E$6="IPCC AR6 Report(2021)",'6.GWP'!$G$5,0))))),0) -> 0 | AT24: =IF(AE24="V",IF('1.GHG Inventory Form'!$E$6="IPCC AR2 Report(1995)",'6.GWP'!$C$4,IF('1.GHG Inventory Form'!$E$6="IPCC AR3 Report(2001)",'6.GWP'!$D$4,IF('1.GHG Inventory Form'!$E$6="IPCC AR4 Report(2007)",'6.GWP'!$E$4,IF('1.GHG Inventory Form'!$E$6="IPCC AR5 Report(2013)",'6.GWP'!$F$4,IF('1.GHG Inventory Form'!$E$6="IPCC AR6 Report(2021)",'6.GWP'!$G$4,0))))),0) -> 0 | AU24: =IFERROR($L24*AF24*AN24,"") | AV24: =IFERROR($L24*AG24*AO24,"") | AW24: =IFERROR($L24*AH24*AP24,"") | AX24: =IFERROR($L24*AI24*AQ24,"") | AY24: =IFERROR($L24*AJ24*AR24,"") | AZ24: =IFERROR($L24*AK24*AS24,"") | BA24: =IFERROR($L24*AL24*AT24,"") | BB24: =ROUND(SUM(AU24:BA24),4) -> 0 | BC24: =BB24/SUM($BB$16:$BB$99) -> 0 | BD24: =BB24/$BB$169 -> 0 | BI24: =IF(H24="","",IF(I24="預設值Default",H24&J24,IF(I24="自訂值Custom Value",H24&K24,""))) | BJ24: =IF(H24="其它設備，請說明","",IF(O24=0,"",O24)) | BK24: =IF(H24="","",IF(I24="預設值Default",AM24,IF(I24="自訂值Custom Value",X24,"")))
A25: 10 | I25: 預設值Default | M25: =IFERROR(IF(I25="預設值Default",VLOOKUP($J25,'4.Default Emission Factor'!$D:$V,16,FALSE),"請填寫自訂活動數據單位Please fill in Custom Unit"),"請選擇預設排放係數名稱Please Choose Default Fuel or Greenhouse Gas") -> 請選擇預設排放係數名稱Please Choose Default Fuel or Greenhouse Gas | Y25: =IF(AF25>0.0000000001,"V","") | Z25: =IF(AG25>0.0000000001,"V","") | AA25: =IF(AH25>0.0000000001,"V","") | AB25: =IF(AI25>0.0000000001,"V","") | AC25: =IF(AJ25>0.0000000001,"V","") | AD25: =IF(AK25>0.0000000001,"V","") | AE25: =IF(AL25>0.0000000001,"V","") | AF25: =IFERROR(IF($I25="預設值Default",ROUND(VLOOKUP($J25,'4.Default Emission Factor'!$D:$V,2,FALSE),10),IF($I25="自訂值Custom Value",P25,0)),0) -> 0 | AG25: =IFERROR(IF($I25="預設值Default",ROUND(VLOOKUP($J25,'4.Default Emission Factor'!$D:$V,4,FALSE),10),IF($I25="自訂值Custom Value",Q25,0)),0) -> 0 | AH25: =IFERROR(IF($I25="預設值Default",ROUND(VLOOKUP($J25,'4.Default Emission Factor'!$D:$V,6,FALSE),10),IF($I25="自訂值Custom Value",R25,0)),0) -> 0 | AI25: =IFERROR(IF($I25="預設值Default",ROUND(VLOOKUP($J25,'4.Default Emission Factor'!$D:$V,8,FALSE),10),IF($I25="自訂值Custom Value",S25,0)),0) -> 0 | AJ25: =IFERROR(IF($I25="預設值Default",ROUND(VLOOKUP($J25,'4.Default Emission Factor'!$D:$V,10,FALSE),10),IF($I25="自訂值Custom Value",T25,0)),0) -> 0 | AK25: =IFERROR(IF($I25="預設值Default",ROUND(VLOOKUP($J25,'4.Default Emission Factor'!$D:$V,12,FALSE),10),IF($I25="自訂值Custom Value",U25,0)),0) -> 0 | AL25: =IFERROR(IF($I25="預設值Default",ROUND(VLOOKUP($J25,'4.Default Emission Factor'!$D:$V,14,FALSE),10),IF($I25="自訂值Custom Value",V25,0)),0) -> 0 | AM25: =IFERROR(IF(I25="預設值Default",VLOOKUP($J25,'4.Default Emission Factor'!$D:$V,17,FALSE),IF(I25="自訂值Custom Value",X25,"")),"") | AN25: =IF(Y25="V",1,0) -> 0 | AO25: =IF(Z25="V",IF('1.GHG Inventory Form'!$E$6="IPCC AR2 Report(1995)",'6.GWP'!$C$2,IF('1.GHG Inventory Form'!$E$6="IPCC AR3 Report(2001)",'6.GWP'!$D$2,IF('1.GHG Inventory Form'!$E$6="IPCC AR4 Report(2007)",'6.GWP'!$E$2,IF('1.GHG Inventory Form'!$E$6="IPCC AR5 Report(2013)",'6.GWP'!$F$2,IF('1.GHG Inventory Form'!$E$6="IPCC AR6 Report(2021)",'6.GWP'!$G$2,0))))),0) -> 0 | AP25: =IF(AA25="V",IF('1.GHG Inventory Form'!$E$6="IPCC AR2 Report(1995)",'6.GWP'!$C$3,IF('1.GHG Inventory Form'!$E$6="IPCC AR3 Report(2001)",'6.GWP'!$D$3,IF('1.GHG Inventory Form'!$E$6="IPCC AR4 Report(2007)",'6.GWP'!$E$3,IF('1.GHG Inventory Form'!$E$6="IPCC AR5 Report(2013)",'6.GWP'!$F$3,IF('1.GHG Inventory Form'!$E$6="IPCC AR6 Report(2021)",'6.GWP'!$G$3,0))))),0) -> 0 | AQ25: =IFERROR(IF(AND(AB25="V",$I25="預設值"),IF('1.GHG Inventory Form'!$E$6="IPCC AR2 Report(1995)",VLOOKUP($J25,'6.GWP'!$B$1:$G$173,2,FALSE),IF('1.GHG Inventory Form'!$E$6="IPCC AR3 Report(2001)",VLOOKUP($J25,'6.GWP'!$B$1:$G$173,3,FALSE),IF('1.GHG Inventory Form'!$E$6="IPCC AR4 Report(2007)",VLOOKUP($J25,'6.GWP'!$B$1:$G$173,4,FALSE),IF('1.GHG Inventory Form'!$E$6="IPCC AR5 Report(2013)",VLOOKUP($J25,'6.GWP'!$B$1:$G$173,5,FALSE),IF('1.GHG Inventory Form'!$E$6="IPCC AR6 Report(2021)",VLOOKUP($J25,'6.GWP'!$B$2:$G$173,6,FALSE),0))))),IF(AND(AB25="V",$I25="自訂值"),IF('1.GHG Inventory Form'!$E$6="IPCC AR2 Report(1995)",VLOOKUP($K25,'6.GWP'!$B$1:$G$173,2,FALSE),IF('1.GHG Inventory Form'!$E$6="IPCC AR3 Report(2001)",VLOOKUP($K25,'6.GWP'!$B$1:$G$173,3,FALSE),IF('1.GHG Inventory Form'!$E$6="IPCC AR4 Report(2007)",VLOOKUP($K25,'6.GWP'!$B$1:$G$173,4,FALSE),IF('1.GHG Inventory Form'!$E$6="IPCC AR5 Report(2013)",VLOOKUP($K25,'6.GWP'!$B$1:$G$173,5,FALSE),IF('1.GHG Inventory Form'!$E$6="IPCC AR6 Report(2021)",VLOOKUP($K25,'6.GWP'!$B$2:$G$173,6,FALSE),0))))),0)),0) -> 0 | AR25: =IFERROR(IF(AND(AC25="V",$I25="預設值"),IF('1.GHG Inventory Form'!$E$6="IPCC AR2 Report(1995)",VLOOKUP($J25,'6.GWP'!$B$1:$G$173,2,FALSE),IF('1.GHG Inventory Form'!$E$6="IPCC AR3 Report(2001)",VLOOKUP($J25,'6.GWP'!$B$1:$G$173,3,FALSE),IF('1.GHG Inventory Form'!$E$6="IPCC AR4 Report(2007)",VLOOKUP($J25,'6.GWP'!$B$1:$G$173,4,FALSE),IF('1.GHG Inventory Form'!$E$6="IPCC AR5 Report(2013)",VLOOKUP($J25,'6.GWP'!$B$1:$G$173,5,FALSE),IF('1.GHG Inventory Form'!$E$6="IPCC AR6 Report(2021)",VLOOKUP($J25,'6.GWP'!$B$2:$G$173,6,FALSE),0))))),IF(AND(AC25="V",$I25="自訂值"),IF('1.GHG Inventory Form'!$E$6="IPCC AR2 Report(1995)",VLOOKUP($K25,'6.GWP'!$B$1:$G$173,2,FALSE),IF('1.GHG Inventory Form'!$E$6="IPCC AR3 Report(2001)",VLOOKUP($K25,'6.GWP'!$B$1:$G$173,3,FALSE),IF('1.GHG Inventory Form'!$E$6="IPCC AR4 Report(2007)",VLOOKUP($K25,'6.GWP'!$B$1:$G$173,4,FALSE),IF('1.GHG Inventory Form'!$E$6="IPCC AR5 Report(2013)",VLOOKUP($K25,'6.GWP'!$B$1:$G$173,5,FALSE),IF('1.GHG Inventory Form'!$E$6="IPCC AR6 Report(2021)",VLOOKUP($K25,'6.GWP'!$B$2:$G$173,6,FALSE),0))))),0)),0) -> 0 | AS25: =IF(AD25="V",IF('1.GHG Inventory Form'!$E$6="IPCC AR2 Report(1995)",'6.GWP'!$C$5,IF('1.GHG Inventory Form'!$E$6="IPCC AR3 Report(2001)",'6.GWP'!$D$5,IF('1.GHG Inventory Form'!$E$6="IPCC AR4 Report(2007)",'6.GWP'!$E$5,IF('1.GHG Inventory Form'!$E$6="IPCC AR5 Report(2013)",'6.GWP'!$F$5,IF('1.GHG Inventory Form'!$E$6="IPCC AR6 Report(2021)",'6.GWP'!$G$5,0))))),0) -> 0 | AT25: =IF(AE25="V",IF('1.GHG Inventory Form'!$E$6="IPCC AR2 Report(1995)",'6.GWP'!$C$4,IF('1.GHG Inventory Form'!$E$6="IPCC AR3 Report(2001)",'6.GWP'!$D$4,IF('1.GHG Inventory Form'!$E$6="IPCC AR4 Report(2007)",'6.GWP'!$E$4,IF('1.GHG Inventory Form'!$E$6="IPCC AR5 Report(2013)",'6.GWP'!$F$4,IF('1.GHG Inventory Form'!$E$6="IPCC AR6 Report(2021)",'6.GWP'!$G$4,0))))),0) -> 0 | AU25: =IFERROR($L25*AF25*AN25,"") | AV25: =IFERROR($L25*AG25*AO25,"") | AW25: =IFERROR($L25*AH25*AP25,"") | AX25: =IFERROR($L25*AI25*AQ25,"") | AY25: =IFERROR($L25*AJ25*AR25,"") | AZ25: =IFERROR($L25*AK25*AS25,"") | BA25: =IFERROR($L25*AL25*AT25,"") | BB25: =ROUND(SUM(AU25:BA25),4) -> 0 | BC25: =BB25/SUM($BB$16:$BB$99) -> 0 | BD25: =BB25/$BB$169 -> 0 | BI25: =IF(H25="","",IF(I25="預設值Default",H25&J25,IF(I25="自訂值Custom Value",H25&K25,""))) | BJ25: =IF(H25="其它設備，請說明","",IF(O25=0,"",O25)) | BK25: =IF(H25="","",IF(I25="預設值Default",AM25,IF(I25="自訂值Custom Value",X25,"")))
A26: 11 | I26: 預設值Default | M26: =IFERROR(IF(I26="預設值Default",VLOOKUP($J26,'4.Default Emission Factor'!$D:$V,16,FALSE),"請填寫自訂活動數據單位Please fill in Custom Unit"),"請選擇預設排放係數名稱Please Choose Default Fuel or Greenhouse Gas") -> 請選擇預設排放係數名稱Please Choose Default Fuel or Greenhouse Gas | Y26: =IF(AF26>0.0000000001,"V","") | Z26: =IF(AG26>0.0000000001,"V","") | AA26: =IF(AH26>0.0000000001,"V","") | AB26: =IF(AI26>0.0000000001,"V","") | AC26: =IF(AJ26>0.0000000001,"V","") | AD26: =IF(AK26>0.0000000001,"V","") | AE26: =IF(AL26>0.0000000001,"V","") | AF26: =IFERROR(IF($I26="預設值Default",ROUND(VLOOKUP($J26,'4.Default Emission Factor'!$D:$V,2,FALSE),10),IF($I26="自訂值Custom Value",P26,0)),0) -> 0 | AG26: =IFERROR(IF($I26="預設值Default",ROUND(VLOOKUP($J26,'4.Default Emission Factor'!$D:$V,4,FALSE),10),IF($I26="自訂值Custom Value",Q26,0)),0) -> 0 | AH26: =IFERROR(IF($I26="預設值Default",ROUND(VLOOKUP($J26,'4.Default Emission Factor'!$D:$V,6,FALSE),10),IF($I26="自訂值Custom Value",R26,0)),0) -> 0 | AI26: =IFERROR(IF($I26="預設值Default",ROUND(VLOOKUP($J26,'4.Default Emission Factor'!$D:$V,8,FALSE),10),IF($I26="自訂值Custom Value",S26,0)),0) -> 0 | AJ26: =IFERROR(IF($I26="預設值Default",ROUND(VLOOKUP($J26,'4.Default Emission Factor'!$D:$V,10,FALSE),10),IF($I26="自訂值Custom Value",T26,0)),0) -> 0 | AK26: =IFERROR(IF($I26="預設值Default",ROUND(VLOOKUP($J26,'4.Default Emission Factor'!$D:$V,12,FALSE),10),IF($I26="自訂值Custom Value",U26,0)),0) -> 0 | AL26: =IFERROR(IF($I26="預設值Default",ROUND(VLOOKUP($J26,'4.Default Emission Factor'!$D:$V,14,FALSE),10),IF($I26="自訂值Custom Value",V26,0)),0) -> 0 | AM26: =IFERROR(IF(I26="預設值Default",VLOOKUP($J26,'4.Default Emission Factor'!$D:$V,17,FALSE),IF(I26="自訂值Custom Value",X26,"")),"") | AN26: =IF(Y26="V",1,0) -> 0 | AO26: =IF(Z26="V",IF('1.GHG Inventory Form'!$E$6="IPCC AR2 Report(1995)",'6.GWP'!$C$2,IF('1.GHG Inventory Form'!$E$6="IPCC AR3 Report(2001)",'6.GWP'!$D$2,IF('1.GHG Inventory Form'!$E$6="IPCC AR4 Report(2007)",'6.GWP'!$E$2,IF('1.GHG Inventory Form'!$E$6="IPCC AR5 Report(2013)",'6.GWP'!$F$2,IF('1.GHG Inventory Form'!$E$6="IPCC AR6 Report(2021)",'6.GWP'!$G$2,0))))),0) -> 0 | AP26: =IF(AA26="V",IF('1.GHG Inventory Form'!$E$6="IPCC AR2 Report(1995)",'6.GWP'!$C$3,IF('1.GHG Inventory Form'!$E$6="IPCC AR3 Report(2001)",'6.GWP'!$D$3,IF('1.GHG Inventory Form'!$E$6="IPCC AR4 Report(2007)",'6.GWP'!$E$3,IF('1.GHG Inventory Form'!$E$6="IPCC AR5 Report(2013)",'6.GWP'!$F$3,IF('1.GHG Inventory Form'!$E$6="IPCC AR6 Report(2021)",'6.GWP'!$G$3,0))))),0) -> 0 | AQ26: =IFERROR(IF(AND(AB26="V",$I26="預設值"),IF('1.GHG Inventory Form'!$E$6="IPCC AR2 Report(1995)",VLOOKUP($J26,'6.GWP'!$B$1:$G$173,2,FALSE),IF('1.GHG Inventory Form'!$E$6="IPCC AR3 Report(2001)",VLOOKUP($J26,'6.GWP'!$B$1:$G$173,3,FALSE),IF('1.GHG Inventory Form'!$E$6="IPCC AR4 Report(2007)",VLOOKUP($J26,'6.GWP'!$B$1:$G$173,4,FALSE),IF('1.GHG Inventory Form'!$E$6="IPCC AR5 Report(2013)",VLOOKUP($J26,'6.GWP'!$B$1:$G$173,5,FALSE),IF('1.GHG Inventory Form'!$E$6="IPCC AR6 Report(2021)",VLOOKUP($J26,'6.GWP'!$B$2:$G$173,6,FALSE),0))))),IF(AND(AB26="V",$I26="自訂值"),IF('1.GHG Inventory Form'!$E$6="IPCC AR2 Report(1995)",VLOOKUP($K26,'6.GWP'!$B$1:$G$173,2,FALSE),IF('1.GHG Inventory Form'!$E$6="IPCC AR3 Report(2001)",VLOOKUP($K26,'6.GWP'!$B$1:$G$173,3,FALSE),IF('1.GHG Inventory Form'!$E$6="IPCC AR4 Report(2007)",VLOOKUP($K26,'6.GWP'!$B$1:$G$173,4,FALSE),IF('1.GHG Inventory Form'!$E$6="IPCC AR5 Report(2013)",VLOOKUP($K26,'6.GWP'!$B$1:$G$173,5,FALSE),IF('1.GHG Inventory Form'!$E$6="IPCC AR6 Report(2021)",VLOOKUP($K26,'6.GWP'!$B$2:$G$173,6,FALSE),0))))),0)),0) -> 0 | AR26: =IFERROR(IF(AND(AC26="V",$I26="預設值"),IF('1.GHG Inventory Form'!$E$6="IPCC AR2 Report(1995)",VLOOKUP($J26,'6.GWP'!$B$1:$G$173,2,FALSE),IF('1.GHG Inventory Form'!$E$6="IPCC AR3 Report(2001)",VLOOKUP($J26,'6.GWP'!$B$1:$G$173,3,FALSE),IF('1.GHG Inventory Form'!$E$6="IPCC AR4 Report(2007)",VLOOKUP($J26,'6.GWP'!$B$1:$G$173,4,FALSE),IF('1.GHG Inventory Form'!$E$6="IPCC AR5 Report(2013)",VLOOKUP($J26,'6.GWP'!$B$1:$G$173,5,FALSE),IF('1.GHG Inventory Form'!$E$6="IPCC AR6 Report(2021)",VLOOKUP($J26,'6.GWP'!$B$2:$G$173,6,FALSE),0))))),IF(AND(AC26="V",$I26="自訂值"),IF('1.GHG Inventory Form'!$E$6="IPCC AR2 Report(1995)",VLOOKUP($K26,'6.GWP'!$B$1:$G$173,2,FALSE),IF('1.GHG Inventory Form'!$E$6="IPCC AR3 Report(2001)",VLOOKUP($K26,'6.GWP'!$B$1:$G$173,3,FALSE),IF('1.GHG Inventory Form'!$E$6="IPCC AR4 Report(2007)",VLOOKUP($K26,'6.GWP'!$B$1:$G$173,4,FALSE),IF('1.GHG Inventory Form'!$E$6="IPCC AR5 Report(2013)",VLOOKUP($K26,'6.GWP'!$B$1:$G$173,5,FALSE),IF('1.GHG Inventory Form'!$E$6="IPCC AR6 Report(2021)",VLOOKUP($K26,'6.GWP'!$B$2:$G$173,6,FALSE),0))))),0)),0) -> 0 | AS26: =IF(AD26="V",IF('1.GHG Inventory Form'!$E$6="IPCC AR2 Report(1995)",'6.GWP'!$C$5,IF('1.GHG Inventory Form'!$E$6="IPCC AR3 Report(2001)",'6.GWP'!$D$5,IF('1.GHG Inventory Form'!$E$6="IPCC AR4 Report(2007)",'6.GWP'!$E$5,IF('1.GHG Inventory Form'!$E$6="IPCC AR5 Report(2013)",'6.GWP'!$F$5,IF('1.GHG Inventory Form'!$E$6="IPCC AR6 Report(2021)",'6.GWP'!$G$5,0))))),0) -> 0 | AT26: =IF(AE26="V",IF('1.GHG Inventory Form'!$E$6="IPCC AR2 Report(1995)",'6.GWP'!$C$4,IF('1.GHG Inventory Form'!$E$6="IPCC AR3 Report(2001)",'6.GWP'!$D$4,IF('1.GHG Inventory Form'!$E$6="IPCC AR4 Report(2007)",'6.GWP'!$E$4,IF('1.GHG Inventory Form'!$E$6="IPCC AR5 Report(2013)",'6.GWP'!$F$4,IF('1.GHG Inventory Form'!$E$6="IPCC AR6 Report(2021)",'6.GWP'!$G$4,0))))),0) -> 0 | AU26: =IFERROR($L26*AF26*AN26,"") | AV26: =IFERROR($L26*AG26*AO26,"") | AW26: =IFERROR($L26*AH26*AP26,"") | AX26: =IFERROR($L26*AI26*AQ26,"") | AY26: =IFERROR($L26*AJ26*AR26,"") | AZ26: =IFERROR($L26*AK26*AS26,"") | BA26: =IFERROR($L26*AL26*AT26,"") | BB26: =ROUND(SUM(AU26:BA26),4) -> 0 | BC26: =BB26/SUM($BB$16:$BB$99) -> 0 | BD26: =BB26/$BB$169 -> 0 | BI26: =IF(H26="","",IF(I26="預設值Default",H26&J26,IF(I26="自訂值Custom Value",H26&K26,""))) | BJ26: =IF(H26="其它設備，請說明","",IF(O26=0,"",O26)) | BK26: =IF(H26="","",IF(I26="預設值Default",AM26,IF(I26="自訂值Custom Value",X26,"")))
A27: 12 | I27: 預設值Default | M27: =IFERROR(IF(I27="預設值Default",VLOOKUP($J27,'4.Default Emission Factor'!$D:$V,16,FALSE),"請填寫自訂活動數據單位Please fill in Custom Unit"),"請選擇預設排放係數名稱Please Choose Default Fuel or Greenhouse Gas") -> 請選擇預設排放係數名稱Please Choose Default Fuel or Greenhouse Gas | Y27: =IF(AF27>0.0000000001,"V","") | Z27: =IF(AG27>0.0000000001,"V","") | AA27: =IF(AH27>0.0000000001,"V","") | AB27: =IF(AI27>0.0000000001,"V","") | AC27: =IF(AJ27>0.0000000001,"V","") | AD27: =IF(AK27>0.0000000001,"V","") | AE27: =IF(AL27>0.0000000001,"V","") | AF27: =IFERROR(IF($I27="預設值Default",ROUND(VLOOKUP($J27,'4.Default Emission Factor'!$D:$V,2,FALSE),10),IF($I27="自訂值Custom Value",P27,0)),0) -> 0 | AG27: =IFERROR(IF($I27="預設值Default",ROUND(VLOOKUP($J27,'4.Default Emission Factor'!$D:$V,4,FALSE),10),IF($I27="自訂值Custom Value",Q27,0)),0) -> 0 | AH27: =IFERROR(IF($I27="預設值Default",ROUND(VLOOKUP($J27,'4.Default Emission Factor'!$D:$V,6,FALSE),10),IF($I27="自訂值Custom Value",R27,0)),0) -> 0 | AI27: =IFERROR(IF($I27="預設值Default",ROUND(VLOOKUP($J27,'4.Default Emission Factor'!$D:$V,8,FALSE),10),IF($I27="自訂值Custom Value",S27,0)),0) -> 0 | AJ27: =IFERROR(IF($I27="預設值Default",ROUND(VLOOKUP($J27,'4.Default Emission Factor'!$D:$V,10,FALSE),10),IF($I27="自訂值Custom Value",T27,0)),0) -> 0 | AK27: =IFERROR(IF($I27="預設值Default",ROUND(VLOOKUP($J27,'4.Default Emission Factor'!$D:$V,12,FALSE),10),IF($I27="自訂值Custom Value",U27,0)),0) -> 0 | AL27: =IFERROR(IF($I27="預設值Default",ROUND(VLOOKUP($J27,'4.Default Emission Factor'!$D:$V,14,FALSE),10),IF($I27="自訂值Custom Value",V27,0)),0) -> 0 | AM27: =IFERROR(IF(I27="預設值Default",VLOOKUP($J27,'4.Default Emission Factor'!$D:$V,17,FALSE),IF(I27="自訂值Custom Value",X27,"")),"") | AN27: =IF(Y27="V",1,0) -> 0 | AO27: =IF(Z27="V",IF('1.GHG Inventory Form'!$E$6="IPCC AR2 Report(1995)",'6.GWP'!$C$2,IF('1.GHG Inventory Form'!$E$6="IPCC AR3 Report(2001)",'6.GWP'!$D$2,IF('1.GHG Inventory Form'!$E$6="IPCC AR4 Report(2007)",'6.GWP'!$E$2,IF('1.GHG Inventory Form'!$E$6="IPCC AR5 Report(2013)",'6.GWP'!$F$2,IF('1.GHG Inventory Form'!$E$6="IPCC AR6 Report(2021)",'6.GWP'!$G$2,0))))),0) -> 0 | AP27: =IF(AA27="V",IF('1.GHG Inventory Form'!$E$6="IPCC AR2 Report(1995)",'6.GWP'!$C$3,IF('1.GHG Inventory Form'!$E$6="IPCC AR3 Report(2001)",'6.GWP'!$D$3,IF('1.GHG Inventory Form'!$E$6="IPCC AR4 Report(2007)",'6.GWP'!$E$3,IF('1.GHG Inventory Form'!$E$6="IPCC AR5 Report(2013)",'6.GWP'!$F$3,IF('1.GHG Inventory Form'!$E$6="IPCC AR6 Report(2021)",'6.GWP'!$G$3,0))))),0) -> 0 | AQ27: =IFERROR(IF(AND(AB27="V",$I27="預設值"),IF('1.GHG Inventory Form'!$E$6="IPCC AR2 Report(1995)",VLOOKUP($J27,'6.GWP'!$B$1:$G$173,2,FALSE),IF('1.GHG Inventory Form'!$E$6="IPCC AR3 Report(2001)",VLOOKUP($J27,'6.GWP'!$B$1:$G$173,3,FALSE),IF('1.GHG Inventory Form'!$E$6="IPCC AR4 Report(2007)",VLOOKUP($J27,'6.GWP'!$B$1:$G$173,4,FALSE),IF('1.GHG Inventory Form'!$E$6="IPCC AR5 Report(2013)",VLOOKUP($J27,'6.GWP'!$B$1:$G$173,5,FALSE),IF('1.GHG Inventory Form'!$E$6="IPCC AR6 Report(2021)",VLOOKUP($J27,'6.GWP'!$B$2:$G$173,6,FALSE),0))))),IF(AND(AB27="V",$I27="自訂值"),IF('1.GHG Inventory Form'!$E$6="IPCC AR2 Report(1995)",VLOOKUP($K27,'6.GWP'!$B$1:$G$173,2,FALSE),IF('1.GHG Inventory Form'!$E$6="IPCC AR3 Report(2001)",VLOOKUP($K27,'6.GWP'!$B$1:$G$173,3,FALSE),IF('1.GHG Inventory Form'!$E$6="IPCC AR4 Report(2007)",VLOOKUP($K27,'6.GWP'!$B$1:$G$173,4,FALSE),IF('1.GHG Inventory Form'!$E$6="IPCC AR5 Report(2013)",VLOOKUP($K27,'6.GWP'!$B$1:$G$173,5,FALSE),IF('1.GHG Inventory Form'!$E$6="IPCC AR6 Report(2021)",VLOOKUP($K27,'6.GWP'!$B$2:$G$173,6,FALSE),0))))),0)),0) -> 0 | AR27: =IFERROR(IF(AND(AC27="V",$I27="預設值"),IF('1.GHG Inventory Form'!$E$6="IPCC AR2 Report(1995)",VLOOKUP($J27,'6.GWP'!$B$1:$G$173,2,FALSE),IF('1.GHG Inventory Form'!$E$6="IPCC AR3 Report(2001)",VLOOKUP($J27,'6.GWP'!$B$1:$G$173,3,FALSE),IF('1.GHG Inventory Form'!$E$6="IPCC AR4 Report(2007)",VLOOKUP($J27,'6.GWP'!$B$1:$G$173,4,FALSE),IF('1.GHG Inventory Form'!$E$6="IPCC AR5 Report(2013)",VLOOKUP($J27,'6.GWP'!$B$1:$G$173,5,FALSE),IF('1.GHG Inventory Form'!$E$6="IPCC AR6 Report(2021)",VLOOKUP($J27,'6.GWP'!$B$2:$G$173,6,FALSE),0))))),IF(AND(AC27="V",$I27="自訂值"),IF('1.GHG Inventory Form'!$E$6="IPCC AR2 Report(1995)",VLOOKUP($K27,'6.GWP'!$B$1:$G$173,2,FALSE),IF('1.GHG Inventory Form'!$E$6="IPCC AR3 Report(2001)",VLOOKUP($K27,'6.GWP'!$B$1:$G$173,3,FALSE),IF('1.GHG Inventory Form'!$E$6="IPCC AR4 Report(2007)",VLOOKUP($K27,'6.GWP'!$B$1:$G$173,4,FALSE),IF('1.GHG Inventory Form'!$E$6="IPCC AR5 Report(2013)",VLOOKUP($K27,'6.GWP'!$B$1:$G$173,5,FALSE),IF('1.GHG Inventory Form'!$E$6="IPCC AR6 Report(2021)",VLOOKUP($K27,'6.GWP'!$B$2:$G$173,6,FALSE),0))))),0)),0) -> 0 | AS27: =IF(AD27="V",IF('1.GHG Inventory Form'!$E$6="IPCC AR2 Report(1995)",'6.GWP'!$C$5,IF('1.GHG Inventory Form'!$E$6="IPCC AR3 Report(2001)",'6.GWP'!$D$5,IF('1.GHG Inventory Form'!$E$6="IPCC AR4 Report(2007)",'6.GWP'!$E$5,IF('1.GHG Inventory Form'!$E$6="IPCC AR5 Report(2013)",'6.GWP'!$F$5,IF('1.GHG Inventory Form'!$E$6="IPCC AR6 Report(2021)",'6.GWP'!$G$5,0))))),0) -> 0 | AT27: =IF(AE27="V",IF('1.GHG Inventory Form'!$E$6="IPCC AR2 Report(1995)",'6.GWP'!$C$4,IF('1.GHG Inventory Form'!$E$6="IPCC AR3 Report(2001)",'6.GWP'!$D$4,IF('1.GHG Inventory Form'!$E$6="IPCC AR4 Report(2007)",'6.GWP'!$E$4,IF('1.GHG Inventory Form'!$E$6="IPCC AR5 Report(2013)",'6.GWP'!$F$4,IF('1.GHG Inventory Form'!$E$6="IPCC AR6 Report(2021)",'6.GWP'!$G$4,0))))),0) -> 0 | AU27: =IFERROR($L27*AF27*AN27,"") | AV27: =IFERROR($L27*AG27*AO27,"") | AW27: =IFERROR($L27*AH27*AP27,"") | AX27: =IFERROR($L27*AI27*AQ27,"") | AY27: =IFERROR($L27*AJ27*AR27,"") | AZ27: =IFERROR($L27*AK27*AS27,"") | BA27: =IFERROR($L27*AL27*AT27,"") | BB27: =ROUND(SUM(AU27:BA27),4) -> 0 | BC27: =BB27/SUM($BB$16:$BB$99) -> 0 | BD27: =BB27/$BB$169 -> 0 | BI27: =IF(H27="","",IF(I27="預設值Default",H27&J27,IF(I27="自訂值Custom Value",H27&K27,""))) | BJ27: =IF(H27="其它設備，請說明","",IF(O27=0,"",O27)) | BK27: =IF(H27="","",IF(I27="預設值Default",AM27,IF(I27="自訂值Custom Value",X27,"")))
A28: 1 | C28: 1.2 | D28: 移動燃燒直接排放 Mobile Combustion | G28: Y | H28: 車輛 vehicle | I28: 預設值Default | J28: 車用汽油(移動源)Motor Gasoline(Mobile combustion emissions) | L28: 22.07112 | M28: =IFERROR(IF(I28="預設值Default",VLOOKUP($J28,'4.Default Emission Factor'!$D:$V,16,FALSE),"請填寫自訂活動數據單位Please fill in Custom Unit"),"請選擇預設排放係數名稱Please Choose Default Fuel or Greenhouse Gas") -> KL | Y28: =IF(AF28>0.0000000001,"V","") -> V | Z28: =IF(AG28>0.0000000001,"V","") -> V | AA28: =IF(AH28>0.0000000001,"V","") -> V | AB28: =IF(AI28>0.0000000001,"V","") | AC28: =IF(AJ28>0.0000000001,"V","") | AD28: =IF(AK28>0.0000000001,"V","") | AE28: =IF(AL28>0.0000000001,"V","") | AF28: =IFERROR(IF($I28="預設值Default",ROUND(VLOOKUP($J28,'4.Default Emission Factor'!$D:$V,2,FALSE),10),IF($I28="自訂值Custom Value",P28,0)),0) -> 2.2631329 | AG28: =IFERROR(IF($I28="預設值Default",ROUND(VLOOKUP($J28,'4.Default Emission Factor'!$D:$V,4,FALSE),10),IF($I28="自訂值Custom Value",Q28,0)),0) -> 0.000816426 | AH28: =IFERROR(IF($I28="預設值Default",ROUND(VLOOKUP($J28,'4.Default Emission Factor'!$D:$V,6,FALSE),10),IF($I28="自訂值Custom Value",R28,0)),0) -> 0.0002612563 | AI28: =IFERROR(IF($I28="預設值Default",ROUND(VLOOKUP($J28,'4.Default Emission Factor'!$D:$V,8,FALSE),10),IF($I28="自訂值Custom Value",S28,0)),0) -> 0 | AJ28: =IFERROR(IF($I28="預設值Default",ROUND(VLOOKUP($J28,'4.Default Emission Factor'!$D:$V,10,FALSE),10),IF($I28="自訂值Custom Value",T28,0)),0) -> 0 | AK28: =IFERROR(IF($I28="預設值Default",ROUND(VLOOKUP($J28,'4.Default Emission Factor'!$D:$V,12,FALSE),10),IF($I28="自訂值Custom Value",U28,0)),0) -> 0 | AL28: =IFERROR(IF($I28="預設值Default",ROUND(VLOOKUP($J28,'4.Default Emission Factor'!$D:$V,14,FALSE),10),IF($I28="自訂值Custom Value",V28,0)),0) -> 0 | AM28: =IFERROR(IF(I28="預設值Default",VLOOKUP($J28,'4.Default Emission Factor'!$D:$V,17,FALSE),IF(I28="自訂值Custom Value",X28,"")),"") -> 環保署排放係管理表6.0.4Taiwan EPA GHG coefficient table 6.0.4 | AN28: =IF(Y28="V",1,0) -> 1 | AO28: =IF(Z28="V",IF('1.GHG Inventory Form'!$E$6="IPCC AR2 Report(1995)",'6.GWP'!$C$2,IF('1.GHG Inventory Form'!$E$6="IPCC AR3 Report(2001)",'6.GWP'!$D$2,IF('1.GHG Inventory Form'!$E$6="IPCC AR4 Report(2007)",'6.GWP'!$E$2,IF('1.GHG Inventory Form'!$E$6="IPCC AR5 Report(2013)",'6.GWP'!$F$2,IF('1.GHG Inventory Form'!$E$6="IPCC AR6 Report(2021)",'6.GWP'!$G$2,0))))),0) -> 27.9 | AP28: =IF(AA28="V",IF('1.GHG Inventory Form'!$E$6="IPCC AR2 Report(1995)",'6.GWP'!$C$3,IF('1.GHG Inventory Form'!$E$6="IPCC AR3 Report(2001)",'6.GWP'!$D$3,IF('1.GHG Inventory Form'!$E$6="IPCC AR4 Report(2007)",'6.GWP'!$E$3,IF('1.GHG Inventory Form'!$E$6="IPCC AR5 Report(2013)",'6.GWP'!$F$3,IF('1.GHG Inventory Form'!$E$6="IPCC AR6 Report(2021)",'6.GWP'!$G$3,0))))),0) -> 273 | AQ28: =IFERROR(IF(AND(AB28="V",$I28="預設值"),IF('1.GHG Inventory Form'!$E$6="IPCC AR2 Report(1995)",VLOOKUP($J28,'6.GWP'!$B$1:$G$173,2,FALSE),IF('1.GHG Inventory Form'!$E$6="IPCC AR3 Report(2001)",VLOOKUP($J28,'6.GWP'!$B$1:$G$173,3,FALSE),IF('1.GHG Inventory Form'!$E$6="IPCC AR4 Report(2007)",VLOOKUP($J28,'6.GWP'!$B$1:$G$173,4,FALSE),IF('1.GHG Inventory Form'!$E$6="IPCC AR5 Report(2013)",VLOOKUP($J28,'6.GWP'!$B$1:$G$173,5,FALSE),IF('1.GHG Inventory Form'!$E$6="IPCC AR6 Report(2021)",VLOOKUP($J28,'6.GWP'!$B$2:$G$173,6,FALSE),0))))),IF(AND(AB28="V",$I28="自訂值"),IF('1.GHG Inventory Form'!$E$6="IPCC AR2 Report(1995)",VLOOKUP($K28,'6.GWP'!$B$1:$G$173,2,FALSE),IF('1.GHG Inventory Form'!$E$6="IPCC AR3 Report(2001)",VLOOKUP($K28,'6.GWP'!$B$1:$G$173,3,FALSE),IF('1.GHG Inventory Form'!$E$6="IPCC AR4 Report(2007)",VLOOKUP($K28,'6.GWP'!$B$1:$G$173,4,FALSE),IF('1.GHG Inventory Form'!$E$6="IPCC AR5 Report(2013)",VLOOKUP($K28,'6.GWP'!$B$1:$G$173,5,FALSE),IF('1.GHG Inventory Form'!$E$6="IPCC AR6 Report(2021)",VLOOKUP($K28,'6.GWP'!$B$2:$G$173,6,FALSE),0))))),0)),0) -> 0 | AR28: =IFERROR(IF(AND(AC28="V",$I28="預設值"),IF('1.GHG Inventory Form'!$E$6="IPCC AR2 Report(1995)",VLOOKUP($J28,'6.GWP'!$B$1:$G$173,2,FALSE),IF('1.GHG Inventory Form'!$E$6="IPCC AR3 Report(2001)",VLOOKUP($J28,'6.GWP'!$B$1:$G$173,3,FALSE),IF('1.GHG Inventory Form'!$E$6="IPCC AR4 Report(2007)",VLOOKUP($J28,'6.GWP'!$B$1:$G$173,4,FALSE),IF('1.GHG Inventory Form'!$E$6="IPCC AR5 Report(2013)",VLOOKUP($J28,'6.GWP'!$B$1:$G$173,5,FALSE),IF('1.GHG Inventory Form'!$E$6="IPCC AR6 Report(2021)",VLOOKUP($J28,'6.GWP'!$B$2:$G$173,6,FALSE),0))))),IF(AND(AC28="V",$I28="自訂值"),IF('1.GHG Inventory Form'!$E$6="IPCC AR2 Report(1995)",VLOOKUP($K28,'6.GWP'!$B$1:$G$173,2,FALSE),IF('1.GHG Inventory Form'!$E$6="IPCC AR3 Report(2001)",VLOOKUP($K28,'6.GWP'!$B$1:$G$173,3,FALSE),IF('1.GHG Inventory Form'!$E$6="IPCC AR4 Report(2007)",VLOOKUP($K28,'6.GWP'!$B$1:$G$173,4,FALSE),IF('1.GHG Inventory Form'!$E$6="IPCC AR5 Report(2013)",VLOOKUP($K28,'6.GWP'!$B$1:$G$173,5,FALSE),IF('1.GHG Inventory Form'!$E$6="IPCC AR6 Report(2021)",VLOOKUP($K28,'6.GWP'!$B$2:$G$173,6,FALSE),0))))),0)),0) -> 0 | AS28: =IF(AD28="V",IF('1.GHG Inventory Form'!$E$6="IPCC AR2 Report(1995)",'6.GWP'!$C$5,IF('1.GHG Inventory Form'!$E$6="IPCC AR3 Report(2001)",'6.GWP'!$D$5,IF('1.GHG Inventory Form'!$E$6="IPCC AR4 Report(2007)",'6.GWP'!$E$5,IF('1.GHG Inventory Form'!$E$6="IPCC AR5 Report(2013)",'6.GWP'!$F$5,IF('1.GHG Inventory Form'!$E$6="IPCC AR6 Report(2021)",'6.GWP'!$G$5,0))))),0) -> 0 | AT28: =IF(AE28="V",IF('1.GHG Inventory Form'!$E$6="IPCC AR2 Report(1995)",'6.GWP'!$C$4,IF('1.GHG Inventory Form'!$E$6="IPCC AR3 Report(2001)",'6.GWP'!$D$4,IF('1.GHG Inventory Form'!$E$6="IPCC AR4 Report(2007)",'6.GWP'!$E$4,IF('1.GHG Inventory Form'!$E$6="IPCC AR5 Report(2013)",'6.GWP'!$F$4,IF('1.GHG Inventory Form'!$E$6="IPCC AR6 Report(2021)",'6.GWP'!$G$4,0))))),0) -> 0 | AU28: =IFERROR($L28*AF28*AN28,"") -> 49.949877 | AV28: =IFERROR($L28*AG28*AO28,"") -> 0.50274227 | AW28: =IFERROR($L28*AH28*AP28,"") -> 1.5741778 | AX28: =IFERROR($L28*AI28*AQ28,"") -> 0 | AY28: =IFERROR($L28*AJ28*AR28,"") -> 0 | AZ28: =IFERROR($L28*AK28*AS28,"") -> 0 | BA28: =IFERROR($L28*AL28*AT28,"") -> 0 | BB28: =ROUND(SUM(AU28:BA28),4) -> 52.0268 | BC28: =BB28/SUM($BB$16:$BB$99) -> 0.036400254 | BD28: =BB28/$BB$169 -> 0.032805641 | BI28: =IF(H28="","",IF(I28="預設值Default",H28&J28,IF(I28="自訂值Custom Value",H28&K28,""))) -> 車輛 vehicle車用汽油(移動源)Motor Gasoline(Mobile combustion emissions) | BJ28: =IF(H28="其它設備，請說明","",IF(O28=0,"",O28)) | BK28: =IF(H28="","",IF(I28="預設值Default",AM28,IF(I28="自訂值Custom Value",X28,""))) -> 環保署排放係管理表6.0.4Taiwan EPA GHG coefficient table 6.0.4
A29: 2 | G29: Y | H29: 車輛 vehicle | I29: 預設值Default | J29: 柴油(移動源)Diesel Oil(Mobile combustion emissions) | L29: 0.31542 | M29: =IFERROR(IF(I29="預設值Default",VLOOKUP($J29,'4.Default Emission Factor'!$D:$V,16,FALSE),"請填寫自訂活動數據單位Please fill in Custom Unit"),"請選擇預設排放係數名稱Please Choose Default Fuel or Greenhouse Gas") -> KL | Y29: =IF(AF29>0.0000000001,"V","") -> V | Z29: =IF(AG29>0.0000000001,"V","") -> V | AA29: =IF(AH29>0.0000000001,"V","") -> V | AB29: =IF(AI29>0.0000000001,"V","") | AC29: =IF(AJ29>0.0000000001,"V","") | AD29: =IF(AK29>0.0000000001,"V","") | AE29: =IF(AL29>0.0000000001,"V","") | AF29: =IFERROR(IF($I29="預設值Default",ROUND(VLOOKUP($J29,'4.Default Emission Factor'!$D:$V,2,FALSE),10),IF($I29="自訂值Custom Value",P29,0)),0) -> 2.6060318 | AG29: =IFERROR(IF($I29="預設值Default",ROUND(VLOOKUP($J29,'4.Default Emission Factor'!$D:$V,4,FALSE),10),IF($I29="自訂值Custom Value",Q29,0)),0) -> 0.0001371596 | AH29: =IFERROR(IF($I29="預設值Default",ROUND(VLOOKUP($J29,'4.Default Emission Factor'!$D:$V,6,FALSE),10),IF($I29="自訂值Custom Value",R29,0)),0) -> 0.0001371596 | AI29: =IFERROR(IF($I29="預設值Default",ROUND(VLOOKUP($J29,'4.Default Emission Factor'!$D:$V,8,FALSE),10),IF($I29="自訂值Custom Value",S29,0)),0) -> 0 | AJ29: =IFERROR(IF($I29="預設值Default",ROUND(VLOOKUP($J29,'4.Default Emission Factor'!$D:$V,10,FALSE),10),IF($I29="自訂值Custom Value",T29,0)),0) -> 0 | AK29: =IFERROR(IF($I29="預設值Default",ROUND(VLOOKUP($J29,'4.Default Emission Factor'!$D:$V,12,FALSE),10),IF($I29="自訂值Custom Value",U29,0)),0) -> 0 | AL29: =IFERROR(IF($I29="預設值Default",ROUND(VLOOKUP($J29,'4.Default Emission Factor'!$D:$V,14,FALSE),10),IF($I29="自訂值Custom Value",V29,0)),0) -> 0 | AM29: =IFERROR(IF(I29="預設值Default",VLOOKUP($J29,'4.Default Emission Factor'!$D:$V,17,FALSE),IF(I29="自訂值Custom Value",X29,"")),"") -> 環保署排放係管理表6.0.4Taiwan EPA GHG coefficient table 6.0.4 | AN29: =IF(Y29="V",1,0) -> 1 | AO29: =IF(Z29="V",IF('1.GHG Inventory Form'!$E$6="IPCC AR2 Report(1995)",'6.GWP'!$C$2,IF('1.GHG Inventory Form'!$E$6="IPCC AR3 Report(2001)",'6.GWP'!$D$2,IF('1.GHG Inventory Form'!$E$6="IPCC AR4 Report(2007)",'6.GWP'!$E$2,IF('1.GHG Inventory Form'!$E$6="IPCC AR5 Report(2013)",'6.GWP'!$F$2,IF('1.GHG Inventory Form'!$E$6="IPCC AR6 Report(2021)",'6.GWP'!$G$2,0))))),0) -> 27.9 | AP29: =IF(AA29="V",IF('1.GHG Inventory Form'!$E$6="IPCC AR2 Report(1995)",'6.GWP'!$C$3,IF('1.GHG Inventory Form'!$E$6="IPCC AR3 Report(2001)",'6.GWP'!$D$3,IF('1.GHG Inventory Form'!$E$6="IPCC AR4 Report(2007)",'6.GWP'!$E$3,IF('1.GHG Inventory Form'!$E$6="IPCC AR5 Report(2013)",'6.GWP'!$F$3,IF('1.GHG Inventory Form'!$E$6="IPCC AR6 Report(2021)",'6.GWP'!$G$3,0))))),0) -> 273 | AQ29: =IFERROR(IF(AND(AB29="V",$I29="預設值"),IF('1.GHG Inventory Form'!$E$6="IPCC AR2 Report(1995)",VLOOKUP($J29,'6.GWP'!$B$1:$G$173,2,FALSE),IF('1.GHG Inventory Form'!$E$6="IPCC AR3 Report(2001)",VLOOKUP($J29,'6.GWP'!$B$1:$G$173,3,FALSE),IF('1.GHG Inventory Form'!$E$6="IPCC AR4 Report(2007)",VLOOKUP($J29,'6.GWP'!$B$1:$G$173,4,FALSE),IF('1.GHG Inventory Form'!$E$6="IPCC AR5 Report(2013)",VLOOKUP($J29,'6.GWP'!$B$1:$G$173,5,FALSE),IF('1.GHG Inventory Form'!$E$6="IPCC AR6 Report(2021)",VLOOKUP($J29,'6.GWP'!$B$2:$G$173,6,FALSE),0))))),IF(AND(AB29="V",$I29="自訂值"),IF('1.GHG Inventory Form'!$E$6="IPCC AR2 Report(1995)",VLOOKUP($K29,'6.GWP'!$B$1:$G$173,2,FALSE),IF('1.GHG Inventory Form'!$E$6="IPCC AR3 Report(2001)",VLOOKUP($K29,'6.GWP'!$B$1:$G$173,3,FALSE),IF('1.GHG Inventory Form'!$E$6="IPCC AR4 Report(2007)",VLOOKUP($K29,'6.GWP'!$B$1:$G$173,4,FALSE),IF('1.GHG Inventory Form'!$E$6="IPCC AR5 Report(2013)",VLOOKUP($K29,'6.GWP'!$B$1:$G$173,5,FALSE),IF('1.GHG Inventory Form'!$E$6="IPCC AR6 Report(2021)",VLOOKUP($K29,'6.GWP'!$B$2:$G$173,6,FALSE),0))))),0)),0) -> 0 | AR29: =IFERROR(IF(AND(AC29="V",$I29="預設值"),IF('1.GHG Inventory Form'!$E$6="IPCC AR2 Report(1995)",VLOOKUP($J29,'6.GWP'!$B$1:$G$173,2,FALSE),IF('1.GHG Inventory Form'!$E$6="IPCC AR3 Report(2001)",VLOOKUP($J29,'6.GWP'!$B$1:$G$173,3,FALSE),IF('1.GHG Inventory Form'!$E$6="IPCC AR4 Report(2007)",VLOOKUP($J29,'6.GWP'!$B$1:$G$173,4,FALSE),IF('1.GHG Inventory Form'!$E$6="IPCC AR5 Report(2013)",VLOOKUP($J29,'6.GWP'!$B$1:$G$173,5,FALSE),IF('1.GHG Inventory Form'!$E$6="IPCC AR6 Report(2021)",VLOOKUP($J29,'6.GWP'!$B$2:$G$173,6,FALSE),0))))),IF(AND(AC29="V",$I29="自訂值"),IF('1.GHG Inventory Form'!$E$6="IPCC AR2 Report(1995)",VLOOKUP($K29,'6.GWP'!$B$1:$G$173,2,FALSE),IF('1.GHG Inventory Form'!$E$6="IPCC AR3 Report(2001)",VLOOKUP($K29,'6.GWP'!$B$1:$G$173,3,FALSE),IF('1.GHG Inventory Form'!$E$6="IPCC AR4 Report(2007)",VLOOKUP($K29,'6.GWP'!$B$1:$G$173,4,FALSE),IF('1.GHG Inventory Form'!$E$6="IPCC AR5 Report(2013)",VLOOKUP($K29,'6.GWP'!$B$1:$G$173,5,FALSE),IF('1.GHG Inventory Form'!$E$6="IPCC AR6 Report(2021)",VLOOKUP($K29,'6.GWP'!$B$2:$G$173,6,FALSE),0))))),0)),0) -> 0 | AS29: =IF(AD29="V",IF('1.GHG Inventory Form'!$E$6="IPCC AR2 Report(1995)",'6.GWP'!$C$5,IF('1.GHG Inventory Form'!$E$6="IPCC AR3 Report(2001)",'6.GWP'!$D$5,IF('1.GHG Inventory Form'!$E$6="IPCC AR4 Report(2007)",'6.GWP'!$E$5,IF('1.GHG Inventory Form'!$E$6="IPCC AR5 Report(2013)",'6.GWP'!$F$5,IF('1.GHG Inventory Form'!$E$6="IPCC AR6 Report(2021)",'6.GWP'!$G$5,0))))),0) -> 0 | AT29: =IF(AE29="V",IF('1.GHG Inventory Form'!$E$6="IPCC AR2 Report(1995)",'6.GWP'!$C$4,IF('1.GHG Inventory Form'!$E$6="IPCC AR3 Report(2001)",'6.GWP'!$D$4,IF('1.GHG Inventory Form'!$E$6="IPCC AR4 Report(2007)",'6.GWP'!$E$4,IF('1.GHG Inventory Form'!$E$6="IPCC AR5 Report(2013)",'6.GWP'!$F$4,IF('1.GHG Inventory Form'!$E$6="IPCC AR6 Report(2021)",'6.GWP'!$G$4,0))))),0) -> 0 | AU29: =IFERROR($L29*AF29*AN29,"") -> 0.82199455 | AV29: =IFERROR($L29*AG29*AO29,"") -> 0.0012070344 | AW29: =IFERROR($L29*AH29*AP29,"") -> 0.011810767 | AX29: =IFERROR($L29*AI29*AQ29,"") -> 0 | AY29: =IFERROR($L29*AJ29*AR29,"") -> 0 | AZ29: =IFERROR($L29*AK29*AS29,"") -> 0 | BA29: =IFERROR($L29*AL29*AT29,"") -> 0 | BB29: =ROUND(SUM(AU29:BA29),4) -> 0.835 | BC29: =BB29/SUM($BB$16:$BB$99) -> 0.000584203 | BD29: =BB29/$BB$169 -> 0.00052651153 | BI29: =IF(H29="","",IF(I29="預設值Default",H29&J29,IF(I29="自訂值Custom Value",H29&K29,""))) -> 車輛 vehicle柴油(移動源)Diesel Oil(Mobile combustion emissions) | BJ29: =IF(H29="其它設備，請說明","",IF(O29=0,"",O29)) | BK29: =IF(H29="","",IF(I29="預設值Default",AM29,IF(I29="自訂值Custom Value",X29,""))) -> 環保署排放係管理表6.0.4Taiwan EPA GHG coefficient table 6.0.4
A30: 3 | M30: =IFERROR(IF(I30="預設值Default",VLOOKUP($J30,'4.Default Emission Factor'!$D:$V,16,FALSE),"請填寫自訂活動數據單位Please fill in Custom Unit"),"請選擇預設排放係數名稱Please Choose Default Fuel or Greenhouse Gas") -> 請填寫自訂活動數據單位Please fill in Custom Unit | Y30: =IF(AF30>0.0000000001,"V","") | Z30: =IF(AG30>0.0000000001,"V","") | AA30: =IF(AH30>0.0000000001,"V","") | AB30: =IF(AI30>0.0000000001,"V","") | AC30: =IF(AJ30>0.0000000001,"V","") | AD30: =IF(AK30>0.0000000001,"V","") | AE30: =IF(AL30>0.0000000001,"V","") | AF30: =IFERROR(IF($I30="預設值Default",ROUND(VLOOKUP($J30,'4.Default Emission Factor'!$D:$V,2,FALSE),10),IF($I30="自訂值Custom Value",P30,0)),0) -> 0 | AG30: =IFERROR(IF($I30="預設值Default",ROUND(VLOOKUP($J30,'4.Default Emission Factor'!$D:$V,4,FALSE),10),IF($I30="自訂值Custom Value",Q30,0)),0) -> 0 | AH30: =IFERROR(IF($I30="預設值Default",ROUND(VLOOKUP($J30,'4.Default Emission Factor'!$D:$V,6,FALSE),10),IF($I30="自訂值Custom Value",R30,0)),0) -> 0 | AI30: =IFERROR(IF($I30="預設值Default",ROUND(VLOOKUP($J30,'4.Default Emission Factor'!$D:$V,8,FALSE),10),IF($I30="自訂值Custom Value",S30,0)),0) -> 0 | AJ30: =IFERROR(IF($I30="預設值Default",ROUND(VLOOKUP($J30,'4.Default Emission Factor'!$D:$V,10,FALSE),10),IF($I30="自訂值Custom Value",T30,0)),0) -> 0 | AK30: =IFERROR(IF($I30="預設值Default",ROUND(VLOOKUP($J30,'4.Default Emission Factor'!$D:$V,12,FALSE),10),IF($I30="自訂值Custom Value",U30,0)),0) -> 0 | AL30: =IFERROR(IF($I30="預設值Default",ROUND(VLOOKUP($J30,'4.Default Emission Factor'!$D:$V,14,FALSE),10),IF($I30="自訂值Custom Value",V30,0)),0) -> 0 | AM30: =IFERROR(IF(I30="預設值Default",VLOOKUP($J30,'4.Default Emission Factor'!$D:$V,17,FALSE),IF(I30="自訂值Custom Value",X30,"")),"") | AN30: =IF(Y30="V",1,0) -> 0 | AO30: =IF(Z30="V",IF('1.GHG Inventory Form'!$E$6="IPCC AR2 Report(1995)",'6.GWP'!$C$2,IF('1.GHG Inventory Form'!$E$6="IPCC AR3 Report(2001)",'6.GWP'!$D$2,IF('1.GHG Inventory Form'!$E$6="IPCC AR4 Report(2007)",'6.GWP'!$E$2,IF('1.GHG Inventory Form'!$E$6="IPCC AR5 Report(2013)",'6.GWP'!$F$2,IF('1.GHG Inventory Form'!$E$6="IPCC AR6 Report(2021)",'6.GWP'!$G$2,0))))),0) -> 0 | AP30: =IF(AA30="V",IF('1.GHG Inventory Form'!$E$6="IPCC AR2 Report(1995)",'6.GWP'!$C$3,IF('1.GHG Inventory Form'!$E$6="IPCC AR3 Report(2001)",'6.GWP'!$D$3,IF('1.GHG Inventory Form'!$E$6="IPCC AR4 Report(2007)",'6.GWP'!$E$3,IF('1.GHG Inventory Form'!$E$6="IPCC AR5 Report(2013)",'6.GWP'!$F$3,IF('1.GHG Inventory Form'!$E$6="IPCC AR6 Report(2021)",'6.GWP'!$G$3,0))))),0) -> 0 | AQ30: =IFERROR(IF(AND(AB30="V",$I30="預設值"),IF('1.GHG Inventory Form'!$E$6="IPCC AR2 Report(1995)",VLOOKUP($J30,'6.GWP'!$B$1:$G$173,2,FALSE),IF('1.GHG Inventory Form'!$E$6="IPCC AR3 Report(2001)",VLOOKUP($J30,'6.GWP'!$B$1:$G$173,3,FALSE),IF('1.GHG Inventory Form'!$E$6="IPCC AR4 Report(2007)",VLOOKUP($J30,'6.GWP'!$B$1:$G$173,4,FALSE),IF('1.GHG Inventory Form'!$E$6="IPCC AR5 Report(2013)",VLOOKUP($J30,'6.GWP'!$B$1:$G$173,5,FALSE),IF('1.GHG Inventory Form'!$E$6="IPCC AR6 Report(2021)",VLOOKUP($J30,'6.GWP'!$B$2:$G$173,6,FALSE),0))))),IF(AND(AB30="V",$I30="自訂值"),IF('1.GHG Inventory Form'!$E$6="IPCC AR2 Report(1995)",VLOOKUP($K30,'6.GWP'!$B$1:$G$173,2,FALSE),IF('1.GHG Inventory Form'!$E$6="IPCC AR3 Report(2001)",VLOOKUP($K30,'6.GWP'!$B$1:$G$173,3,FALSE),IF('1.GHG Inventory Form'!$E$6="IPCC AR4 Report(2007)",VLOOKUP($K30,'6.GWP'!$B$1:$G$173,4,FALSE),IF('1.GHG Inventory Form'!$E$6="IPCC AR5 Report(2013)",VLOOKUP($K30,'6.GWP'!$B$1:$G$173,5,FALSE),IF('1.GHG Inventory Form'!$E$6="IPCC AR6 Report(2021)",VLOOKUP($K30,'6.GWP'!$B$2:$G$173,6,FALSE),0))))),0)),0) -> 0 | AR30: =IFERROR(IF(AND(AC30="V",$I30="預設值"),IF('1.GHG Inventory Form'!$E$6="IPCC AR2 Report(1995)",VLOOKUP($J30,'6.GWP'!$B$1:$G$173,2,FALSE),IF('1.GHG Inventory Form'!$E$6="IPCC AR3 Report(2001)",VLOOKUP($J30,'6.GWP'!$B$1:$G$173,3,FALSE),IF('1.GHG Inventory Form'!$E$6="IPCC AR4 Report(2007)",VLOOKUP($J30,'6.GWP'!$B$1:$G$173,4,FALSE),IF('1.GHG Inventory Form'!$E$6="IPCC AR5 Report(2013)",VLOOKUP($J30,'6.GWP'!$B$1:$G$173,5,FALSE),IF('1.GHG Inventory Form'!$E$6="IPCC AR6 Report(2021)",VLOOKUP($J30,'6.GWP'!$B$2:$G$173,6,FALSE),0))))),IF(AND(AC30="V",$I30="自訂值"),IF('1.GHG Inventory Form'!$E$6="IPCC AR2 Report(1995)",VLOOKUP($K30,'6.GWP'!$B$1:$G$173,2,FALSE),IF('1.GHG Inventory Form'!$E$6="IPCC AR3 Report(2001)",VLOOKUP($K30,'6.GWP'!$B$1:$G$173,3,FALSE),IF('1.GHG Inventory Form'!$E$6="IPCC AR4 Report(2007)",VLOOKUP($K30,'6.GWP'!$B$1:$G$173,4,FALSE),IF('1.GHG Inventory Form'!$E$6="IPCC AR5 Report(2013)",VLOOKUP($K30,'6.GWP'!$B$1:$G$173,5,FALSE),IF('1.GHG Inventory Form'!$E$6="IPCC AR6 Report(2021)",VLOOKUP($K30,'6.GWP'!$B$2:$G$173,6,FALSE),0))))),0)),0) -> 0 | AS30: =IF(AD30="V",IF('1.GHG Inventory Form'!$E$6="IPCC AR2 Report(1995)",'6.GWP'!$C$5,IF('1.GHG Inventory Form'!$E$6="IPCC AR3 Report(2001)",'6.GWP'!$D$5,IF('1.GHG Inventory Form'!$E$6="IPCC AR4 Report(2007)",'6.GWP'!$E$5,IF('1.GHG Inventory Form'!$E$6="IPCC AR5 Report(2013)",'6.GWP'!$F$5,IF('1.GHG Inventory Form'!$E$6="IPCC AR6 Report(2021)",'6.GWP'!$G$5,0))))),0) -> 0 | AT30: =IF(AE30="V",IF('1.GHG Inventory Form'!$E$6="IPCC AR2 Report(1995)",'6.GWP'!$C$4,IF('1.GHG Inventory Form'!$E$6="IPCC AR3 Report(2001)",'6.GWP'!$D$4,IF('1.GHG Inventory Form'!$E$6="IPCC AR4 Report(2007)",'6.GWP'!$E$4,IF('1.GHG Inventory Form'!$E$6="IPCC AR5 Report(2013)",'6.GWP'!$F$4,IF('1.GHG Inventory Form'!$E$6="IPCC AR6 Report(2021)",'6.GWP'!$G$4,0))))),0) -> 0 | AU30: =IFERROR($L30*AF30*AN30,"") -> 0 | AV30: =IFERROR($L30*AG30*AO30,"") -> 0 | AW30: =IFERROR($L30*AH30*AP30,"") -> 0 | AX30: =IFERROR($L30*AI30*AQ30,"") -> 0 | AY30: =IFERROR($L30*AJ30*AR30,"") -> 0 | AZ30: =IFERROR($L30*AK30*AS30,"") -> 0 | BA30: =IFERROR($L30*AL30*AT30,"") -> 0 | BB30: =ROUND(SUM(AU30:BA30),4) -> 0 | BC30: =BB30/SUM($BB$16:$BB$99) -> 0 | BD30: =BB30/$BB$169 -> 0 | BI30: =IF(H30="","",IF(I30="預設值Default",H30&J30,IF(I30="自訂值Custom Value",H30&K30,""))) | BJ30: =IF(H30="其它設備，請說明","",IF(O30=0,"",O30)) | BK30: =IF(H30="","",IF(I30="預設值Default",AM30,IF(I30="自訂值Custom Value",X30,"")))
A31: 4 | M31: =IFERROR(IF(I31="預設值Default",VLOOKUP($J31,'4.Default Emission Factor'!$D:$V,16,FALSE),"請填寫自訂活動數據單位Please fill in Custom Unit"),"請選擇預設排放係數名稱Please Choose Default Fuel or Greenhouse Gas") -> 請填寫自訂活動數據單位Please fill in Custom Unit | Y31: =IF(AF31>0.0000000001,"V","") | Z31: =IF(AG31>0.0000000001,"V","") | AA31: =IF(AH31>0.0000000001,"V","") | AB31: =IF(AI31>0.0000000001,"V","") | AC31: =IF(AJ31>0.0000000001,"V","") | AD31: =IF(AK31>0.0000000001,"V","") | AE31: =IF(AL31>0.0000000001,"V","") | AF31: =IFERROR(IF($I31="預設值Default",ROUND(VLOOKUP($J31,'4.Default Emission Factor'!$D:$V,2,FALSE),10),IF($I31="自訂值Custom Value",P31,0)),0) -> 0 | AG31: =IFERROR(IF($I31="預設值Default",ROUND(VLOOKUP($J31,'4.Default Emission Factor'!$D:$V,4,FALSE),10),IF($I31="自訂值Custom Value",Q31,0)),0) -> 0 | AH31: =IFERROR(IF($I31="預設值Default",ROUND(VLOOKUP($J31,'4.Default Emission Factor'!$D:$V,6,FALSE),10),IF($I31="自訂值Custom Value",R31,0)),0) -> 0 | AI31: =IFERROR(IF($I31="預設值Default",ROUND(VLOOKUP($J31,'4.Default Emission Factor'!$D:$V,8,FALSE),10),IF($I31="自訂值Custom Value",S31,0)),0) -> 0 | AJ31: =IFERROR(IF($I31="預設值Default",ROUND(VLOOKUP($J31,'4.Default Emission Factor'!$D:$V,10,FALSE),10),IF($I31="自訂值Custom Value",T31,0)),0) -> 0 | AK31: =IFERROR(IF($I31="預設值Default",ROUND(VLOOKUP($J31,'4.Default Emission Factor'!$D:$V,12,FALSE),10),IF($I31="自訂值Custom Value",U31,0)),0) -> 0 | AL31: =IFERROR(IF($I31="預設值Default",ROUND(VLOOKUP($J31,'4.Default Emission Factor'!$D:$V,14,FALSE),10),IF($I31="自訂值Custom Value",V31,0)),0) -> 0 | AM31: =IFERROR(IF(I31="預設值Default",VLOOKUP($J31,'4.Default Emission Factor'!$D:$V,17,FALSE),IF(I31="自訂值Custom Value",X31,"")),"") | AN31: =IF(Y31="V",1,0) -> 0 | AO31: =IF(Z31="V",IF('1.GHG Inventory Form'!$E$6="IPCC AR2 Report(1995)",'6.GWP'!$C$2,IF('1.GHG Inventory Form'!$E$6="IPCC AR3 Report(2001)",'6.GWP'!$D$2,IF('1.GHG Inventory Form'!$E$6="IPCC AR4 Report(2007)",'6.GWP'!$E$2,IF('1.GHG Inventory Form'!$E$6="IPCC AR5 Report(2013)",'6.GWP'!$F$2,IF('1.GHG Inventory Form'!$E$6="IPCC AR6 Report(2021)",'6.GWP'!$G$2,0))))),0) -> 0 | AP31: =IF(AA31="V",IF('1.GHG Inventory Form'!$E$6="IPCC AR2 Report(1995)",'6.GWP'!$C$3,IF('1.GHG Inventory Form'!$E$6="IPCC AR3 Report(2001)",'6.GWP'!$D$3,IF('1.GHG Inventory Form'!$E$6="IPCC AR4 Report(2007)",'6.GWP'!$E$3,IF('1.GHG Inventory Form'!$E$6="IPCC AR5 Report(2013)",'6.GWP'!$F$3,IF('1.GHG Inventory Form'!$E$6="IPCC AR6 Report(2021)",'6.GWP'!$G$3,0))))),0) -> 0 | AQ31: =IFERROR(IF(AND(AB31="V",$I31="預設值"),IF('1.GHG Inventory Form'!$E$6="IPCC AR2 Report(1995)",VLOOKUP($J31,'6.GWP'!$B$1:$G$173,2,FALSE),IF('1.GHG Inventory Form'!$E$6="IPCC AR3 Report(2001)",VLOOKUP($J31,'6.GWP'!$B$1:$G$173,3,FALSE),IF('1.GHG Inventory Form'!$E$6="IPCC AR4 Report(2007)",VLOOKUP($J31,'6.GWP'!$B$1:$G$173,4,FALSE),IF('1.GHG Inventory Form'!$E$6="IPCC AR5 Report(2013)",VLOOKUP($J31,'6.GWP'!$B$1:$G$173,5,FALSE),IF('1.GHG Inventory Form'!$E$6="IPCC AR6 Report(2021)",VLOOKUP($J31,'6.GWP'!$B$2:$G$173,6,FALSE),0))))),IF(AND(AB31="V",$I31="自訂值"),IF('1.GHG Inventory Form'!$E$6="IPCC AR2 Report(1995)",VLOOKUP($K31,'6.GWP'!$B$1:$G$173,2,FALSE),IF('1.GHG Inventory Form'!$E$6="IPCC AR3 Report(2001)",VLOOKUP($K31,'6.GWP'!$B$1:$G$173,3,FALSE),IF('1.GHG Inventory Form'!$E$6="IPCC AR4 Report(2007)",VLOOKUP($K31,'6.GWP'!$B$1:$G$173,4,FALSE),IF('1.GHG Inventory Form'!$E$6="IPCC AR5 Report(2013)",VLOOKUP($K31,'6.GWP'!$B$1:$G$173,5,FALSE),IF('1.GHG Inventory Form'!$E$6="IPCC AR6 Report(2021)",VLOOKUP($K31,'6.GWP'!$B$2:$G$173,6,FALSE),0))))),0)),0) -> 0 | AR31: =IFERROR(IF(AND(AC31="V",$I31="預設值"),IF('1.GHG Inventory Form'!$E$6="IPCC AR2 Report(1995)",VLOOKUP($J31,'6.GWP'!$B$1:$G$173,2,FALSE),IF('1.GHG Inventory Form'!$E$6="IPCC AR3 Report(2001)",VLOOKUP($J31,'6.GWP'!$B$1:$G$173,3,FALSE),IF('1.GHG Inventory Form'!$E$6="IPCC AR4 Report(2007)",VLOOKUP($J31,'6.GWP'!$B$1:$G$173,4,FALSE),IF('1.GHG Inventory Form'!$E$6="IPCC AR5 Report(2013)",VLOOKUP($J31,'6.GWP'!$B$1:$G$173,5,FALSE),IF('1.GHG Inventory Form'!$E$6="IPCC AR6 Report(2021)",VLOOKUP($J31,'6.GWP'!$B$2:$G$173,6,FALSE),0))))),IF(AND(AC31="V",$I31="自訂值"),IF('1.GHG Inventory Form'!$E$6="IPCC AR2 Report(1995)",VLOOKUP($K31,'6.GWP'!$B$1:$G$173,2,FALSE),IF('1.GHG Inventory Form'!$E$6="IPCC AR3 Report(2001)",VLOOKUP($K31,'6.GWP'!$B$1:$G$173,3,FALSE),IF('1.GHG Inventory Form'!$E$6="IPCC AR4 Report(2007)",VLOOKUP($K31,'6.GWP'!$B$1:$G$173,4,FALSE),IF('1.GHG Inventory Form'!$E$6="IPCC AR5 Report(2013)",VLOOKUP($K31,'6.GWP'!$B$1:$G$173,5,FALSE),IF('1.GHG Inventory Form'!$E$6="IPCC AR6 Report(2021)",VLOOKUP($K31,'6.GWP'!$B$2:$G$173,6,FALSE),0))))),0)),0) -> 0 | AS31: =IF(AD31="V",IF('1.GHG Inventory Form'!$E$6="IPCC AR2 Report(1995)",'6.GWP'!$C$5,IF('1.GHG Inventory Form'!$E$6="IPCC AR3 Report(2001)",'6.GWP'!$D$5,IF('1.GHG Inventory Form'!$E$6="IPCC AR4 Report(2007)",'6.GWP'!$E$5,IF('1.GHG Inventory Form'!$E$6="IPCC AR5 Report(2013)",'6.GWP'!$F$5,IF('1.GHG Inventory Form'!$E$6="IPCC AR6 Report(2021)",'6.GWP'!$G$5,0))))),0) -> 0 | AT31: =IF(AE31="V",IF('1.GHG Inventory Form'!$E$6="IPCC AR2 Report(1995)",'6.GWP'!$C$4,IF('1.GHG Inventory Form'!$E$6="IPCC AR3 Report(2001)",'6.GWP'!$D$4,IF('1.GHG Inventory Form'!$E$6="IPCC AR4 Report(2007)",'6.GWP'!$E$4,IF('1.GHG Inventory Form'!$E$6="IPCC AR5 Report(2013)",'6.GWP'!$F$4,IF('1.GHG Inventory Form'!$E$6="IPCC AR6 Report(2021)",'6.GWP'!$G$4,0))))),0) -> 0 | AU31: =IFERROR($L31*AF31*AN31,"") -> 0 | AV31: =IFERROR($L31*AG31*AO31,"") -> 0 | AW31: =IFERROR($L31*AH31*AP31,"") -> 0 | AX31: =IFERROR($L31*AI31*AQ31,"") -> 0 | AY31: =IFERROR($L31*AJ31*AR31,"") -> 0 | AZ31: =IFERROR($L31*AK31*AS31,"") -> 0 | BA31: =IFERROR($L31*AL31*AT31,"") -> 0 | BB31: =ROUND(SUM(AU31:BA31),4) -> 0 | BC31: =BB31/SUM($BB$16:$BB$99) -> 0 | BD31: =BB31/$BB$169 -> 0 | BI31: =IF(H31="","",IF(I31="預設值Default",H31&J31,IF(I31="自訂值Custom Value",H31&K31,""))) | BJ31: =IF(H31="其它設備，請說明","",IF(O31=0,"",O31)) | BK31: =IF(H31="","",IF(I31="預設值Default",AM31,IF(I31="自訂值Custom Value",X31,"")))
A32: 5 | M32: =IFERROR(IF(I32="預設值Default",VLOOKUP($J32,'4.Default Emission Factor'!$D:$V,16,FALSE),"請填寫自訂活動數據單位Please fill in Custom Unit"),"請選擇預設排放係數名稱Please Choose Default Fuel or Greenhouse Gas") -> 請填寫自訂活動數據單位Please fill in Custom Unit | Y32: =IF(AF32>0.0000000001,"V","") | Z32: =IF(AG32>0.0000000001,"V","") | AA32: =IF(AH32>0.0000000001,"V","") | AB32: =IF(AI32>0.0000000001,"V","") | AC32: =IF(AJ32>0.0000000001,"V","") | AD32: =IF(AK32>0.0000000001,"V","") | AE32: =IF(AL32>0.0000000001,"V","") | AF32: =IFERROR(IF($I32="預設值Default",ROUND(VLOOKUP($J32,'4.Default Emission Factor'!$D:$V,2,FALSE),10),IF($I32="自訂值Custom Value",P32,0)),0) -> 0 | AG32: =IFERROR(IF($I32="預設值Default",ROUND(VLOOKUP($J32,'4.Default Emission Factor'!$D:$V,4,FALSE),10),IF($I32="自訂值Custom Value",Q32,0)),0) -> 0 | AH32: =IFERROR(IF($I32="預設值Default",ROUND(VLOOKUP($J32,'4.Default Emission Factor'!$D:$V,6,FALSE),10),IF($I32="自訂值Custom Value",R32,0)),0) -> 0 | AI32: =IFERROR(IF($I32="預設值Default",ROUND(VLOOKUP($J32,'4.Default Emission Factor'!$D:$V,8,FALSE),10),IF($I32="自訂值Custom Value",S32,0)),0) -> 0 | AJ32: =IFERROR(IF($I32="預設值Default",ROUND(VLOOKUP($J32,'4.Default Emission Factor'!$D:$V,10,FALSE),10),IF($I32="自訂值Custom Value",T32,0)),0) -> 0 | AK32: =IFERROR(IF($I32="預設值Default",ROUND(VLOOKUP($J32,'4.Default Emission Factor'!$D:$V,12,FALSE),10),IF($I32="自訂值Custom Value",U32,0)),0) -> 0 | AL32: =IFERROR(IF($I32="預設值Default",ROUND(VLOOKUP($J32,'4.Default Emission Factor'!$D:$V,14,FALSE),10),IF($I32="自訂值Custom Value",V32,0)),0) -> 0 | AM32: =IFERROR(IF(I32="預設值Default",VLOOKUP($J32,'4.Default Emission Factor'!$D:$V,17,FALSE),IF(I32="自訂值Custom Value",X32,"")),"") | AN32: =IF(Y32="V",1,0) -> 0 | AO32: =IF(Z32="V",IF('1.GHG Inventory Form'!$E$6="IPCC AR2 Report(1995)",'6.GWP'!$C$2,IF('1.GHG Inventory Form'!$E$6="IPCC AR3 Report(2001)",'6.GWP'!$D$2,IF('1.GHG Inventory Form'!$E$6="IPCC AR4 Report(2007)",'6.GWP'!$E$2,IF('1.GHG Inventory Form'!$E$6="IPCC AR5 Report(2013)",'6.GWP'!$F$2,IF('1.GHG Inventory Form'!$E$6="IPCC AR6 Report(2021)",'6.GWP'!$G$2,0))))),0) -> 0 | AP32: =IF(AA32="V",IF('1.GHG Inventory Form'!$E$6="IPCC AR2 Report(1995)",'6.GWP'!$C$3,IF('1.GHG Inventory Form'!$E$6="IPCC AR3 Report(2001)",'6.GWP'!$D$3,IF('1.GHG Inventory Form'!$E$6="IPCC AR4 Report(2007)",'6.GWP'!$E$3,IF('1.GHG Inventory Form'!$E$6="IPCC AR5 Report(2013)",'6.GWP'!$F$3,IF('1.GHG Inventory Form'!$E$6="IPCC AR6 Report(2021)",'6.GWP'!$G$3,0))))),0) -> 0 | AQ32: =IFERROR(IF(AND(AB32="V",$I32="預設值"),IF('1.GHG Inventory Form'!$E$6="IPCC AR2 Report(1995)",VLOOKUP($J32,'6.GWP'!$B$1:$G$173,2,FALSE),IF('1.GHG Inventory Form'!$E$6="IPCC AR3 Report(2001)",VLOOKUP($J32,'6.GWP'!$B$1:$G$173,3,FALSE),IF('1.GHG Inventory Form'!$E$6="IPCC AR4 Report(2007)",VLOOKUP($J32,'6.GWP'!$B$1:$G$173,4,FALSE),IF('1.GHG Inventory Form'!$E$6="IPCC AR5 Report(2013)",VLOOKUP($J32,'6.GWP'!$B$1:$G$173,5,FALSE),IF('1.GHG Inventory Form'!$E$6="IPCC AR6 Report(2021)",VLOOKUP($J32,'6.GWP'!$B$2:$G$173,6,FALSE),0))))),IF(AND(AB32="V",$I32="自訂值"),IF('1.GHG Inventory Form'!$E$6="IPCC AR2 Report(1995)",VLOOKUP($K32,'6.GWP'!$B$1:$G$173,2,FALSE),IF('1.GHG Inventory Form'!$E$6="IPCC AR3 Report(2001)",VLOOKUP($K32,'6.GWP'!$B$1:$G$173,3,FALSE),IF('1.GHG Inventory Form'!$E$6="IPCC AR4 Report(2007)",VLOOKUP($K32,'6.GWP'!$B$1:$G$173,4,FALSE),IF('1.GHG Inventory Form'!$E$6="IPCC AR5 Report(2013)",VLOOKUP($K32,'6.GWP'!$B$1:$G$173,5,FALSE),IF('1.GHG Inventory Form'!$E$6="IPCC AR6 Report(2021)",VLOOKUP($K32,'6.GWP'!$B$2:$G$173,6,FALSE),0))))),0)),0) -> 0 | AR32: =IFERROR(IF(AND(AC32="V",$I32="預設值"),IF('1.GHG Inventory Form'!$E$6="IPCC AR2 Report(1995)",VLOOKUP($J32,'6.GWP'!$B$1:$G$173,2,FALSE),IF('1.GHG Inventory Form'!$E$6="IPCC AR3 Report(2001)",VLOOKUP($J32,'6.GWP'!$B$1:$G$173,3,FALSE),IF('1.GHG Inventory Form'!$E$6="IPCC AR4 Report(2007)",VLOOKUP($J32,'6.GWP'!$B$1:$G$173,4,FALSE),IF('1.GHG Inventory Form'!$E$6="IPCC AR5 Report(2013)",VLOOKUP($J32,'6.GWP'!$B$1:$G$173,5,FALSE),IF('1.GHG Inventory Form'!$E$6="IPCC AR6 Report(2021)",VLOOKUP($J32,'6.GWP'!$B$2:$G$173,6,FALSE),0))))),IF(AND(AC32="V",$I32="自訂值"),IF('1.GHG Inventory Form'!$E$6="IPCC AR2 Report(1995)",VLOOKUP($K32,'6.GWP'!$B$1:$G$173,2,FALSE),IF('1.GHG Inventory Form'!$E$6="IPCC AR3 Report(2001)",VLOOKUP($K32,'6.GWP'!$B$1:$G$173,3,FALSE),IF('1.GHG Inventory Form'!$E$6="IPCC AR4 Report(2007)",VLOOKUP($K32,'6.GWP'!$B$1:$G$173,4,FALSE),IF('1.GHG Inventory Form'!$E$6="IPCC AR5 Report(2013)",VLOOKUP($K32,'6.GWP'!$B$1:$G$173,5,FALSE),IF('1.GHG Inventory Form'!$E$6="IPCC AR6 Report(2021)",VLOOKUP($K32,'6.GWP'!$B$2:$G$173,6,FALSE),0))))),0)),0) -> 0 | AS32: =IF(AD32="V",IF('1.GHG Inventory Form'!$E$6="IPCC AR2 Report(1995)",'6.GWP'!$C$5,IF('1.GHG Inventory Form'!$E$6="IPCC AR3 Report(2001)",'6.GWP'!$D$5,IF('1.GHG Inventory Form'!$E$6="IPCC AR4 Report(2007)",'6.GWP'!$E$5,IF('1.GHG Inventory Form'!$E$6="IPCC AR5 Report(2013)",'6.GWP'!$F$5,IF('1.GHG Inventory Form'!$E$6="IPCC AR6 Report(2021)",'6.GWP'!$G$5,0))))),0) -> 0 | AT32: =IF(AE32="V",IF('1.GHG Inventory Form'!$E$6="IPCC AR2 Report(1995)",'6.GWP'!$C$4,IF('1.GHG Inventory Form'!$E$6="IPCC AR3 Report(2001)",'6.GWP'!$D$4,IF('1.GHG Inventory Form'!$E$6="IPCC AR4 Report(2007)",'6.GWP'!$E$4,IF('1.GHG Inventory Form'!$E$6="IPCC AR5 Report(2013)",'6.GWP'!$F$4,IF('1.GHG Inventory Form'!$E$6="IPCC AR6 Report(2021)",'6.GWP'!$G$4,0))))),0) -> 0 | AU32: =IFERROR($L32*AF32*AN32,"") -> 0 | AV32: =IFERROR($L32*AG32*AO32,"") -> 0 | AW32: =IFERROR($L32*AH32*AP32,"") -> 0 | AX32: =IFERROR($L32*AI32*AQ32,"") -> 0 | AY32: =IFERROR($L32*AJ32*AR32,"") -> 0 | AZ32: =IFERROR($L32*AK32*AS32,"") -> 0 | BA32: =IFERROR($L32*AL32*AT32,"") -> 0 | BB32: =ROUND(SUM(AU32:BA32),4) -> 0 | BC32: =BB32/SUM($BB$16:$BB$99) -> 0 | BD32: =BB32/$BB$169 -> 0 | BI32: =IF(H32="","",IF(I32="預設值Default",H32&J32,IF(I32="自訂值Custom Value",H32&K32,""))) | BJ32: =IF(H32="其它設備，請說明","",IF(O32=0,"",O32)) | BK32: =IF(H32="","",IF(I32="預設值Default",AM32,IF(I32="自訂值Custom Value",X32,"")))
A33: 6 | M33: =IFERROR(IF(I33="預設值Default",VLOOKUP($J33,'4.Default Emission Factor'!$D:$V,16,FALSE),"請填寫自訂活動數據單位Please fill in Custom Unit"),"請選擇預設排放係數名稱Please Choose Default Fuel or Greenhouse Gas") -> 請填寫自訂活動數據單位Please fill in Custom Unit | Y33: =IF(AF33>0.0000000001,"V","") | Z33: =IF(AG33>0.0000000001,"V","") | AA33: =IF(AH33>0.0000000001,"V","") | AB33: =IF(AI33>0.0000000001,"V","") | AC33: =IF(AJ33>0.0000000001,"V","") | AD33: =IF(AK33>0.0000000001,"V","") | AE33: =IF(AL33>0.0000000001,"V","") | AF33: =IFERROR(IF($I33="預設值Default",ROUND(VLOOKUP($J33,'4.Default Emission Factor'!$D:$V,2,FALSE),10),IF($I33="自訂值Custom Value",P33,0)),0) -> 0 | AG33: =IFERROR(IF($I33="預設值Default",ROUND(VLOOKUP($J33,'4.Default Emission Factor'!$D:$V,4,FALSE),10),IF($I33="自訂值Custom Value",Q33,0)),0) -> 0 | AH33: =IFERROR(IF($I33="預設值Default",ROUND(VLOOKUP($J33,'4.Default Emission Factor'!$D:$V,6,FALSE),10),IF($I33="自訂值Custom Value",R33,0)),0) -> 0 | AI33: =IFERROR(IF($I33="預設值Default",ROUND(VLOOKUP($J33,'4.Default Emission Factor'!$D:$V,8,FALSE),10),IF($I33="自訂值Custom Value",S33,0)),0) -> 0 | AJ33: =IFERROR(IF($I33="預設值Default",ROUND(VLOOKUP($J33,'4.Default Emission Factor'!$D:$V,10,FALSE),10),IF($I33="自訂值Custom Value",T33,0)),0) -> 0 | AK33: =IFERROR(IF($I33="預設值Default",ROUND(VLOOKUP($J33,'4.Default Emission Factor'!$D:$V,12,FALSE),10),IF($I33="自訂值Custom Value",U33,0)),0) -> 0 | AL33: =IFERROR(IF($I33="預設值Default",ROUND(VLOOKUP($J33,'4.Default Emission Factor'!$D:$V,14,FALSE),10),IF($I33="自訂值Custom Value",V33,0)),0) -> 0 | AM33: =IFERROR(IF(I33="預設值Default",VLOOKUP($J33,'4.Default Emission Factor'!$D:$V,17,FALSE),IF(I33="自訂值Custom Value",X33,"")),"") | AN33: =IF(Y33="V",1,0) -> 0 | AO33: =IF(Z33="V",IF('1.GHG Inventory Form'!$E$6="IPCC AR2 Report(1995)",'6.GWP'!$C$2,IF('1.GHG Inventory Form'!$E$6="IPCC AR3 Report(2001)",'6.GWP'!$D$2,IF('1.GHG Inventory Form'!$E$6="IPCC AR4 Report(2007)",'6.GWP'!$E$2,IF('1.GHG Inventory Form'!$E$6="IPCC AR5 Report(2013)",'6.GWP'!$F$2,IF('1.GHG Inventory Form'!$E$6="IPCC AR6 Report(2021)",'6.GWP'!$G$2,0))))),0) -> 0 | AP33: =IF(AA33="V",IF('1.GHG Inventory Form'!$E$6="IPCC AR2 Report(1995)",'6.GWP'!$C$3,IF('1.GHG Inventory Form'!$E$6="IPCC AR3 Report(2001)",'6.GWP'!$D$3,IF('1.GHG Inventory Form'!$E$6="IPCC AR4 Report(2007)",'6.GWP'!$E$3,IF('1.GHG Inventory Form'!$E$6="IPCC AR5 Report(2013)",'6.GWP'!$F$3,IF('1.GHG Inventory Form'!$E$6="IPCC AR6 Report(2021)",'6.GWP'!$G$3,0))))),0) -> 0 | AQ33: =IFERROR(IF(AND(AB33="V",$I33="預設值"),IF('1.GHG Inventory Form'!$E$6="IPCC AR2 Report(1995)",VLOOKUP($J33,'6.GWP'!$B$1:$G$173,2,FALSE),IF('1.GHG Inventory Form'!$E$6="IPCC AR3 Report(2001)",VLOOKUP($J33,'6.GWP'!$B$1:$G$173,3,FALSE),IF('1.GHG Inventory Form'!$E$6="IPCC AR4 Report(2007)",VLOOKUP($J33,'6.GWP'!$B$1:$G$173,4,FALSE),IF('1.GHG Inventory Form'!$E$6="IPCC AR5 Report(2013)",VLOOKUP($J33,'6.GWP'!$B$1:$G$173,5,FALSE),IF('1.GHG Inventory Form'!$E$6="IPCC AR6 Report(2021)",VLOOKUP($J33,'6.GWP'!$B$2:$G$173,6,FALSE),0))))),IF(AND(AB33="V",$I33="自訂值"),IF('1.GHG Inventory Form'!$E$6="IPCC AR2 Report(1995)",VLOOKUP($K33,'6.GWP'!$B$1:$G$173,2,FALSE),IF('1.GHG Inventory Form'!$E$6="IPCC AR3 Report(2001)",VLOOKUP($K33,'6.GWP'!$B$1:$G$173,3,FALSE),IF('1.GHG Inventory Form'!$E$6="IPCC AR4 Report(2007)",VLOOKUP($K33,'6.GWP'!$B$1:$G$173,4,FALSE),IF('1.GHG Inventory Form'!$E$6="IPCC AR5 Report(2013)",VLOOKUP($K33,'6.GWP'!$B$1:$G$173,5,FALSE),IF('1.GHG Inventory Form'!$E$6="IPCC AR6 Report(2021)",VLOOKUP($K33,'6.GWP'!$B$2:$G$173,6,FALSE),0))))),0)),0) -> 0 | AR33: =IFERROR(IF(AND(AC33="V",$I33="預設值"),IF('1.GHG Inventory Form'!$E$6="IPCC AR2 Report(1995)",VLOOKUP($J33,'6.GWP'!$B$1:$G$173,2,FALSE),IF('1.GHG Inventory Form'!$E$6="IPCC AR3 Report(2001)",VLOOKUP($J33,'6.GWP'!$B$1:$G$173,3,FALSE),IF('1.GHG Inventory Form'!$E$6="IPCC AR4 Report(2007)",VLOOKUP($J33,'6.GWP'!$B$1:$G$173,4,FALSE),IF('1.GHG Inventory Form'!$E$6="IPCC AR5 Report(2013)",VLOOKUP($J33,'6.GWP'!$B$1:$G$173,5,FALSE),IF('1.GHG Inventory Form'!$E$6="IPCC AR6 Report(2021)",VLOOKUP($J33,'6.GWP'!$B$2:$G$173,6,FALSE),0))))),IF(AND(AC33="V",$I33="自訂值"),IF('1.GHG Inventory Form'!$E$6="IPCC AR2 Report(1995)",VLOOKUP($K33,'6.GWP'!$B$1:$G$173,2,FALSE),IF('1.GHG Inventory Form'!$E$6="IPCC AR3 Report(2001)",VLOOKUP($K33,'6.GWP'!$B$1:$G$173,3,FALSE),IF('1.GHG Inventory Form'!$E$6="IPCC AR4 Report(2007)",VLOOKUP($K33,'6.GWP'!$B$1:$G$173,4,FALSE),IF('1.GHG Inventory Form'!$E$6="IPCC AR5 Report(2013)",VLOOKUP($K33,'6.GWP'!$B$1:$G$173,5,FALSE),IF('1.GHG Inventory Form'!$E$6="IPCC AR6 Report(2021)",VLOOKUP($K33,'6.GWP'!$B$2:$G$173,6,FALSE),0))))),0)),0) -> 0 | AS33: =IF(AD33="V",IF('1.GHG Inventory Form'!$E$6="IPCC AR2 Report(1995)",'6.GWP'!$C$5,IF('1.GHG Inventory Form'!$E$6="IPCC AR3 Report(2001)",'6.GWP'!$D$5,IF('1.GHG Inventory Form'!$E$6="IPCC AR4 Report(2007)",'6.GWP'!$E$5,IF('1.GHG Inventory Form'!$E$6="IPCC AR5 Report(2013)",'6.GWP'!$F$5,IF('1.GHG Inventory Form'!$E$6="IPCC AR6 Report(2021)",'6.GWP'!$G$5,0))))),0) -> 0 | AT33: =IF(AE33="V",IF('1.GHG Inventory Form'!$E$6="IPCC AR2 Report(1995)",'6.GWP'!$C$4,IF('1.GHG Inventory Form'!$E$6="IPCC AR3 Report(2001)",'6.GWP'!$D$4,IF('1.GHG Inventory Form'!$E$6="IPCC AR4 Report(2007)",'6.GWP'!$E$4,IF('1.GHG Inventory Form'!$E$6="IPCC AR5 Report(2013)",'6.GWP'!$F$4,IF('1.GHG Inventory Form'!$E$6="IPCC AR6 Report(2021)",'6.GWP'!$G$4,0))))),0) -> 0 | AU33: =IFERROR($L33*AF33*AN33,"") -> 0 | AV33: =IFERROR($L33*AG33*AO33,"") -> 0 | AW33: =IFERROR($L33*AH33*AP33,"") -> 0 | AX33: =IFERROR($L33*AI33*AQ33,"") -> 0 | AY33: =IFERROR($L33*AJ33*AR33,"") -> 0 | AZ33: =IFERROR($L33*AK33*AS33,"") -> 0 | BA33: =IFERROR($L33*AL33*AT33,"") -> 0 | BB33: =ROUND(SUM(AU33:BA33),4) -> 0 | BC33: =BB33/SUM($BB$16:$BB$99) -> 0 | BD33: =BB33/$BB$169 -> 0 | BI33: =IF(H33="","",IF(I33="預設值Default",H33&J33,IF(I33="自訂值Custom Value",H33&K33,""))) | BJ33: =IF(H33="其它設備，請說明","",IF(O33=0,"",O33)) | BK33: =IF(H33="","",IF(I33="預設值Default",AM33,IF(I33="自訂值Custom Value",X33,"")))
M34: =IFERROR(IF(I34="預設值Default",VLOOKUP($J34,'4.Default Emission Factor'!$D:$V,16,FALSE),"請填寫自訂活動數據單位Please fill in Custom Unit"),"請選擇預設排放係數名稱Please Choose Default Fuel or Greenhouse Gas") -> 請填寫自訂活動數據單位Please fill in Custom Unit | Y34: =IF(AF34>0.0000000001,"V","") | Z34: =IF(AG34>0.0000000001,"V","") | AA34: =IF(AH34>0.0000000001,"V","") | AB34: =IF(AI34>0.0000000001,"V","") | AC34: =IF(AJ34>0.0000000001,"V","") | AD34: =IF(AK34>0.0000000001,"V","") | AE34: =IF(AL34>0.0000000001,"V","") | AF34: =IFERROR(IF($I34="預設值Default",ROUND(VLOOKUP($J34,'4.Default Emission Factor'!$D:$V,2,FALSE),10),IF($I34="自訂值Custom Value",P34,0)),0) -> 0 | AG34: =IFERROR(IF($I34="預設值Default",ROUND(VLOOKUP($J34,'4.Default Emission Factor'!$D:$V,4,FALSE),10),IF($I34="自訂值Custom Value",Q34,0)),0) -> 0 | AH34: =IFERROR(IF($I34="預設值Default",ROUND(VLOOKUP($J34,'4.Default Emission Factor'!$D:$V,6,FALSE),10),IF($I34="自訂值Custom Value",R34,0)),0) -> 0 | AI34: =IFERROR(IF($I34="預設值Default",ROUND(VLOOKUP($J34,'4.Default Emission Factor'!$D:$V,8,FALSE),10),IF($I34="自訂值Custom Value",S34,0)),0) -> 0 | AJ34: =IFERROR(IF($I34="預設值Default",ROUND(VLOOKUP($J34,'4.Default Emission Factor'!$D:$V,10,FALSE),10),IF($I34="自訂值Custom Value",T34,0)),0) -> 0 | AK34: =IFERROR(IF($I34="預設值Default",ROUND(VLOOKUP($J34,'4.Default Emission Factor'!$D:$V,12,FALSE),10),IF($I34="自訂值Custom Value",U34,0)),0) -> 0 | AL34: =IFERROR(IF($I34="預設值Default",ROUND(VLOOKUP($J34,'4.Default Emission Factor'!$D:$V,14,FALSE),10),IF($I34="自訂值Custom Value",V34,0)),0) -> 0 | AM34: =IFERROR(IF(I34="預設值Default",VLOOKUP($J34,'4.Default Emission Factor'!$D:$V,17,FALSE),IF(I34="自訂值Custom Value",X34,"")),"") | AN34: =IF(Y34="V",1,0) -> 0 | AO34: =IF(Z34="V",IF('1.GHG Inventory Form'!$E$6="IPCC AR2 Report(1995)",'6.GWP'!$C$2,IF('1.GHG Inventory Form'!$E$6="IPCC AR3 Report(2001)",'6.GWP'!$D$2,IF('1.GHG Inventory Form'!$E$6="IPCC AR4 Report(2007)",'6.GWP'!$E$2,IF('1.GHG Inventory Form'!$E$6="IPCC AR5 Report(2013)",'6.GWP'!$F$2,IF('1.GHG Inventory Form'!$E$6="IPCC AR6 Report(2021)",'6.GWP'!$G$2,0))))),0) -> 0 | AP34: =IF(AA34="V",IF('1.GHG Inventory Form'!$E$6="IPCC AR2 Report(1995)",'6.GWP'!$C$3,IF('1.GHG Inventory Form'!$E$6="IPCC AR3 Report(2001)",'6.GWP'!$D$3,IF('1.GHG Inventory Form'!$E$6="IPCC AR4 Report(2007)",'6.GWP'!$E$3,IF('1.GHG Inventory Form'!$E$6="IPCC AR5 Report(2013)",'6.GWP'!$F$3,IF('1.GHG Inventory Form'!$E$6="IPCC AR6 Report(2021)",'6.GWP'!$G$3,0))))),0) -> 0 | AQ34: =IFERROR(IF(AND(AB34="V",$I34="預設值"),IF('1.GHG Inventory Form'!$E$6="IPCC AR2 Report(1995)",VLOOKUP($J34,'6.GWP'!$B$1:$G$173,2,FALSE),IF('1.GHG Inventory Form'!$E$6="IPCC AR3 Report(2001)",VLOOKUP($J34,'6.GWP'!$B$1:$G$173,3,FALSE),IF('1.GHG Inventory Form'!$E$6="IPCC AR4 Report(2007)",VLOOKUP($J34,'6.GWP'!$B$1:$G$173,4,FALSE),IF('1.GHG Inventory Form'!$E$6="IPCC AR5 Report(2013)",VLOOKUP($J34,'6.GWP'!$B$1:$G$173,5,FALSE),IF('1.GHG Inventory Form'!$E$6="IPCC AR6 Report(2021)",VLOOKUP($J34,'6.GWP'!$B$2:$G$173,6,FALSE),0))))),IF(AND(AB34="V",$I34="自訂值"),IF('1.GHG Inventory Form'!$E$6="IPCC AR2 Report(1995)",VLOOKUP($K34,'6.GWP'!$B$1:$G$173,2,FALSE),IF('1.GHG Inventory Form'!$E$6="IPCC AR3 Report(2001)",VLOOKUP($K34,'6.GWP'!$B$1:$G$173,3,FALSE),IF('1.GHG Inventory Form'!$E$6="IPCC AR4 Report(2007)",VLOOKUP($K34,'6.GWP'!$B$1:$G$173,4,FALSE),IF('1.GHG Inventory Form'!$E$6="IPCC AR5 Report(2013)",VLOOKUP($K34,'6.GWP'!$B$1:$G$173,5,FALSE),IF('1.GHG Inventory Form'!$E$6="IPCC AR6 Report(2021)",VLOOKUP($K34,'6.GWP'!$B$2:$G$173,6,FALSE),0))))),0)),0) -> 0 | AR34: =IFERROR(IF(AND(AC34="V",$I34="預設值"),IF('1.GHG Inventory Form'!$E$6="IPCC AR2 Report(1995)",VLOOKUP($J34,'6.GWP'!$B$1:$G$173,2,FALSE),IF('1.GHG Inventory Form'!$E$6="IPCC AR3 Report(2001)",VLOOKUP($J34,'6.GWP'!$B$1:$G$173,3,FALSE),IF('1.GHG Inventory Form'!$E$6="IPCC AR4 Report(2007)",VLOOKUP($J34,'6.GWP'!$B$1:$G$173,4,FALSE),IF('1.GHG Inventory Form'!$E$6="IPCC AR5 Report(2013)",VLOOKUP($J34,'6.GWP'!$B$1:$G$173,5,FALSE),IF('1.GHG Inventory Form'!$E$6="IPCC AR6 Report(2021)",VLOOKUP($J34,'6.GWP'!$B$2:$G$173,6,FALSE),0))))),IF(AND(AC34="V",$I34="自訂值"),IF('1.GHG Inventory Form'!$E$6="IPCC AR2 Report(1995)",VLOOKUP($K34,'6.GWP'!$B$1:$G$173,2,FALSE),IF('1.GHG Inventory Form'!$E$6="IPCC AR3 Report(2001)",VLOOKUP($K34,'6.GWP'!$B$1:$G$173,3,FALSE),IF('1.GHG Inventory Form'!$E$6="IPCC AR4 Report(2007)",VLOOKUP($K34,'6.GWP'!$B$1:$G$173,4,FALSE),IF('1.GHG Inventory Form'!$E$6="IPCC AR5 Report(2013)",VLOOKUP($K34,'6.GWP'!$B$1:$G$173,5,FALSE),IF('1.GHG Inventory Form'!$E$6="IPCC AR6 Report(2021)",VLOOKUP($K34,'6.GWP'!$B$2:$G$173,6,FALSE),0))))),0)),0) -> 0 | AS34: =IF(AD34="V",IF('1.GHG Inventory Form'!$E$6="IPCC AR2 Report(1995)",'6.GWP'!$C$5,IF('1.GHG Inventory Form'!$E$6="IPCC AR3 Report(2001)",'6.GWP'!$D$5,IF('1.GHG Inventory Form'!$E$6="IPCC AR4 Report(2007)",'6.GWP'!$E$5,IF('1.GHG Inventory Form'!$E$6="IPCC AR5 Report(2013)",'6.GWP'!$F$5,IF('1.GHG Inventory Form'!$E$6="IPCC AR6 Report(2021)",'6.GWP'!$G$5,0))))),0) -> 0 | AT34: =IF(AE34="V",IF('1.GHG Inventory Form'!$E$6="IPCC AR2 Report(1995)",'6.GWP'!$C$4,IF('1.GHG Inventory Form'!$E$6="IPCC AR3 Report(2001)",'6.GWP'!$D$4,IF('1.GHG Inventory Form'!$E$6="IPCC AR4 Report(2007)",'6.GWP'!$E$4,IF('1.GHG Inventory Form'!$E$6="IPCC AR5 Report(2013)",'6.GWP'!$F$4,IF('1.GHG Inventory Form'!$E$6="IPCC AR6 Report(2021)",'6.GWP'!$G$4,0))))),0) -> 0 | AU34: =IFERROR($L34*AF34*AN34,"") -> 0 | AV34: =IFERROR($L34*AG34*AO34,"") -> 0 | AW34: =IFERROR($L34*AH34*AP34,"") -> 0 | AX34: =IFERROR($L34*AI34*AQ34,"") -> 0 | AY34: =IFERROR($L34*AJ34*AR34,"") -> 0 | AZ34: =IFERROR($L34*AK34*AS34,"") -> 0 | BA34: =IFERROR($L34*AL34*AT34,"") -> 0 | BB34: =ROUND(SUM(AU34:BA34),4) -> 0 | BC34: =BB34/SUM($BB$16:$BB$99) -> 0 | BD34: =BB34/$BB$169 -> 0 | BI34: =IF(H34="","",IF(I34="預設值Default",H34&J34,IF(I34="自訂值Custom Value",H34&K34,""))) | BJ34: =IF(H34="其它設備，請說明","",IF(O34=0,"",O34)) | BK34: =IF(H34="","",IF(I34="預設值Default",AM34,IF(I34="自訂值Custom Value",X34,"")))
A35: 1 | C35: 1.3 | D35: 工業製程之直接製程排放及移除 Industrial Processes | M35: =IFERROR(IF(I35="預設值Default",VLOOKUP($J35,'4.Default Emission Factor'!$D:$V,16,FALSE),"請填寫自訂活動數據單位Please fill in Custom Unit"),"請選擇預設排放係數名稱Please Choose Default Fuel or Greenhouse Gas") -> 請填寫自訂活動數據單位Please fill in Custom Unit | Y35: =IF(AF35>0.0000000001,"V","") | Z35: =IF(AG35>0.0000000001,"V","") | AA35: =IF(AH35>0.0000000001,"V","") | AB35: =IF(AI35>0.0000000001,"V","") | AC35: =IF(AJ35>0.0000000001,"V","") | AD35: =IF(AK35>0.0000000001,"V","") | AE35: =IF(AL35>0.0000000001,"V","") | AF35: =IFERROR(IF($I35="預設值Default",ROUND(VLOOKUP($J35,'4.Default Emission Factor'!$D:$V,2,FALSE),10),IF($I35="自訂值Custom Value",P35,0)),0) -> 0 | AG35: =IFERROR(IF($I35="預設值Default",ROUND(VLOOKUP($J35,'4.Default Emission Factor'!$D:$V,4,FALSE),10),IF($I35="自訂值Custom Value",Q35,0)),0) -> 0 | AH35: =IFERROR(IF($I35="預設值Default",ROUND(VLOOKUP($J35,'4.Default Emission Factor'!$D:$V,6,FALSE),10),IF($I35="自訂值Custom Value",R35,0)),0) -> 0 | AI35: =IFERROR(IF($I35="預設值Default",ROUND(VLOOKUP($J35,'4.Default Emission Factor'!$D:$V,8,FALSE),10),IF($I35="自訂值Custom Value",S35,0)),0) -> 0 | AJ35: =IFERROR(IF($I35="預設值Default",ROUND(VLOOKUP($J35,'4.Default Emission Factor'!$D:$V,10,FALSE),10),IF($I35="自訂值Custom Value",T35,0)),0) -> 0 | AK35: =IFERROR(IF($I35="預設值Default",ROUND(VLOOKUP($J35,'4.Default Emission Factor'!$D:$V,12,FALSE),10),IF($I35="自訂值Custom Value",U35,0)),0) -> 0 | AL35: =IFERROR(IF($I35="預設值Default",ROUND(VLOOKUP($J35,'4.Default Emission Factor'!$D:$V,14,FALSE),10),IF($I35="自訂值Custom Value",V35,0)),0) -> 0 | AM35: =IFERROR(IF(I35="預設值Default",VLOOKUP($J35,'4.Default Emission Factor'!$D:$V,17,FALSE),IF(I35="自訂值Custom Value",X35,"")),"") | AN35: =IF(Y35="V",1,0) -> 0 | AO35: =IF(Z35="V",IF('1.GHG Inventory Form'!$E$6="IPCC AR2 Report(1995)",'6.GWP'!$C$2,IF('1.GHG Inventory Form'!$E$6="IPCC AR3 Report(2001)",'6.GWP'!$D$2,IF('1.GHG Inventory Form'!$E$6="IPCC AR4 Report(2007)",'6.GWP'!$E$2,IF('1.GHG Inventory Form'!$E$6="IPCC AR5 Report(2013)",'6.GWP'!$F$2,IF('1.GHG Inventory Form'!$E$6="IPCC AR6 Report(2021)",'6.GWP'!$G$2,0))))),0) -> 0 | AP35: =IF(AA35="V",IF('1.GHG Inventory Form'!$E$6="IPCC AR2 Report(1995)",'6.GWP'!$C$3,IF('1.GHG Inventory Form'!$E$6="IPCC AR3 Report(2001)",'6.GWP'!$D$3,IF('1.GHG Inventory Form'!$E$6="IPCC AR4 Report(2007)",'6.GWP'!$E$3,IF('1.GHG Inventory Form'!$E$6="IPCC AR5 Report(2013)",'6.GWP'!$F$3,IF('1.GHG Inventory Form'!$E$6="IPCC AR6 Report(2021)",'6.GWP'!$G$3,0))))),0) -> 0 | AQ35: =IFERROR(IF(AND(AB35="V",$I35="預設值"),IF('1.GHG Inventory Form'!$E$6="IPCC AR2 Report(1995)",VLOOKUP($J35,'6.GWP'!$B$1:$G$173,2,FALSE),IF('1.GHG Inventory Form'!$E$6="IPCC AR3 Report(2001)",VLOOKUP($J35,'6.GWP'!$B$1:$G$173,3,FALSE),IF('1.GHG Inventory Form'!$E$6="IPCC AR4 Report(2007)",VLOOKUP($J35,'6.GWP'!$B$1:$G$173,4,FALSE),IF('1.GHG Inventory Form'!$E$6="IPCC AR5 Report(2013)",VLOOKUP($J35,'6.GWP'!$B$1:$G$173,5,FALSE),IF('1.GHG Inventory Form'!$E$6="IPCC AR6 Report(2021)",VLOOKUP($J35,'6.GWP'!$B$2:$G$173,6,FALSE),0))))),IF(AND(AB35="V",$I35="自訂值"),IF('1.GHG Inventory Form'!$E$6="IPCC AR2 Report(1995)",VLOOKUP($K35,'6.GWP'!$B$1:$G$173,2,FALSE),IF('1.GHG Inventory Form'!$E$6="IPCC AR3 Report(2001)",VLOOKUP($K35,'6.GWP'!$B$1:$G$173,3,FALSE),IF('1.GHG Inventory Form'!$E$6="IPCC AR4 Report(2007)",VLOOKUP($K35,'6.GWP'!$B$1:$G$173,4,FALSE),IF('1.GHG Inventory Form'!$E$6="IPCC AR5 Report(2013)",VLOOKUP($K35,'6.GWP'!$B$1:$G$173,5,FALSE),IF('1.GHG Inventory Form'!$E$6="IPCC AR6 Report(2021)",VLOOKUP($K35,'6.GWP'!$B$2:$G$173,6,FALSE),0))))),0)),0) -> 0 | AR35: =IFERROR(IF(AND(AC35="V",$I35="預設值"),IF('1.GHG Inventory Form'!$E$6="IPCC AR2 Report(1995)",VLOOKUP($J35,'6.GWP'!$B$1:$G$173,2,FALSE),IF('1.GHG Inventory Form'!$E$6="IPCC AR3 Report(2001)",VLOOKUP($J35,'6.GWP'!$B$1:$G$173,3,FALSE),IF('1.GHG Inventory Form'!$E$6="IPCC AR4 Report(2007)",VLOOKUP($J35,'6.GWP'!$B$1:$G$173,4,FALSE),IF('1.GHG Inventory Form'!$E$6="IPCC AR5 Report(2013)",VLOOKUP($J35,'6.GWP'!$B$1:$G$173,5,FALSE),IF('1.GHG Inventory Form'!$E$6="IPCC AR6 Report(2021)",VLOOKUP($J35,'6.GWP'!$B$2:$G$173,6,FALSE),0))))),IF(AND(AC35="V",$I35="自訂值"),IF('1.GHG Inventory Form'!$E$6="IPCC AR2 Report(1995)",VLOOKUP($K35,'6.GWP'!$B$1:$G$173,2,FALSE),IF('1.GHG Inventory Form'!$E$6="IPCC AR3 Report(2001)",VLOOKUP($K35,'6.GWP'!$B$1:$G$173,3,FALSE),IF('1.GHG Inventory Form'!$E$6="IPCC AR4 Report(2007)",VLOOKUP($K35,'6.GWP'!$B$1:$G$173,4,FALSE),IF('1.GHG Inventory Form'!$E$6="IPCC AR5 Report(2013)",VLOOKUP($K35,'6.GWP'!$B$1:$G$173,5,FALSE),IF('1.GHG Inventory Form'!$E$6="IPCC AR6 Report(2021)",VLOOKUP($K35,'6.GWP'!$B$2:$G$173,6,FALSE),0))))),0)),0) -> 0 | AS35: =IF(AD35="V",IF('1.GHG Inventory Form'!$E$6="IPCC AR2 Report(1995)",'6.GWP'!$C$5,IF('1.GHG Inventory Form'!$E$6="IPCC AR3 Report(2001)",'6.GWP'!$D$5,IF('1.GHG Inventory Form'!$E$6="IPCC AR4 Report(2007)",'6.GWP'!$E$5,IF('1.GHG Inventory Form'!$E$6="IPCC AR5 Report(2013)",'6.GWP'!$F$5,IF('1.GHG Inventory Form'!$E$6="IPCC AR6 Report(2021)",'6.GWP'!$G$5,0))))),0) -> 0 | AT35: =IF(AE35="V",IF('1.GHG Inventory Form'!$E$6="IPCC AR2 Report(1995)",'6.GWP'!$C$4,IF('1.GHG Inventory Form'!$E$6="IPCC AR3 Report(2001)",'6.GWP'!$D$4,IF('1.GHG Inventory Form'!$E$6="IPCC AR4 Report(2007)",'6.GWP'!$E$4,IF('1.GHG Inventory Form'!$E$6="IPCC AR5 Report(2013)",'6.GWP'!$F$4,IF('1.GHG Inventory Form'!$E$6="IPCC AR6 Report(2021)",'6.GWP'!$G$4,0))))),0) -> 0 | AU35: =IFERROR($L35*AF35*AN35,"") -> 0 | AV35: =IFERROR($L35*AG35*AO35,"") -> 0 | AW35: =IFERROR($L35*AH35*AP35,"") -> 0 | AX35: =IFERROR($L35*AI35*AQ35,"") -> 0 | AY35: =IFERROR($L35*AJ35*AR35,"") -> 0 | AZ35: =IFERROR($L35*AK35*AS35,"") -> 0 | BA35: =IFERROR($L35*AL35*AT35,"") -> 0 | BB35: =ROUND(SUM(AU35:BA35),4) -> 0 | BC35: =BB35/SUM($BB$16:$BB$99) -> 0 | BD35: =BB35/$BB$169 -> 0 | BI35: =IF(H35="","",IF(I35="預設值Default",H35&J35,IF(I35="自訂值Custom Value",H35&K35,""))) | BJ35: =IF(H35="其它設備，請說明","",IF(O35=0,"",O35)) | BK35: =IF(H35="","",IF(I35="預設值Default",AM35,IF(I35="自訂值Custom Value",X35,"")))
A36: 2 | M36: =IFERROR(IF(I36="預設值Default",VLOOKUP($J36,'4.Default Emission Factor'!$D:$V,16,FALSE),"請填寫自訂活動數據單位Please fill in Custom Unit"),"請選擇預設排放係數名稱Please Choose Default Fuel or Greenhouse Gas") -> 請填寫自訂活動數據單位Please fill in Custom Unit | Y36: =IF(AF36>0.0000000001,"V","") | Z36: =IF(AG36>0.0000000001,"V","") | AA36: =IF(AH36>0.0000000001,"V","") | AB36: =IF(AI36>0.0000000001,"V","") | AC36: =IF(AJ36>0.0000000001,"V","") | AD36: =IF(AK36>0.0000000001,"V","") | AE36: =IF(AL36>0.0000000001,"V","") | AF36: =IFERROR(IF($I36="預設值Default",ROUND(VLOOKUP($J36,'4.Default Emission Factor'!$D:$V,2,FALSE),10),IF($I36="自訂值Custom Value",P36,0)),0) -> 0 | AG36: =IFERROR(IF($I36="預設值Default",ROUND(VLOOKUP($J36,'4.Default Emission Factor'!$D:$V,4,FALSE),10),IF($I36="自訂值Custom Value",Q36,0)),0) -> 0 | AH36: =IFERROR(IF($I36="預設值Default",ROUND(VLOOKUP($J36,'4.Default Emission Factor'!$D:$V,6,FALSE),10),IF($I36="自訂值Custom Value",R36,0)),0) -> 0 | AI36: =IFERROR(IF($I36="預設值Default",ROUND(VLOOKUP($J36,'4.Default Emission Factor'!$D:$V,8,FALSE),10),IF($I36="自訂值Custom Value",S36,0)),0) -> 0 | AJ36: =IFERROR(IF($I36="預設值Default",ROUND(VLOOKUP($J36,'4.Default Emission Factor'!$D:$V,10,FALSE),10),IF($I36="自訂值Custom Value",T36,0)),0) -> 0 | AK36: =IFERROR(IF($I36="預設值Default",ROUND(VLOOKUP($J36,'4.Default Emission Factor'!$D:$V,12,FALSE),10),IF($I36="自訂值Custom Value",U36,0)),0) -> 0 | AL36: =IFERROR(IF($I36="預設值Default",ROUND(VLOOKUP($J36,'4.Default Emission Factor'!$D:$V,14,FALSE),10),IF($I36="自訂值Custom Value",V36,0)),0) -> 0 | AM36: =IFERROR(IF(I36="預設值Default",VLOOKUP($J36,'4.Default Emission Factor'!$D:$V,17,FALSE),IF(I36="自訂值Custom Value",X36,"")),"") | AN36: =IF(Y36="V",1,0) -> 0 | AO36: =IF(Z36="V",IF('1.GHG Inventory Form'!$E$6="IPCC AR2 Report(1995)",'6.GWP'!$C$2,IF('1.GHG Inventory Form'!$E$6="IPCC AR3 Report(2001)",'6.GWP'!$D$2,IF('1.GHG Inventory Form'!$E$6="IPCC AR4 Report(2007)",'6.GWP'!$E$2,IF('1.GHG Inventory Form'!$E$6="IPCC AR5 Report(2013)",'6.GWP'!$F$2,IF('1.GHG Inventory Form'!$E$6="IPCC AR6 Report(2021)",'6.GWP'!$G$2,0))))),0) -> 0 | AP36: =IF(AA36="V",IF('1.GHG Inventory Form'!$E$6="IPCC AR2 Report(1995)",'6.GWP'!$C$3,IF('1.GHG Inventory Form'!$E$6="IPCC AR3 Report(2001)",'6.GWP'!$D$3,IF('1.GHG Inventory Form'!$E$6="IPCC AR4 Report(2007)",'6.GWP'!$E$3,IF('1.GHG Inventory Form'!$E$6="IPCC AR5 Report(2013)",'6.GWP'!$F$3,IF('1.GHG Inventory Form'!$E$6="IPCC AR6 Report(2021)",'6.GWP'!$G$3,0))))),0) -> 0 | AQ36: =IFERROR(IF(AND(AB36="V",$I36="預設值"),IF('1.GHG Inventory Form'!$E$6="IPCC AR2 Report(1995)",VLOOKUP($J36,'6.GWP'!$B$1:$G$173,2,FALSE),IF('1.GHG Inventory Form'!$E$6="IPCC AR3 Report(2001)",VLOOKUP($J36,'6.GWP'!$B$1:$G$173,3,FALSE),IF('1.GHG Inventory Form'!$E$6="IPCC AR4 Report(2007)",VLOOKUP($J36,'6.GWP'!$B$1:$G$173,4,FALSE),IF('1.GHG Inventory Form'!$E$6="IPCC AR5 Report(2013)",VLOOKUP($J36,'6.GWP'!$B$1:$G$173,5,FALSE),IF('1.GHG Inventory Form'!$E$6="IPCC AR6 Report(2021)",VLOOKUP($J36,'6.GWP'!$B$2:$G$173,6,FALSE),0))))),IF(AND(AB36="V",$I36="自訂值"),IF('1.GHG Inventory Form'!$E$6="IPCC AR2 Report(1995)",VLOOKUP($K36,'6.GWP'!$B$1:$G$173,2,FALSE),IF('1.GHG Inventory Form'!$E$6="IPCC AR3 Report(2001)",VLOOKUP($K36,'6.GWP'!$B$1:$G$173,3,FALSE),IF('1.GHG Inventory Form'!$E$6="IPCC AR4 Report(2007)",VLOOKUP($K36,'6.GWP'!$B$1:$G$173,4,FALSE),IF('1.GHG Inventory Form'!$E$6="IPCC AR5 Report(2013)",VLOOKUP($K36,'6.GWP'!$B$1:$G$173,5,FALSE),IF('1.GHG Inventory Form'!$E$6="IPCC AR6 Report(2021)",VLOOKUP($K36,'6.GWP'!$B$2:$G$173,6,FALSE),0))))),0)),0) -> 0 | AR36: =IFERROR(IF(AND(AC36="V",$I36="預設值"),IF('1.GHG Inventory Form'!$E$6="IPCC AR2 Report(1995)",VLOOKUP($J36,'6.GWP'!$B$1:$G$173,2,FALSE),IF('1.GHG Inventory Form'!$E$6="IPCC AR3 Report(2001)",VLOOKUP($J36,'6.GWP'!$B$1:$G$173,3,FALSE),IF('1.GHG Inventory Form'!$E$6="IPCC AR4 Report(2007)",VLOOKUP($J36,'6.GWP'!$B$1:$G$173,4,FALSE),IF('1.GHG Inventory Form'!$E$6="IPCC AR5 Report(2013)",VLOOKUP($J36,'6.GWP'!$B$1:$G$173,5,FALSE),IF('1.GHG Inventory Form'!$E$6="IPCC AR6 Report(2021)",VLOOKUP($J36,'6.GWP'!$B$2:$G$173,6,FALSE),0))))),IF(AND(AC36="V",$I36="自訂值"),IF('1.GHG Inventory Form'!$E$6="IPCC AR2 Report(1995)",VLOOKUP($K36,'6.GWP'!$B$1:$G$173,2,FALSE),IF('1.GHG Inventory Form'!$E$6="IPCC AR3 Report(2001)",VLOOKUP($K36,'6.GWP'!$B$1:$G$173,3,FALSE),IF('1.GHG Inventory Form'!$E$6="IPCC AR4 Report(2007)",VLOOKUP($K36,'6.GWP'!$B$1:$G$173,4,FALSE),IF('1.GHG Inventory Form'!$E$6="IPCC AR5 Report(2013)",VLOOKUP($K36,'6.GWP'!$B$1:$G$173,5,FALSE),IF('1.GHG Inventory Form'!$E$6="IPCC AR6 Report(2021)",VLOOKUP($K36,'6.GWP'!$B$2:$G$173,6,FALSE),0))))),0)),0) -> 0 | AS36: =IF(AD36="V",IF('1.GHG Inventory Form'!$E$6="IPCC AR2 Report(1995)",'6.GWP'!$C$5,IF('1.GHG Inventory Form'!$E$6="IPCC AR3 Report(2001)",'6.GWP'!$D$5,IF('1.GHG Inventory Form'!$E$6="IPCC AR4 Report(2007)",'6.GWP'!$E$5,IF('1.GHG Inventory Form'!$E$6="IPCC AR5 Report(2013)",'6.GWP'!$F$5,IF('1.GHG Inventory Form'!$E$6="IPCC AR6 Report(2021)",'6.GWP'!$G$5,0))))),0) -> 0 | AT36: =IF(AE36="V",IF('1.GHG Inventory Form'!$E$6="IPCC AR2 Report(1995)",'6.GWP'!$C$4,IF('1.GHG Inventory Form'!$E$6="IPCC AR3 Report(2001)",'6.GWP'!$D$4,IF('1.GHG Inventory Form'!$E$6="IPCC AR4 Report(2007)",'6.GWP'!$E$4,IF('1.GHG Inventory Form'!$E$6="IPCC AR5 Report(2013)",'6.GWP'!$F$4,IF('1.GHG Inventory Form'!$E$6="IPCC AR6 Report(2021)",'6.GWP'!$G$4,0))))),0) -> 0 | AU36: =IFERROR($L36*AF36*AN36,"") -> 0 | AV36: =IFERROR($L36*AG36*AO36,"") -> 0 | AW36: =IFERROR($L36*AH36*AP36,"") -> 0 | AX36: =IFERROR($L36*AI36*AQ36,"") -> 0 | AY36: =IFERROR($L36*AJ36*AR36,"") -> 0 | AZ36: =IFERROR($L36*AK36*AS36,"") -> 0 | BA36: =IFERROR($L36*AL36*AT36,"") -> 0 | BB36: =ROUND(SUM(AU36:BA36),4) -> 0 | BC36: =BB36/SUM($BB$16:$BB$99) -> 0 | BD36: =BB36/$BB$169 -> 0 | BI36: =IF(H36="","",IF(I36="預設值Default",H36&J36,IF(I36="自訂值Custom Value",H36&K36,""))) | BJ36: =IF(H36="其它設備，請說明","",IF(O36=0,"",O36)) | BK36: =IF(H36="","",IF(I36="預設值Default",AM36,IF(I36="自訂值Custom Value",X36,"")))
A37: 3 | M37: =IFERROR(IF(I37="預設值Default",VLOOKUP($J37,'4.Default Emission Factor'!$D:$V,16,FALSE),"請填寫自訂活動數據單位Please fill in Custom Unit"),"請選擇預設排放係數名稱Please Choose Default Fuel or Greenhouse Gas") -> 請填寫自訂活動數據單位Please fill in Custom Unit | Y37: =IF(AF37>0.0000000001,"V","") | Z37: =IF(AG37>0.0000000001,"V","") | AA37: =IF(AH37>0.0000000001,"V","") | AB37: =IF(AI37>0.0000000001,"V","") | AC37: =IF(AJ37>0.0000000001,"V","") | AD37: =IF(AK37>0.0000000001,"V","") | AE37: =IF(AL37>0.0000000001,"V","") | AF37: =IFERROR(IF($I37="預設值Default",ROUND(VLOOKUP($J37,'4.Default Emission Factor'!$D:$V,2,FALSE),10),IF($I37="自訂值Custom Value",P37,0)),0) -> 0 | AG37: =IFERROR(IF($I37="預設值Default",ROUND(VLOOKUP($J37,'4.Default Emission Factor'!$D:$V,4,FALSE),10),IF($I37="自訂值Custom Value",Q37,0)),0) -> 0 | AH37: =IFERROR(IF($I37="預設值Default",ROUND(VLOOKUP($J37,'4.Default Emission Factor'!$D:$V,6,FALSE),10),IF($I37="自訂值Custom Value",R37,0)),0) -> 0 | AI37: =IFERROR(IF($I37="預設值Default",ROUND(VLOOKUP($J37,'4.Default Emission Factor'!$D:$V,8,FALSE),10),IF($I37="自訂值Custom Value",S37,0)),0) -> 0 | AJ37: =IFERROR(IF($I37="預設值Default",ROUND(VLOOKUP($J37,'4.Default Emission Factor'!$D:$V,10,FALSE),10),IF($I37="自訂值Custom Value",T37,0)),0) -> 0 | AK37: =IFERROR(IF($I37="預設值Default",ROUND(VLOOKUP($J37,'4.Default Emission Factor'!$D:$V,12,FALSE),10),IF($I37="自訂值Custom Value",U37,0)),0) -> 0 | AL37: =IFERROR(IF($I37="預設值Default",ROUND(VLOOKUP($J37,'4.Default Emission Factor'!$D:$V,14,FALSE),10),IF($I37="自訂值Custom Value",V37,0)),0) -> 0 | AM37: =IFERROR(IF(I37="預設值Default",VLOOKUP($J37,'4.Default Emission Factor'!$D:$V,17,FALSE),IF(I37="自訂值Custom Value",X37,"")),"") | AN37: =IF(Y37="V",1,0) -> 0 | AO37: =IF(Z37="V",IF('1.GHG Inventory Form'!$E$6="IPCC AR2 Report(1995)",'6.GWP'!$C$2,IF('1.GHG Inventory Form'!$E$6="IPCC AR3 Report(2001)",'6.GWP'!$D$2,IF('1.GHG Inventory Form'!$E$6="IPCC AR4 Report(2007)",'6.GWP'!$E$2,IF('1.GHG Inventory Form'!$E$6="IPCC AR5 Report(2013)",'6.GWP'!$F$2,IF('1.GHG Inventory Form'!$E$6="IPCC AR6 Report(2021)",'6.GWP'!$G$2,0))))),0) -> 0 | AP37: =IF(AA37="V",IF('1.GHG Inventory Form'!$E$6="IPCC AR2 Report(1995)",'6.GWP'!$C$3,IF('1.GHG Inventory Form'!$E$6="IPCC AR3 Report(2001)",'6.GWP'!$D$3,IF('1.GHG Inventory Form'!$E$6="IPCC AR4 Report(2007)",'6.GWP'!$E$3,IF('1.GHG Inventory Form'!$E$6="IPCC AR5 Report(2013)",'6.GWP'!$F$3,IF('1.GHG Inventory Form'!$E$6="IPCC AR6 Report(2021)",'6.GWP'!$G$3,0))))),0) -> 0 | AQ37: =IFERROR(IF(AND(AB37="V",$I37="預設值"),IF('1.GHG Inventory Form'!$E$6="IPCC AR2 Report(1995)",VLOOKUP($J37,'6.GWP'!$B$1:$G$173,2,FALSE),IF('1.GHG Inventory Form'!$E$6="IPCC AR3 Report(2001)",VLOOKUP($J37,'6.GWP'!$B$1:$G$173,3,FALSE),IF('1.GHG Inventory Form'!$E$6="IPCC AR4 Report(2007)",VLOOKUP($J37,'6.GWP'!$B$1:$G$173,4,FALSE),IF('1.GHG Inventory Form'!$E$6="IPCC AR5 Report(2013)",VLOOKUP($J37,'6.GWP'!$B$1:$G$173,5,FALSE),IF('1.GHG Inventory Form'!$E$6="IPCC AR6 Report(2021)",VLOOKUP($J37,'6.GWP'!$B$2:$G$173,6,FALSE),0))))),IF(AND(AB37="V",$I37="自訂值"),IF('1.GHG Inventory Form'!$E$6="IPCC AR2 Report(1995)",VLOOKUP($K37,'6.GWP'!$B$1:$G$173,2,FALSE),IF('1.GHG Inventory Form'!$E$6="IPCC AR3 Report(2001)",VLOOKUP($K37,'6.GWP'!$B$1:$G$173,3,FALSE),IF('1.GHG Inventory Form'!$E$6="IPCC AR4 Report(2007)",VLOOKUP($K37,'6.GWP'!$B$1:$G$173,4,FALSE),IF('1.GHG Inventory Form'!$E$6="IPCC AR5 Report(2013)",VLOOKUP($K37,'6.GWP'!$B$1:$G$173,5,FALSE),IF('1.GHG Inventory Form'!$E$6="IPCC AR6 Report(2021)",VLOOKUP($K37,'6.GWP'!$B$2:$G$173,6,FALSE),0))))),0)),0) -> 0 | AR37: =IFERROR(IF(AND(AC37="V",$I37="預設值"),IF('1.GHG Inventory Form'!$E$6="IPCC AR2 Report(1995)",VLOOKUP($J37,'6.GWP'!$B$1:$G$173,2,FALSE),IF('1.GHG Inventory Form'!$E$6="IPCC AR3 Report(2001)",VLOOKUP($J37,'6.GWP'!$B$1:$G$173,3,FALSE),IF('1.GHG Inventory Form'!$E$6="IPCC AR4 Report(2007)",VLOOKUP($J37,'6.GWP'!$B$1:$G$173,4,FALSE),IF('1.GHG Inventory Form'!$E$6="IPCC AR5 Report(2013)",VLOOKUP($J37,'6.GWP'!$B$1:$G$173,5,FALSE),IF('1.GHG Inventory Form'!$E$6="IPCC AR6 Report(2021)",VLOOKUP($J37,'6.GWP'!$B$2:$G$173,6,FALSE),0))))),IF(AND(AC37="V",$I37="自訂值"),IF('1.GHG Inventory Form'!$E$6="IPCC AR2 Report(1995)",VLOOKUP($K37,'6.GWP'!$B$1:$G$173,2,FALSE),IF('1.GHG Inventory Form'!$E$6="IPCC AR3 Report(2001)",VLOOKUP($K37,'6.GWP'!$B$1:$G$173,3,FALSE),IF('1.GHG Inventory Form'!$E$6="IPCC AR4 Report(2007)",VLOOKUP($K37,'6.GWP'!$B$1:$G$173,4,FALSE),IF('1.GHG Inventory Form'!$E$6="IPCC AR5 Report(2013)",VLOOKUP($K37,'6.GWP'!$B$1:$G$173,5,FALSE),IF('1.GHG Inventory Form'!$E$6="IPCC AR6 Report(2021)",VLOOKUP($K37,'6.GWP'!$B$2:$G$173,6,FALSE),0))))),0)),0) -> 0 | AS37: =IF(AD37="V",IF('1.GHG Inventory Form'!$E$6="IPCC AR2 Report(1995)",'6.GWP'!$C$5,IF('1.GHG Inventory Form'!$E$6="IPCC AR3 Report(2001)",'6.GWP'!$D$5,IF('1.GHG Inventory Form'!$E$6="IPCC AR4 Report(2007)",'6.GWP'!$E$5,IF('1.GHG Inventory Form'!$E$6="IPCC AR5 Report(2013)",'6.GWP'!$F$5,IF('1.GHG Inventory Form'!$E$6="IPCC AR6 Report(2021)",'6.GWP'!$G$5,0))))),0) -> 0 | AT37: =IF(AE37="V",IF('1.GHG Inventory Form'!$E$6="IPCC AR2 Report(1995)",'6.GWP'!$C$4,IF('1.GHG Inventory Form'!$E$6="IPCC AR3 Report(2001)",'6.GWP'!$D$4,IF('1.GHG Inventory Form'!$E$6="IPCC AR4 Report(2007)",'6.GWP'!$E$4,IF('1.GHG Inventory Form'!$E$6="IPCC AR5 Report(2013)",'6.GWP'!$F$4,IF('1.GHG Inventory Form'!$E$6="IPCC AR6 Report(2021)",'6.GWP'!$G$4,0))))),0) -> 0 | AU37: =IFERROR($L37*AF37*AN37,"") -> 0 | AV37: =IFERROR($L37*AG37*AO37,"") -> 0 | AW37: =IFERROR($L37*AH37*AP37,"") -> 0 | AX37: =IFERROR($L37*AI37*AQ37,"") -> 0 | AY37: =IFERROR($L37*AJ37*AR37,"") -> 0 | AZ37: =IFERROR($L37*AK37*AS37,"") -> 0 | BA37: =IFERROR($L37*AL37*AT37,"") -> 0 | BB37: =ROUND(SUM(AU37:BA37),4) -> 0 | BC37: =BB37/SUM($BB$16:$BB$99) -> 0 | BD37: =BB37/$BB$169 -> 0 | BI37: =IF(H37="","",IF(I37="預設值Default",H37&J37,IF(I37="自訂值Custom Value",H37&K37,""))) | BJ37: =IF(H37="其它設備，請說明","",IF(O37=0,"",O37)) | BK37: =IF(H37="","",IF(I37="預設值Default",AM37,IF(I37="自訂值Custom Value",X37,"")))
A38: 4 | M38: =IFERROR(IF(I38="預設值Default",VLOOKUP($J38,'4.Default Emission Factor'!$D:$V,16,FALSE),"請填寫自訂活動數據單位Please fill in Custom Unit"),"請選擇預設排放係數名稱Please Choose Default Fuel or Greenhouse Gas") -> 請填寫自訂活動數據單位Please fill in Custom Unit | Y38: =IF(AF38>0.0000000001,"V","") | Z38: =IF(AG38>0.0000000001,"V","") | AA38: =IF(AH38>0.0000000001,"V","") | AB38: =IF(AI38>0.0000000001,"V","") | AC38: =IF(AJ38>0.0000000001,"V","") | AD38: =IF(AK38>0.0000000001,"V","") | AE38: =IF(AL38>0.0000000001,"V","") | AF38: =IFERROR(IF($I38="預設值Default",ROUND(VLOOKUP($J38,'4.Default Emission Factor'!$D:$V,2,FALSE),10),IF($I38="自訂值Custom Value",P38,0)),0) -> 0 | AG38: =IFERROR(IF($I38="預設值Default",ROUND(VLOOKUP($J38,'4.Default Emission Factor'!$D:$V,4,FALSE),10),IF($I38="自訂值Custom Value",Q38,0)),0) -> 0 | AH38: =IFERROR(IF($I38="預設值Default",ROUND(VLOOKUP($J38,'4.Default Emission Factor'!$D:$V,6,FALSE),10),IF($I38="自訂值Custom Value",R38,0)),0) -> 0 | AI38: =IFERROR(IF($I38="預設值Default",ROUND(VLOOKUP($J38,'4.Default Emission Factor'!$D:$V,8,FALSE),10),IF($I38="自訂值Custom Value",S38,0)),0) -> 0 | AJ38: =IFERROR(IF($I38="預設值Default",ROUND(VLOOKUP($J38,'4.Default Emission Factor'!$D:$V,10,FALSE),10),IF($I38="自訂值Custom Value",T38,0)),0) -> 0 | AK38: =IFERROR(IF($I38="預設值Default",ROUND(VLOOKUP($J38,'4.Default Emission Factor'!$D:$V,12,FALSE),10),IF($I38="自訂值Custom Value",U38,0)),0) -> 0 | AL38: =IFERROR(IF($I38="預設值Default",ROUND(VLOOKUP($J38,'4.Default Emission Factor'!$D:$V,14,FALSE),10),IF($I38="自訂值Custom Value",V38,0)),0) -> 0 | AM38: =IFERROR(IF(I38="預設值Default",VLOOKUP($J38,'4.Default Emission Factor'!$D:$V,17,FALSE),IF(I38="自訂值Custom Value",X38,"")),"") | AN38: =IF(Y38="V",1,0) -> 0 | AO38: =IF(Z38="V",IF('1.GHG Inventory Form'!$E$6="IPCC AR2 Report(1995)",'6.GWP'!$C$2,IF('1.GHG Inventory Form'!$E$6="IPCC AR3 Report(2001)",'6.GWP'!$D$2,IF('1.GHG Inventory Form'!$E$6="IPCC AR4 Report(2007)",'6.GWP'!$E$2,IF('1.GHG Inventory Form'!$E$6="IPCC AR5 Report(2013)",'6.GWP'!$F$2,IF('1.GHG Inventory Form'!$E$6="IPCC AR6 Report(2021)",'6.GWP'!$G$2,0))))),0) -> 0 | AP38: =IF(AA38="V",IF('1.GHG Inventory Form'!$E$6="IPCC AR2 Report(1995)",'6.GWP'!$C$3,IF('1.GHG Inventory Form'!$E$6="IPCC AR3 Report(2001)",'6.GWP'!$D$3,IF('1.GHG Inventory Form'!$E$6="IPCC AR4 Report(2007)",'6.GWP'!$E$3,IF('1.GHG Inventory Form'!$E$6="IPCC AR5 Report(2013)",'6.GWP'!$F$3,IF('1.GHG Inventory Form'!$E$6="IPCC AR6 Report(2021)",'6.GWP'!$G$3,0))))),0) -> 0 | AQ38: =IFERROR(IF(AND(AB38="V",$I38="預設值"),IF('1.GHG Inventory Form'!$E$6="IPCC AR2 Report(1995)",VLOOKUP($J38,'6.GWP'!$B$1:$G$173,2,FALSE),IF('1.GHG Inventory Form'!$E$6="IPCC AR3 Report(2001)",VLOOKUP($J38,'6.GWP'!$B$1:$G$173,3,FALSE),IF('1.GHG Inventory Form'!$E$6="IPCC AR4 Report(2007)",VLOOKUP($J38,'6.GWP'!$B$1:$G$173,4,FALSE),IF('1.GHG Inventory Form'!$E$6="IPCC AR5 Report(2013)",VLOOKUP($J38,'6.GWP'!$B$1:$G$173,5,FALSE),IF('1.GHG Inventory Form'!$E$6="IPCC AR6 Report(2021)",VLOOKUP($J38,'6.GWP'!$B$2:$G$173,6,FALSE),0))))),IF(AND(AB38="V",$I38="自訂值"),IF('1.GHG Inventory Form'!$E$6="IPCC AR2 Report(1995)",VLOOKUP($K38,'6.GWP'!$B$1:$G$173,2,FALSE),IF('1.GHG Inventory Form'!$E$6="IPCC AR3 Report(2001)",VLOOKUP($K38,'6.GWP'!$B$1:$G$173,3,FALSE),IF('1.GHG Inventory Form'!$E$6="IPCC AR4 Report(2007)",VLOOKUP($K38,'6.GWP'!$B$1:$G$173,4,FALSE),IF('1.GHG Inventory Form'!$E$6="IPCC AR5 Report(2013)",VLOOKUP($K38,'6.GWP'!$B$1:$G$173,5,FALSE),IF('1.GHG Inventory Form'!$E$6="IPCC AR6 Report(2021)",VLOOKUP($K38,'6.GWP'!$B$2:$G$173,6,FALSE),0))))),0)),0) -> 0 | AR38: =IFERROR(IF(AND(AC38="V",$I38="預設值"),IF('1.GHG Inventory Form'!$E$6="IPCC AR2 Report(1995)",VLOOKUP($J38,'6.GWP'!$B$1:$G$173,2,FALSE),IF('1.GHG Inventory Form'!$E$6="IPCC AR3 Report(2001)",VLOOKUP($J38,'6.GWP'!$B$1:$G$173,3,FALSE),IF('1.GHG Inventory Form'!$E$6="IPCC AR4 Report(2007)",VLOOKUP($J38,'6.GWP'!$B$1:$G$173,4,FALSE),IF('1.GHG Inventory Form'!$E$6="IPCC AR5 Report(2013)",VLOOKUP($J38,'6.GWP'!$B$1:$G$173,5,FALSE),IF('1.GHG Inventory Form'!$E$6="IPCC AR6 Report(2021)",VLOOKUP($J38,'6.GWP'!$B$2:$G$173,6,FALSE),0))))),IF(AND(AC38="V",$I38="自訂值"),IF('1.GHG Inventory Form'!$E$6="IPCC AR2 Report(1995)",VLOOKUP($K38,'6.GWP'!$B$1:$G$173,2,FALSE),IF('1.GHG Inventory Form'!$E$6="IPCC AR3 Report(2001)",VLOOKUP($K38,'6.GWP'!$B$1:$G$173,3,FALSE),IF('1.GHG Inventory Form'!$E$6="IPCC AR4 Report(2007)",VLOOKUP($K38,'6.GWP'!$B$1:$G$173,4,FALSE),IF('1.GHG Inventory Form'!$E$6="IPCC AR5 Report(2013)",VLOOKUP($K38,'6.GWP'!$B$1:$G$173,5,FALSE),IF('1.GHG Inventory Form'!$E$6="IPCC AR6 Report(2021)",VLOOKUP($K38,'6.GWP'!$B$2:$G$173,6,FALSE),0))))),0)),0) -> 0 | AS38: =IF(AD38="V",IF('1.GHG Inventory Form'!$E$6="IPCC AR2 Report(1995)",'6.GWP'!$C$5,IF('1.GHG Inventory Form'!$E$6="IPCC AR3 Report(2001)",'6.GWP'!$D$5,IF('1.GHG Inventory Form'!$E$6="IPCC AR4 Report(2007)",'6.GWP'!$E$5,IF('1.GHG Inventory Form'!$E$6="IPCC AR5 Report(2013)",'6.GWP'!$F$5,IF('1.GHG Inventory Form'!$E$6="IPCC AR6 Report(2021)",'6.GWP'!$G$5,0))))),0) -> 0 | AT38: =IF(AE38="V",IF('1.GHG Inventory Form'!$E$6="IPCC AR2 Report(1995)",'6.GWP'!$C$4,IF('1.GHG Inventory Form'!$E$6="IPCC AR3 Report(2001)",'6.GWP'!$D$4,IF('1.GHG Inventory Form'!$E$6="IPCC AR4 Report(2007)",'6.GWP'!$E$4,IF('1.GHG Inventory Form'!$E$6="IPCC AR5 Report(2013)",'6.GWP'!$F$4,IF('1.GHG Inventory Form'!$E$6="IPCC AR6 Report(2021)",'6.GWP'!$G$4,0))))),0) -> 0 | AU38: =IFERROR($L38*AF38*AN38,"") -> 0 | AV38: =IFERROR($L38*AG38*AO38,"") -> 0 | AW38: =IFERROR($L38*AH38*AP38,"") -> 0 | AX38: =IFERROR($L38*AI38*AQ38,"") -> 0 | AY38: =IFERROR($L38*AJ38*AR38,"") -> 0 | AZ38: =IFERROR($L38*AK38*AS38,"") -> 0 | BA38: =IFERROR($L38*AL38*AT38,"") -> 0 | BB38: =ROUND(SUM(AU38:BA38),4) -> 0 | BC38: =BB38/SUM($BB$16:$BB$99) -> 0 | BD38: =BB38/$BB$169 -> 0 | BI38: =IF(H38="","",IF(I38="預設值Default",H38&J38,IF(I38="自訂值Custom Value",H38&K38,""))) | BJ38: =IF(H38="其它設備，請說明","",IF(O38=0,"",O38)) | BK38: =IF(H38="","",IF(I38="預設值Default",AM38,IF(I38="自訂值Custom Value",X38,"")))
A39: 5 | M39: =IFERROR(IF(I39="預設值Default",VLOOKUP($J39,'4.Default Emission Factor'!$D:$V,16,FALSE),"請填寫自訂活動數據單位Please fill in Custom Unit"),"請選擇預設排放係數名稱Please Choose Default Fuel or Greenhouse Gas") -> 請填寫自訂活動數據單位Please fill in Custom Unit | Y39: =IF(AF39>0.0000000001,"V","") | Z39: =IF(AG39>0.0000000001,"V","") | AA39: =IF(AH39>0.0000000001,"V","") | AB39: =IF(AI39>0.0000000001,"V","") | AC39: =IF(AJ39>0.0000000001,"V","") | AD39: =IF(AK39>0.0000000001,"V","") | AE39: =IF(AL39>0.0000000001,"V","") | AF39: =IFERROR(IF($I39="預設值Default",ROUND(VLOOKUP($J39,'4.Default Emission Factor'!$D:$V,2,FALSE),10),IF($I39="自訂值Custom Value",P39,0)),0) -> 0 | AG39: =IFERROR(IF($I39="預設值Default",ROUND(VLOOKUP($J39,'4.Default Emission Factor'!$D:$V,4,FALSE),10),IF($I39="自訂值Custom Value",Q39,0)),0) -> 0 | AH39: =IFERROR(IF($I39="預設值Default",ROUND(VLOOKUP($J39,'4.Default Emission Factor'!$D:$V,6,FALSE),10),IF($I39="自訂值Custom Value",R39,0)),0) -> 0 | AI39: =IFERROR(IF($I39="預設值Default",ROUND(VLOOKUP($J39,'4.Default Emission Factor'!$D:$V,8,FALSE),10),IF($I39="自訂值Custom Value",S39,0)),0) -> 0 | AJ39: =IFERROR(IF($I39="預設值Default",ROUND(VLOOKUP($J39,'4.Default Emission Factor'!$D:$V,10,FALSE),10),IF($I39="自訂值Custom Value",T39,0)),0) -> 0 | AK39: =IFERROR(IF($I39="預設值Default",ROUND(VLOOKUP($J39,'4.Default Emission Factor'!$D:$V,12,FALSE),10),IF($I39="自訂值Custom Value",U39,0)),0) -> 0 | AL39: =IFERROR(IF($I39="預設值Default",ROUND(VLOOKUP($J39,'4.Default Emission Factor'!$D:$V,14,FALSE),10),IF($I39="自訂值Custom Value",V39,0)),0) -> 0 | AM39: =IFERROR(IF(I39="預設值Default",VLOOKUP($J39,'4.Default Emission Factor'!$D:$V,17,FALSE),IF(I39="自訂值Custom Value",X39,"")),"") | AN39: =IF(Y39="V",1,0) -> 0 | AO39: =IF(Z39="V",IF('1.GHG Inventory Form'!$E$6="IPCC AR2 Report(1995)",'6.GWP'!$C$2,IF('1.GHG Inventory Form'!$E$6="IPCC AR3 Report(2001)",'6.GWP'!$D$2,IF('1.GHG Inventory Form'!$E$6="IPCC AR4 Report(2007)",'6.GWP'!$E$2,IF('1.GHG Inventory Form'!$E$6="IPCC AR5 Report(2013)",'6.GWP'!$F$2,IF('1.GHG Inventory Form'!$E$6="IPCC AR6 Report(2021)",'6.GWP'!$G$2,0))))),0) -> 0 | AP39: =IF(AA39="V",IF('1.GHG Inventory Form'!$E$6="IPCC AR2 Report(1995)",'6.GWP'!$C$3,IF('1.GHG Inventory Form'!$E$6="IPCC AR3 Report(2001)",'6.GWP'!$D$3,IF('1.GHG Inventory Form'!$E$6="IPCC AR4 Report(2007)",'6.GWP'!$E$3,IF('1.GHG Inventory Form'!$E$6="IPCC AR5 Report(2013)",'6.GWP'!$F$3,IF('1.GHG Inventory Form'!$E$6="IPCC AR6 Report(2021)",'6.GWP'!$G$3,0))))),0) -> 0 | AQ39: =IFERROR(IF(AND(AB39="V",$I39="預設值"),IF('1.GHG Inventory Form'!$E$6="IPCC AR2 Report(1995)",VLOOKUP($J39,'6.GWP'!$B$1:$G$173,2,FALSE),IF('1.GHG Inventory Form'!$E$6="IPCC AR3 Report(2001)",VLOOKUP($J39,'6.GWP'!$B$1:$G$173,3,FALSE),IF('1.GHG Inventory Form'!$E$6="IPCC AR4 Report(2007)",VLOOKUP($J39,'6.GWP'!$B$1:$G$173,4,FALSE),IF('1.GHG Inventory Form'!$E$6="IPCC AR5 Report(2013)",VLOOKUP($J39,'6.GWP'!$B$1:$G$173,5,FALSE),IF('1.GHG Inventory Form'!$E$6="IPCC AR6 Report(2021)",VLOOKUP($J39,'6.GWP'!$B$2:$G$173,6,FALSE),0))))),IF(AND(AB39="V",$I39="自訂值"),IF('1.GHG Inventory Form'!$E$6="IPCC AR2 Report(1995)",VLOOKUP($K39,'6.GWP'!$B$1:$G$173,2,FALSE),IF('1.GHG Inventory Form'!$E$6="IPCC AR3 Report(2001)",VLOOKUP($K39,'6.GWP'!$B$1:$G$173,3,FALSE),IF('1.GHG Inventory Form'!$E$6="IPCC AR4 Report(2007)",VLOOKUP($K39,'6.GWP'!$B$1:$G$173,4,FALSE),IF('1.GHG Inventory Form'!$E$6="IPCC AR5 Report(2013)",VLOOKUP($K39,'6.GWP'!$B$1:$G$173,5,FALSE),IF('1.GHG Inventory Form'!$E$6="IPCC AR6 Report(2021)",VLOOKUP($K39,'6.GWP'!$B$2:$G$173,6,FALSE),0))))),0)),0) -> 0 | AR39: =IFERROR(IF(AND(AC39="V",$I39="預設值"),IF('1.GHG Inventory Form'!$E$6="IPCC AR2 Report(1995)",VLOOKUP($J39,'6.GWP'!$B$1:$G$173,2,FALSE),IF('1.GHG Inventory Form'!$E$6="IPCC AR3 Report(2001)",VLOOKUP($J39,'6.GWP'!$B$1:$G$173,3,FALSE),IF('1.GHG Inventory Form'!$E$6="IPCC AR4 Report(2007)",VLOOKUP($J39,'6.GWP'!$B$1:$G$173,4,FALSE),IF('1.GHG Inventory Form'!$E$6="IPCC AR5 Report(2013)",VLOOKUP($J39,'6.GWP'!$B$1:$G$173,5,FALSE),IF('1.GHG Inventory Form'!$E$6="IPCC AR6 Report(2021)",VLOOKUP($J39,'6.GWP'!$B$2:$G$173,6,FALSE),0))))),IF(AND(AC39="V",$I39="自訂值"),IF('1.GHG Inventory Form'!$E$6="IPCC AR2 Report(1995)",VLOOKUP($K39,'6.GWP'!$B$1:$G$173,2,FALSE),IF('1.GHG Inventory Form'!$E$6="IPCC AR3 Report(2001)",VLOOKUP($K39,'6.GWP'!$B$1:$G$173,3,FALSE),IF('1.GHG Inventory Form'!$E$6="IPCC AR4 Report(2007)",VLOOKUP($K39,'6.GWP'!$B$1:$G$173,4,FALSE),IF('1.GHG Inventory Form'!$E$6="IPCC AR5 Report(2013)",VLOOKUP($K39,'6.GWP'!$B$1:$G$173,5,FALSE),IF('1.GHG Inventory Form'!$E$6="IPCC AR6 Report(2021)",VLOOKUP($K39,'6.GWP'!$B$2:$G$173,6,FALSE),0))))),0)),0) -> 0 | AS39: =IF(AD39="V",IF('1.GHG Inventory Form'!$E$6="IPCC AR2 Report(1995)",'6.GWP'!$C$5,IF('1.GHG Inventory Form'!$E$6="IPCC AR3 Report(2001)",'6.GWP'!$D$5,IF('1.GHG Inventory Form'!$E$6="IPCC AR4 Report(2007)",'6.GWP'!$E$5,IF('1.GHG Inventory Form'!$E$6="IPCC AR5 Report(2013)",'6.GWP'!$F$5,IF('1.GHG Inventory Form'!$E$6="IPCC AR6 Report(2021)",'6.GWP'!$G$5,0))))),0) -> 0 | AT39: =IF(AE39="V",IF('1.GHG Inventory Form'!$E$6="IPCC AR2 Report(1995)",'6.GWP'!$C$4,IF('1.GHG Inventory Form'!$E$6="IPCC AR3 Report(2001)",'6.GWP'!$D$4,IF('1.GHG Inventory Form'!$E$6="IPCC AR4 Report(2007)",'6.GWP'!$E$4,IF('1.GHG Inventory Form'!$E$6="IPCC AR5 Report(2013)",'6.GWP'!$F$4,IF('1.GHG Inventory Form'!$E$6="IPCC AR6 Report(2021)",'6.GWP'!$G$4,0))))),0) -> 0 | AU39: =IFERROR($L39*AF39*AN39,"") -> 0 | AV39: =IFERROR($L39*AG39*AO39,"") -> 0 | AW39: =IFERROR($L39*AH39*AP39,"") -> 0 | AX39: =IFERROR($L39*AI39*AQ39,"") -> 0 | AY39: =IFERROR($L39*AJ39*AR39,"") -> 0 | AZ39: =IFERROR($L39*AK39*AS39,"") -> 0 | BA39: =IFERROR($L39*AL39*AT39,"") -> 0 | BB39: =ROUND(SUM(AU39:BA39),4) -> 0 | BC39: =BB39/SUM($BB$16:$BB$99) -> 0 | BD39: =BB39/$BB$169 -> 0 | BI39: =IF(H39="","",IF(I39="預設值Default",H39&J39,IF(I39="自訂值Custom Value",H39&K39,""))) | BJ39: =IF(H39="其它設備，請說明","",IF(O39=0,"",O39)) | BK39: =IF(H39="","",IF(I39="預設值Default",AM39,IF(I39="自訂值Custom Value",X39,"")))
A40: 6 | M40: =IFERROR(IF(I40="預設值Default",VLOOKUP($J40,'4.Default Emission Factor'!$D:$V,16,FALSE),"請填寫自訂活動數據單位Please fill in Custom Unit"),"請選擇預設排放係數名稱Please Choose Default Fuel or Greenhouse Gas") -> 請填寫自訂活動數據單位Please fill in Custom Unit | Y40: =IF(AF40>0.0000000001,"V","") | Z40: =IF(AG40>0.0000000001,"V","") | AA40: =IF(AH40>0.0000000001,"V","") | AB40: =IF(AI40>0.0000000001,"V","") | AC40: =IF(AJ40>0.0000000001,"V","") | AD40: =IF(AK40>0.0000000001,"V","") | AE40: =IF(AL40>0.0000000001,"V","") | AF40: =IFERROR(IF($I40="預設值Default",ROUND(VLOOKUP($J40,'4.Default Emission Factor'!$D:$V,2,FALSE),10),IF($I40="自訂值Custom Value",P40,0)),0) -> 0 | AG40: =IFERROR(IF($I40="預設值Default",ROUND(VLOOKUP($J40,'4.Default Emission Factor'!$D:$V,4,FALSE),10),IF($I40="自訂值Custom Value",Q40,0)),0) -> 0 | AH40: =IFERROR(IF($I40="預設值Default",ROUND(VLOOKUP($J40,'4.Default Emission Factor'!$D:$V,6,FALSE),10),IF($I40="自訂值Custom Value",R40,0)),0) -> 0 | AI40: =IFERROR(IF($I40="預設值Default",ROUND(VLOOKUP($J40,'4.Default Emission Factor'!$D:$V,8,FALSE),10),IF($I40="自訂值Custom Value",S40,0)),0) -> 0 | AJ40: =IFERROR(IF($I40="預設值Default",ROUND(VLOOKUP($J40,'4.Default Emission Factor'!$D:$V,10,FALSE),10),IF($I40="自訂值Custom Value",T40,0)),0) -> 0 | AK40: =IFERROR(IF($I40="預設值Default",ROUND(VLOOKUP($J40,'4.Default Emission Factor'!$D:$V,12,FALSE),10),IF($I40="自訂值Custom Value",U40,0)),0) -> 0 | AL40: =IFERROR(IF($I40="預設值Default",ROUND(VLOOKUP($J40,'4.Default Emission Factor'!$D:$V,14,FALSE),10),IF($I40="自訂值Custom Value",V40,0)),0) -> 0 | AM40: =IFERROR(IF(I40="預設值Default",VLOOKUP($J40,'4.Default Emission Factor'!$D:$V,17,FALSE),IF(I40="自訂值Custom Value",X40,"")),"") | AN40: =IF(Y40="V",1,0) -> 0 | AO40: =IF(Z40="V",IF('1.GHG Inventory Form'!$E$6="IPCC AR2 Report(1995)",'6.GWP'!$C$2,IF('1.GHG Inventory Form'!$E$6="IPCC AR3 Report(2001)",'6.GWP'!$D$2,IF('1.GHG Inventory Form'!$E$6="IPCC AR4 Report(2007)",'6.GWP'!$E$2,IF('1.GHG Inventory Form'!$E$6="IPCC AR5 Report(2013)",'6.GWP'!$F$2,IF('1.GHG Inventory Form'!$E$6="IPCC AR6 Report(2021)",'6.GWP'!$G$2,0))))),0) -> 0 | AP40: =IF(AA40="V",IF('1.GHG Inventory Form'!$E$6="IPCC AR2 Report(1995)",'6.GWP'!$C$3,IF('1.GHG Inventory Form'!$E$6="IPCC AR3 Report(2001)",'6.GWP'!$D$3,IF('1.GHG Inventory Form'!$E$6="IPCC AR4 Report(2007)",'6.GWP'!$E$3,IF('1.GHG Inventory Form'!$E$6="IPCC AR5 Report(2013)",'6.GWP'!$F$3,IF('1.GHG Inventory Form'!$E$6="IPCC AR6 Report(2021)",'6.GWP'!$G$3,0))))),0) -> 0 | AQ40: =IFERROR(IF(AND(AB40="V",$I40="預設值"),IF('1.GHG Inventory Form'!$E$6="IPCC AR2 Report(1995)",VLOOKUP($J40,'6.GWP'!$B$1:$G$173,2,FALSE),IF('1.GHG Inventory Form'!$E$6="IPCC AR3 Report(2001)",VLOOKUP($J40,'6.GWP'!$B$1:$G$173,3,FALSE),IF('1.GHG Inventory Form'!$E$6="IPCC AR4 Report(2007)",VLOOKUP($J40,'6.GWP'!$B$1:$G$173,4,FALSE),IF('1.GHG Inventory Form'!$E$6="IPCC AR5 Report(2013)",VLOOKUP($J40,'6.GWP'!$B$1:$G$173,5,FALSE),IF('1.GHG Inventory Form'!$E$6="IPCC AR6 Report(2021)",VLOOKUP($J40,'6.GWP'!$B$2:$G$173,6,FALSE),0))))),IF(AND(AB40="V",$I40="自訂值"),IF('1.GHG Inventory Form'!$E$6="IPCC AR2 Report(1995)",VLOOKUP($K40,'6.GWP'!$B$1:$G$173,2,FALSE),IF('1.GHG Inventory Form'!$E$6="IPCC AR3 Report(2001)",VLOOKUP($K40,'6.GWP'!$B$1:$G$173,3,FALSE),IF('1.GHG Inventory Form'!$E$6="IPCC AR4 Report(2007)",VLOOKUP($K40,'6.GWP'!$B$1:$G$173,4,FALSE),IF('1.GHG Inventory Form'!$E$6="IPCC AR5 Report(2013)",VLOOKUP($K40,'6.GWP'!$B$1:$G$173,5,FALSE),IF('1.GHG Inventory Form'!$E$6="IPCC AR6 Report(2021)",VLOOKUP($K40,'6.GWP'!$B$2:$G$173,6,FALSE),0))))),0)),0) -> 0 | AR40: =IFERROR(IF(AND(AC40="V",$I40="預設值"),IF('1.GHG Inventory Form'!$E$6="IPCC AR2 Report(1995)",VLOOKUP($J40,'6.GWP'!$B$1:$G$173,2,FALSE),IF('1.GHG Inventory Form'!$E$6="IPCC AR3 Report(2001)",VLOOKUP($J40,'6.GWP'!$B$1:$G$173,3,FALSE),IF('1.GHG Inventory Form'!$E$6="IPCC AR4 Report(2007)",VLOOKUP($J40,'6.GWP'!$B$1:$G$173,4,FALSE),IF('1.GHG Inventory Form'!$E$6="IPCC AR5 Report(2013)",VLOOKUP($J40,'6.GWP'!$B$1:$G$173,5,FALSE),IF('1.GHG Inventory Form'!$E$6="IPCC AR6 Report(2021)",VLOOKUP($J40,'6.GWP'!$B$2:$G$173,6,FALSE),0))))),IF(AND(AC40="V",$I40="自訂值"),IF('1.GHG Inventory Form'!$E$6="IPCC AR2 Report(1995)",VLOOKUP($K40,'6.GWP'!$B$1:$G$173,2,FALSE),IF('1.GHG Inventory Form'!$E$6="IPCC AR3 Report(2001)",VLOOKUP($K40,'6.GWP'!$B$1:$G$173,3,FALSE),IF('1.GHG Inventory Form'!$E$6="IPCC AR4 Report(2007)",VLOOKUP($K40,'6.GWP'!$B$1:$G$173,4,FALSE),IF('1.GHG Inventory Form'!$E$6="IPCC AR5 Report(2013)",VLOOKUP($K40,'6.GWP'!$B$1:$G$173,5,FALSE),IF('1.GHG Inventory Form'!$E$6="IPCC AR6 Report(2021)",VLOOKUP($K40,'6.GWP'!$B$2:$G$173,6,FALSE),0))))),0)),0) -> 0 | AS40: =IF(AD40="V",IF('1.GHG Inventory Form'!$E$6="IPCC AR2 Report(1995)",'6.GWP'!$C$5,IF('1.GHG Inventory Form'!$E$6="IPCC AR3 Report(2001)",'6.GWP'!$D$5,IF('1.GHG Inventory Form'!$E$6="IPCC AR4 Report(2007)",'6.GWP'!$E$5,IF('1.GHG Inventory Form'!$E$6="IPCC AR5 Report(2013)",'6.GWP'!$F$5,IF('1.GHG Inventory Form'!$E$6="IPCC AR6 Report(2021)",'6.GWP'!$G$5,0))))),0) -> 0 | AT40: =IF(AE40="V",IF('1.GHG Inventory Form'!$E$6="IPCC AR2 Report(1995)",'6.GWP'!$C$4,IF('1.GHG Inventory Form'!$E$6="IPCC AR3 Report(2001)",'6.GWP'!$D$4,IF('1.GHG Inventory Form'!$E$6="IPCC AR4 Report(2007)",'6.GWP'!$E$4,IF('1.GHG Inventory Form'!$E$6="IPCC AR5 Report(2013)",'6.GWP'!$F$4,IF('1.GHG Inventory Form'!$E$6="IPCC AR6 Report(2021)",'6.GWP'!$G$4,0))))),0) -> 0 | AU40: =IFERROR($L40*AF40*AN40,"") -> 0 | AV40: =IFERROR($L40*AG40*AO40,"") -> 0 | AW40: =IFERROR($L40*AH40*AP40,"") -> 0 | AX40: =IFERROR($L40*AI40*AQ40,"") -> 0 | AY40: =IFERROR($L40*AJ40*AR40,"") -> 0 | AZ40: =IFERROR($L40*AK40*AS40,"") -> 0 | BA40: =IFERROR($L40*AL40*AT40,"") -> 0 | BB40: =ROUND(SUM(AU40:BA40),4) -> 0 | BC40: =BB40/SUM($BB$16:$BB$99) -> 0 | BD40: =BB40/$BB$169 -> 0 | BI40: =IF(H40="","",IF(I40="預設值Default",H40&J40,IF(I40="自訂值Custom Value",H40&K40,""))) | BJ40: =IF(H40="其它設備，請說明","",IF(O40=0,"",O40)) | BK40: =IF(H40="","",IF(I40="預設值Default",AM40,IF(I40="自訂值Custom Value",X40,"")))
A41: 7 | M41: =IFERROR(IF(I41="預設值Default",VLOOKUP($J41,'4.Default Emission Factor'!$D:$V,16,FALSE),"請填寫自訂活動數據單位Please fill in Custom Unit"),"請選擇預設排放係數名稱Please Choose Default Fuel or Greenhouse Gas") -> 請填寫自訂活動數據單位Please fill in Custom Unit | Y41: =IF(AF41>0.0000000001,"V","") | Z41: =IF(AG41>0.0000000001,"V","") | AA41: =IF(AH41>0.0000000001,"V","") | AB41: =IF(AI41>0.0000000001,"V","") | AC41: =IF(AJ41>0.0000000001,"V","") | AD41: =IF(AK41>0.0000000001,"V","") | AE41: =IF(AL41>0.0000000001,"V","") | AF41: =IFERROR(IF($I41="預設值Default",ROUND(VLOOKUP($J41,'4.Default Emission Factor'!$D:$V,2,FALSE),10),IF($I41="自訂值Custom Value",P41,0)),0) -> 0 | AG41: =IFERROR(IF($I41="預設值Default",ROUND(VLOOKUP($J41,'4.Default Emission Factor'!$D:$V,4,FALSE),10),IF($I41="自訂值Custom Value",Q41,0)),0) -> 0 | AH41: =IFERROR(IF($I41="預設值Default",ROUND(VLOOKUP($J41,'4.Default Emission Factor'!$D:$V,6,FALSE),10),IF($I41="自訂值Custom Value",R41,0)),0) -> 0 | AI41: =IFERROR(IF($I41="預設值Default",ROUND(VLOOKUP($J41,'4.Default Emission Factor'!$D:$V,8,FALSE),10),IF($I41="自訂值Custom Value",S41,0)),0) -> 0 | AJ41: =IFERROR(IF($I41="預設值Default",ROUND(VLOOKUP($J41,'4.Default Emission Factor'!$D:$V,10,FALSE),10),IF($I41="自訂值Custom Value",T41,0)),0) -> 0 | AK41: =IFERROR(IF($I41="預設值Default",ROUND(VLOOKUP($J41,'4.Default Emission Factor'!$D:$V,12,FALSE),10),IF($I41="自訂值Custom Value",U41,0)),0) -> 0 | AL41: =IFERROR(IF($I41="預設值Default",ROUND(VLOOKUP($J41,'4.Default Emission Factor'!$D:$V,14,FALSE),10),IF($I41="自訂值Custom Value",V41,0)),0) -> 0 | AM41: =IFERROR(IF(I41="預設值Default",VLOOKUP($J41,'4.Default Emission Factor'!$D:$V,17,FALSE),IF(I41="自訂值Custom Value",X41,"")),"") | AN41: =IF(Y41="V",1,0) -> 0 | AO41: =IF(Z41="V",IF('1.GHG Inventory Form'!$E$6="IPCC AR2 Report(1995)",'6.GWP'!$C$2,IF('1.GHG Inventory Form'!$E$6="IPCC AR3 Report(2001)",'6.GWP'!$D$2,IF('1.GHG Inventory Form'!$E$6="IPCC AR4 Report(2007)",'6.GWP'!$E$2,IF('1.GHG Inventory Form'!$E$6="IPCC AR5 Report(2013)",'6.GWP'!$F$2,IF('1.GHG Inventory Form'!$E$6="IPCC AR6 Report(2021)",'6.GWP'!$G$2,0))))),0) -> 0 | AP41: =IF(AA41="V",IF('1.GHG Inventory Form'!$E$6="IPCC AR2 Report(1995)",'6.GWP'!$C$3,IF('1.GHG Inventory Form'!$E$6="IPCC AR3 Report(2001)",'6.GWP'!$D$3,IF('1.GHG Inventory Form'!$E$6="IPCC AR4 Report(2007)",'6.GWP'!$E$3,IF('1.GHG Inventory Form'!$E$6="IPCC AR5 Report(2013)",'6.GWP'!$F$3,IF('1.GHG Inventory Form'!$E$6="IPCC AR6 Report(2021)",'6.GWP'!$G$3,0))))),0) -> 0 | AQ41: =IFERROR(IF(AND(AB41="V",$I41="預設值"),IF('1.GHG Inventory Form'!$E$6="IPCC AR2 Report(1995)",VLOOKUP($J41,'6.GWP'!$B$1:$G$173,2,FALSE),IF('1.GHG Inventory Form'!$E$6="IPCC AR3 Report(2001)",VLOOKUP($J41,'6.GWP'!$B$1:$G$173,3,FALSE),IF('1.GHG Inventory Form'!$E$6="IPCC AR4 Report(2007)",VLOOKUP($J41,'6.GWP'!$B$1:$G$173,4,FALSE),IF('1.GHG Inventory Form'!$E$6="IPCC AR5 Report(2013)",VLOOKUP($J41,'6.GWP'!$B$1:$G$173,5,FALSE),IF('1.GHG Inventory Form'!$E$6="IPCC AR6 Report(2021)",VLOOKUP($J41,'6.GWP'!$B$2:$G$173,6,FALSE),0))))),IF(AND(AB41="V",$I41="自訂值"),IF('1.GHG Inventory Form'!$E$6="IPCC AR2 Report(1995)",VLOOKUP($K41,'6.GWP'!$B$1:$G$173,2,FALSE),IF('1.GHG Inventory Form'!$E$6="IPCC AR3 Report(2001)",VLOOKUP($K41,'6.GWP'!$B$1:$G$173,3,FALSE),IF('1.GHG Inventory Form'!$E$6="IPCC AR4 Report(2007)",VLOOKUP($K41,'6.GWP'!$B$1:$G$173,4,FALSE),IF('1.GHG Inventory Form'!$E$6="IPCC AR5 Report(2013)",VLOOKUP($K41,'6.GWP'!$B$1:$G$173,5,FALSE),IF('1.GHG Inventory Form'!$E$6="IPCC AR6 Report(2021)",VLOOKUP($K41,'6.GWP'!$B$2:$G$173,6,FALSE),0))))),0)),0) -> 0 | AR41: =IFERROR(IF(AND(AC41="V",$I41="預設值"),IF('1.GHG Inventory Form'!$E$6="IPCC AR2 Report(1995)",VLOOKUP($J41,'6.GWP'!$B$1:$G$173,2,FALSE),IF('1.GHG Inventory Form'!$E$6="IPCC AR3 Report(2001)",VLOOKUP($J41,'6.GWP'!$B$1:$G$173,3,FALSE),IF('1.GHG Inventory Form'!$E$6="IPCC AR4 Report(2007)",VLOOKUP($J41,'6.GWP'!$B$1:$G$173,4,FALSE),IF('1.GHG Inventory Form'!$E$6="IPCC AR5 Report(2013)",VLOOKUP($J41,'6.GWP'!$B$1:$G$173,5,FALSE),IF('1.GHG Inventory Form'!$E$6="IPCC AR6 Report(2021)",VLOOKUP($J41,'6.GWP'!$B$2:$G$173,6,FALSE),0))))),IF(AND(AC41="V",$I41="自訂值"),IF('1.GHG Inventory Form'!$E$6="IPCC AR2 Report(1995)",VLOOKUP($K41,'6.GWP'!$B$1:$G$173,2,FALSE),IF('1.GHG Inventory Form'!$E$6="IPCC AR3 Report(2001)",VLOOKUP($K41,'6.GWP'!$B$1:$G$173,3,FALSE),IF('1.GHG Inventory Form'!$E$6="IPCC AR4 Report(2007)",VLOOKUP($K41,'6.GWP'!$B$1:$G$173,4,FALSE),IF('1.GHG Inventory Form'!$E$6="IPCC AR5 Report(2013)",VLOOKUP($K41,'6.GWP'!$B$1:$G$173,5,FALSE),IF('1.GHG Inventory Form'!$E$6="IPCC AR6 Report(2021)",VLOOKUP($K41,'6.GWP'!$B$2:$G$173,6,FALSE),0))))),0)),0) -> 0 | AS41: =IF(AD41="V",IF('1.GHG Inventory Form'!$E$6="IPCC AR2 Report(1995)",'6.GWP'!$C$5,IF('1.GHG Inventory Form'!$E$6="IPCC AR3 Report(2001)",'6.GWP'!$D$5,IF('1.GHG Inventory Form'!$E$6="IPCC AR4 Report(2007)",'6.GWP'!$E$5,IF('1.GHG Inventory Form'!$E$6="IPCC AR5 Report(2013)",'6.GWP'!$F$5,IF('1.GHG Inventory Form'!$E$6="IPCC AR6 Report(2021)",'6.GWP'!$G$5,0))))),0) -> 0 | AT41: =IF(AE41="V",IF('1.GHG Inventory Form'!$E$6="IPCC AR2 Report(1995)",'6.GWP'!$C$4,IF('1.GHG Inventory Form'!$E$6="IPCC AR3 Report(2001)",'6.GWP'!$D$4,IF('1.GHG Inventory Form'!$E$6="IPCC AR4 Report(2007)",'6.GWP'!$E$4,IF('1.GHG Inventory Form'!$E$6="IPCC AR5 Report(2013)",'6.GWP'!$F$4,IF('1.GHG Inventory Form'!$E$6="IPCC AR6 Report(2021)",'6.GWP'!$G$4,0))))),0) -> 0 | AU41: =IFERROR($L41*AF41*AN41,"") -> 0 | AV41: =IFERROR($L41*AG41*AO41,"") -> 0 | AW41: =IFERROR($L41*AH41*AP41,"") -> 0 | AX41: =IFERROR($L41*AI41*AQ41,"") -> 0 | AY41: =IFERROR($L41*AJ41*AR41,"") -> 0 | AZ41: =IFERROR($L41*AK41*AS41,"") -> 0 | BA41: =IFERROR($L41*AL41*AT41,"") -> 0 | BB41: =ROUND(SUM(AU41:BA41),4) -> 0 | BC41: =BB41/SUM($BB$16:$BB$99) -> 0 | BD41: =BB41/$BB$169 -> 0 | BI41: =IF(H41="","",IF(I41="預設值Default",H41&J41,IF(I41="自訂值Custom Value",H41&K41,""))) | BJ41: =IF(H41="其它設備，請說明","",IF(O41=0,"",O41)) | BK41: =IF(H41="","",IF(I41="預設值Default",AM41,IF(I41="自訂值Custom Value",X41,"")))
M42: =IFERROR(IF(I42="預設值Default",VLOOKUP($J42,'4.Default Emission Factor'!$D:$V,16,FALSE),"請填寫自訂活動數據單位Please fill in Custom Unit"),"請選擇預設排放係數名稱Please Choose Default Fuel or Greenhouse Gas") -> 請填寫自訂活動數據單位Please fill in Custom Unit | Y42: =IF(AF42>0.0000000001,"V","") | Z42: =IF(AG42>0.0000000001,"V","") | AA42: =IF(AH42>0.0000000001,"V","") | AB42: =IF(AI42>0.0000000001,"V","") | AC42: =IF(AJ42>0.0000000001,"V","") | AD42: =IF(AK42>0.0000000001,"V","") | AE42: =IF(AL42>0.0000000001,"V","") | AF42: =IFERROR(IF($I42="預設值Default",ROUND(VLOOKUP($J42,'4.Default Emission Factor'!$D:$V,2,FALSE),10),IF($I42="自訂值Custom Value",P42,0)),0) -> 0 | AG42: =IFERROR(IF($I42="預設值Default",ROUND(VLOOKUP($J42,'4.Default Emission Factor'!$D:$V,4,FALSE),10),IF($I42="自訂值Custom Value",Q42,0)),0) -> 0 | AH42: =IFERROR(IF($I42="預設值Default",ROUND(VLOOKUP($J42,'4.Default Emission Factor'!$D:$V,6,FALSE),10),IF($I42="自訂值Custom Value",R42,0)),0) -> 0 | AI42: =IFERROR(IF($I42="預設值Default",ROUND(VLOOKUP($J42,'4.Default Emission Factor'!$D:$V,8,FALSE),10),IF($I42="自訂值Custom Value",S42,0)),0) -> 0 | AJ42: =IFERROR(IF($I42="預設值Default",ROUND(VLOOKUP($J42,'4.Default Emission Factor'!$D:$V,10,FALSE),10),IF($I42="自訂值Custom Value",T42,0)),0) -> 0 | AK42: =IFERROR(IF($I42="預設值Default",ROUND(VLOOKUP($J42,'4.Default Emission Factor'!$D:$V,12,FALSE),10),IF($I42="自訂值Custom Value",U42,0)),0) -> 0 | AL42: =IFERROR(IF($I42="預設值Default",ROUND(VLOOKUP($J42,'4.Default Emission Factor'!$D:$V,14,FALSE),10),IF($I42="自訂值Custom Value",V42,0)),0) -> 0 | AM42: =IFERROR(IF(I42="預設值Default",VLOOKUP($J42,'4.Default Emission Factor'!$D:$V,17,FALSE),IF(I42="自訂值Custom Value",X42,"")),"") | AN42: =IF(Y42="V",1,0) -> 0 | AO42: =IF(Z42="V",IF('1.GHG Inventory Form'!$E$6="IPCC AR2 Report(1995)",'6.GWP'!$C$2,IF('1.GHG Inventory Form'!$E$6="IPCC AR3 Report(2001)",'6.GWP'!$D$2,IF('1.GHG Inventory Form'!$E$6="IPCC AR4 Report(2007)",'6.GWP'!$E$2,IF('1.GHG Inventory Form'!$E$6="IPCC AR5 Report(2013)",'6.GWP'!$F$2,IF('1.GHG Inventory Form'!$E$6="IPCC AR6 Report(2021)",'6.GWP'!$G$2,0))))),0) -> 0 | AP42: =IF(AA42="V",IF('1.GHG Inventory Form'!$E$6="IPCC AR2 Report(1995)",'6.GWP'!$C$3,IF('1.GHG Inventory Form'!$E$6="IPCC AR3 Report(2001)",'6.GWP'!$D$3,IF('1.GHG Inventory Form'!$E$6="IPCC AR4 Report(2007)",'6.GWP'!$E$3,IF('1.GHG Inventory Form'!$E$6="IPCC AR5 Report(2013)",'6.GWP'!$F$3,IF('1.GHG Inventory Form'!$E$6="IPCC AR6 Report(2021)",'6.GWP'!$G$3,0))))),0) -> 0 | AQ42: =IFERROR(IF(AND(AB42="V",$I42="預設值"),IF('1.GHG Inventory Form'!$E$6="IPCC AR2 Report(1995)",VLOOKUP($J42,'6.GWP'!$B$1:$G$173,2,FALSE),IF('1.GHG Inventory Form'!$E$6="IPCC AR3 Report(2001)",VLOOKUP($J42,'6.GWP'!$B$1:$G$173,3,FALSE),IF('1.GHG Inventory Form'!$E$6="IPCC AR4 Report(2007)",VLOOKUP($J42,'6.GWP'!$B$1:$G$173,4,FALSE),IF('1.GHG Inventory Form'!$E$6="IPCC AR5 Report(2013)",VLOOKUP($J42,'6.GWP'!$B$1:$G$173,5,FALSE),IF('1.GHG Inventory Form'!$E$6="IPCC AR6 Report(2021)",VLOOKUP($J42,'6.GWP'!$B$2:$G$173,6,FALSE),0))))),IF(AND(AB42="V",$I42="自訂值"),IF('1.GHG Inventory Form'!$E$6="IPCC AR2 Report(1995)",VLOOKUP($K42,'6.GWP'!$B$1:$G$173,2,FALSE),IF('1.GHG Inventory Form'!$E$6="IPCC AR3 Report(2001)",VLOOKUP($K42,'6.GWP'!$B$1:$G$173,3,FALSE),IF('1.GHG Inventory Form'!$E$6="IPCC AR4 Report(2007)",VLOOKUP($K42,'6.GWP'!$B$1:$G$173,4,FALSE),IF('1.GHG Inventory Form'!$E$6="IPCC AR5 Report(2013)",VLOOKUP($K42,'6.GWP'!$B$1:$G$173,5,FALSE),IF('1.GHG Inventory Form'!$E$6="IPCC AR6 Report(2021)",VLOOKUP($K42,'6.GWP'!$B$2:$G$173,6,FALSE),0))))),0)),0) -> 0 | AR42: =IFERROR(IF(AND(AC42="V",$I42="預設值"),IF('1.GHG Inventory Form'!$E$6="IPCC AR2 Report(1995)",VLOOKUP($J42,'6.GWP'!$B$1:$G$173,2,FALSE),IF('1.GHG Inventory Form'!$E$6="IPCC AR3 Report(2001)",VLOOKUP($J42,'6.GWP'!$B$1:$G$173,3,FALSE),IF('1.GHG Inventory Form'!$E$6="IPCC AR4 Report(2007)",VLOOKUP($J42,'6.GWP'!$B$1:$G$173,4,FALSE),IF('1.GHG Inventory Form'!$E$6="IPCC AR5 Report(2013)",VLOOKUP($J42,'6.GWP'!$B$1:$G$173,5,FALSE),IF('1.GHG Inventory Form'!$E$6="IPCC AR6 Report(2021)",VLOOKUP($J42,'6.GWP'!$B$2:$G$173,6,FALSE),0))))),IF(AND(AC42="V",$I42="自訂值"),IF('1.GHG Inventory Form'!$E$6="IPCC AR2 Report(1995)",VLOOKUP($K42,'6.GWP'!$B$1:$G$173,2,FALSE),IF('1.GHG Inventory Form'!$E$6="IPCC AR3 Report(2001)",VLOOKUP($K42,'6.GWP'!$B$1:$G$173,3,FALSE),IF('1.GHG Inventory Form'!$E$6="IPCC AR4 Report(2007)",VLOOKUP($K42,'6.GWP'!$B$1:$G$173,4,FALSE),IF('1.GHG Inventory Form'!$E$6="IPCC AR5 Report(2013)",VLOOKUP($K42,'6.GWP'!$B$1:$G$173,5,FALSE),IF('1.GHG Inventory Form'!$E$6="IPCC AR6 Report(2021)",VLOOKUP($K42,'6.GWP'!$B$2:$G$173,6,FALSE),0))))),0)),0) -> 0 | AS42: =IF(AD42="V",IF('1.GHG Inventory Form'!$E$6="IPCC AR2 Report(1995)",'6.GWP'!$C$5,IF('1.GHG Inventory Form'!$E$6="IPCC AR3 Report(2001)",'6.GWP'!$D$5,IF('1.GHG Inventory Form'!$E$6="IPCC AR4 Report(2007)",'6.GWP'!$E$5,IF('1.GHG Inventory Form'!$E$6="IPCC AR5 Report(2013)",'6.GWP'!$F$5,IF('1.GHG Inventory Form'!$E$6="IPCC AR6 Report(2021)",'6.GWP'!$G$5,0))))),0) -> 0 | AT42: =IF(AE42="V",IF('1.GHG Inventory Form'!$E$6="IPCC AR2 Report(1995)",'6.GWP'!$C$4,IF('1.GHG Inventory Form'!$E$6="IPCC AR3 Report(2001)",'6.GWP'!$D$4,IF('1.GHG Inventory Form'!$E$6="IPCC AR4 Report(2007)",'6.GWP'!$E$4,IF('1.GHG Inventory Form'!$E$6="IPCC AR5 Report(2013)",'6.GWP'!$F$4,IF('1.GHG Inventory Form'!$E$6="IPCC AR6 Report(2021)",'6.GWP'!$G$4,0))))),0) -> 0 | AU42: =IFERROR($L42*AF42*AN42,"") -> 0 | AV42: =IFERROR($L42*AG42*AO42,"") -> 0 | AW42: =IFERROR($L42*AH42*AP42,"") -> 0 | AX42: =IFERROR($L42*AI42*AQ42,"") -> 0 | AY42: =IFERROR($L42*AJ42*AR42,"") -> 0 | AZ42: =IFERROR($L42*AK42*AS42,"") -> 0 | BA42: =IFERROR($L42*AL42*AT42,"") -> 0 | BB42: =ROUND(SUM(AU42:BA42),4) -> 0 | BC42: =BB42/SUM($BB$16:$BB$99) -> 0 | BD42: =BB42/$BB$169 -> 0 | BI42: =IF(H42="","",IF(I42="預設值Default",H42&J42,IF(I42="自訂值Custom Value",H42&K42,""))) | BJ42: =IF(H42="其它設備，請說明","",IF(O42=0,"",O42)) | BK42: =IF(H42="","",IF(I42="預設值Default",AM42,IF(I42="自訂值Custom Value",X42,"")))
M43: =IFERROR(IF(I43="預設值Default",VLOOKUP($J43,'4.Default Emission Factor'!$D:$V,16,FALSE),"請填寫自訂活動數據單位Please fill in Custom Unit"),"請選擇預設排放係數名稱Please Choose Default Fuel or Greenhouse Gas") -> 請填寫自訂活動數據單位Please fill in Custom Unit | Y43: =IF(AF43>0.0000000001,"V","") | Z43: =IF(AG43>0.0000000001,"V","") | AA43: =IF(AH43>0.0000000001,"V","") | AB43: =IF(AI43>0.0000000001,"V","") | AC43: =IF(AJ43>0.0000000001,"V","") | AD43: =IF(AK43>0.0000000001,"V","") | AE43: =IF(AL43>0.0000000001,"V","") | AF43: =IFERROR(IF($I43="預設值Default",ROUND(VLOOKUP($J43,'4.Default Emission Factor'!$D:$V,2,FALSE),10),IF($I43="自訂值Custom Value",P43,0)),0) -> 0 | AG43: =IFERROR(IF($I43="預設值Default",ROUND(VLOOKUP($J43,'4.Default Emission Factor'!$D:$V,4,FALSE),10),IF($I43="自訂值Custom Value",Q43,0)),0) -> 0 | AH43: =IFERROR(IF($I43="預設值Default",ROUND(VLOOKUP($J43,'4.Default Emission Factor'!$D:$V,6,FALSE),10),IF($I43="自訂值Custom Value",R43,0)),0) -> 0 | AI43: =IFERROR(IF($I43="預設值Default",ROUND(VLOOKUP($J43,'4.Default Emission Factor'!$D:$V,8,FALSE),10),IF($I43="自訂值Custom Value",S43,0)),0) -> 0 | AJ43: =IFERROR(IF($I43="預設值Default",ROUND(VLOOKUP($J43,'4.Default Emission Factor'!$D:$V,10,FALSE),10),IF($I43="自訂值Custom Value",T43,0)),0) -> 0 | AK43: =IFERROR(IF($I43="預設值Default",ROUND(VLOOKUP($J43,'4.Default Emission Factor'!$D:$V,12,FALSE),10),IF($I43="自訂值Custom Value",U43,0)),0) -> 0 | AL43: =IFERROR(IF($I43="預設值Default",ROUND(VLOOKUP($J43,'4.Default Emission Factor'!$D:$V,14,FALSE),10),IF($I43="自訂值Custom Value",V43,0)),0) -> 0 | AM43: =IFERROR(IF(I43="預設值Default",VLOOKUP($J43,'4.Default Emission Factor'!$D:$V,17,FALSE),IF(I43="自訂值Custom Value",X43,"")),"") | AN43: =IF(Y43="V",1,0) -> 0 | AO43: =IF(Z43="V",IF('1.GHG Inventory Form'!$E$6="IPCC AR2 Report(1995)",'6.GWP'!$C$2,IF('1.GHG Inventory Form'!$E$6="IPCC AR3 Report(2001)",'6.GWP'!$D$2,IF('1.GHG Inventory Form'!$E$6="IPCC AR4 Report(2007)",'6.GWP'!$E$2,IF('1.GHG Inventory Form'!$E$6="IPCC AR5 Report(2013)",'6.GWP'!$F$2,IF('1.GHG Inventory Form'!$E$6="IPCC AR6 Report(2021)",'6.GWP'!$G$2,0))))),0) -> 0 | AP43: =IF(AA43="V",IF('1.GHG Inventory Form'!$E$6="IPCC AR2 Report(1995)",'6.GWP'!$C$3,IF('1.GHG Inventory Form'!$E$6="IPCC AR3 Report(2001)",'6.GWP'!$D$3,IF('1.GHG Inventory Form'!$E$6="IPCC AR4 Report(2007)",'6.GWP'!$E$3,IF('1.GHG Inventory Form'!$E$6="IPCC AR5 Report(2013)",'6.GWP'!$F$3,IF('1.GHG Inventory Form'!$E$6="IPCC AR6 Report(2021)",'6.GWP'!$G$3,0))))),0) -> 0 | AQ43: =IFERROR(IF(AND(AB43="V",$I43="預設值"),IF('1.GHG Inventory Form'!$E$6="IPCC AR2 Report(1995)",VLOOKUP($J43,'6.GWP'!$B$1:$G$173,2,FALSE),IF('1.GHG Inventory Form'!$E$6="IPCC AR3 Report(2001)",VLOOKUP($J43,'6.GWP'!$B$1:$G$173,3,FALSE),IF('1.GHG Inventory Form'!$E$6="IPCC AR4 Report(2007)",VLOOKUP($J43,'6.GWP'!$B$1:$G$173,4,FALSE),IF('1.GHG Inventory Form'!$E$6="IPCC AR5 Report(2013)",VLOOKUP($J43,'6.GWP'!$B$1:$G$173,5,FALSE),IF('1.GHG Inventory Form'!$E$6="IPCC AR6 Report(2021)",VLOOKUP($J43,'6.GWP'!$B$2:$G$173,6,FALSE),0))))),IF(AND(AB43="V",$I43="自訂值"),IF('1.GHG Inventory Form'!$E$6="IPCC AR2 Report(1995)",VLOOKUP($K43,'6.GWP'!$B$1:$G$173,2,FALSE),IF('1.GHG Inventory Form'!$E$6="IPCC AR3 Report(2001)",VLOOKUP($K43,'6.GWP'!$B$1:$G$173,3,FALSE),IF('1.GHG Inventory Form'!$E$6="IPCC AR4 Report(2007)",VLOOKUP($K43,'6.GWP'!$B$1:$G$173,4,FALSE),IF('1.GHG Inventory Form'!$E$6="IPCC AR5 Report(2013)",VLOOKUP($K43,'6.GWP'!$B$1:$G$173,5,FALSE),IF('1.GHG Inventory Form'!$E$6="IPCC AR6 Report(2021)",VLOOKUP($K43,'6.GWP'!$B$2:$G$173,6,FALSE),0))))),0)),0) -> 0 | AR43: =IFERROR(IF(AND(AC43="V",$I43="預設值"),IF('1.GHG Inventory Form'!$E$6="IPCC AR2 Report(1995)",VLOOKUP($J43,'6.GWP'!$B$1:$G$173,2,FALSE),IF('1.GHG Inventory Form'!$E$6="IPCC AR3 Report(2001)",VLOOKUP($J43,'6.GWP'!$B$1:$G$173,3,FALSE),IF('1.GHG Inventory Form'!$E$6="IPCC AR4 Report(2007)",VLOOKUP($J43,'6.GWP'!$B$1:$G$173,4,FALSE),IF('1.GHG Inventory Form'!$E$6="IPCC AR5 Report(2013)",VLOOKUP($J43,'6.GWP'!$B$1:$G$173,5,FALSE),IF('1.GHG Inventory Form'!$E$6="IPCC AR6 Report(2021)",VLOOKUP($J43,'6.GWP'!$B$2:$G$173,6,FALSE),0))))),IF(AND(AC43="V",$I43="自訂值"),IF('1.GHG Inventory Form'!$E$6="IPCC AR2 Report(1995)",VLOOKUP($K43,'6.GWP'!$B$1:$G$173,2,FALSE),IF('1.GHG Inventory Form'!$E$6="IPCC AR3 Report(2001)",VLOOKUP($K43,'6.GWP'!$B$1:$G$173,3,FALSE),IF('1.GHG Inventory Form'!$E$6="IPCC AR4 Report(2007)",VLOOKUP($K43,'6.GWP'!$B$1:$G$173,4,FALSE),IF('1.GHG Inventory Form'!$E$6="IPCC AR5 Report(2013)",VLOOKUP($K43,'6.GWP'!$B$1:$G$173,5,FALSE),IF('1.GHG Inventory Form'!$E$6="IPCC AR6 Report(2021)",VLOOKUP($K43,'6.GWP'!$B$2:$G$173,6,FALSE),0))))),0)),0) -> 0 | AS43: =IF(AD43="V",IF('1.GHG Inventory Form'!$E$6="IPCC AR2 Report(1995)",'6.GWP'!$C$5,IF('1.GHG Inventory Form'!$E$6="IPCC AR3 Report(2001)",'6.GWP'!$D$5,IF('1.GHG Inventory Form'!$E$6="IPCC AR4 Report(2007)",'6.GWP'!$E$5,IF('1.GHG Inventory Form'!$E$6="IPCC AR5 Report(2013)",'6.GWP'!$F$5,IF('1.GHG Inventory Form'!$E$6="IPCC AR6 Report(2021)",'6.GWP'!$G$5,0))))),0) -> 0 | AT43: =IF(AE43="V",IF('1.GHG Inventory Form'!$E$6="IPCC AR2 Report(1995)",'6.GWP'!$C$4,IF('1.GHG Inventory Form'!$E$6="IPCC AR3 Report(2001)",'6.GWP'!$D$4,IF('1.GHG Inventory Form'!$E$6="IPCC AR4 Report(2007)",'6.GWP'!$E$4,IF('1.GHG Inventory Form'!$E$6="IPCC AR5 Report(2013)",'6.GWP'!$F$4,IF('1.GHG Inventory Form'!$E$6="IPCC AR6 Report(2021)",'6.GWP'!$G$4,0))))),0) -> 0 | AU43: =IFERROR($L43*AF43*AN43,"") -> 0 | AV43: =IFERROR($L43*AG43*AO43,"") -> 0 | AW43: =IFERROR($L43*AH43*AP43,"") -> 0 | AX43: =IFERROR($L43*AI43*AQ43,"") -> 0 | AY43: =IFERROR($L43*AJ43*AR43,"") -> 0 | AZ43: =IFERROR($L43*AK43*AS43,"") -> 0 | BA43: =IFERROR($L43*AL43*AT43,"") -> 0 | BB43: =ROUND(SUM(AU43:BA43),4) -> 0 | BC43: =BB43/SUM($BB$16:$BB$99) -> 0 | BD43: =BB43/$BB$169 -> 0 | BI43: =IF(H43="","",IF(I43="預設值Default",H43&J43,IF(I43="自訂值Custom Value",H43&K43,""))) | BJ43: =IF(H43="其它設備，請說明","",IF(O43=0,"",O43)) | BK43: =IF(H43="","",IF(I43="預設值Default",AM43,IF(I43="自訂值Custom Value",X43,"")))
M44: =IFERROR(IF(I44="預設值Default",VLOOKUP($J44,'4.Default Emission Factor'!$D:$V,16,FALSE),"請填寫自訂活動數據單位Please fill in Custom Unit"),"請選擇預設排放係數名稱Please Choose Default Fuel or Greenhouse Gas") -> 請填寫自訂活動數據單位Please fill in Custom Unit | Y44: =IF(AF44>0.0000000001,"V","") | Z44: =IF(AG44>0.0000000001,"V","") | AA44: =IF(AH44>0.0000000001,"V","") | AB44: =IF(AI44>0.0000000001,"V","") | AC44: =IF(AJ44>0.0000000001,"V","") | AD44: =IF(AK44>0.0000000001,"V","") | AE44: =IF(AL44>0.0000000001,"V","") | AF44: =IFERROR(IF($I44="預設值Default",ROUND(VLOOKUP($J44,'4.Default Emission Factor'!$D:$V,2,FALSE),10),IF($I44="自訂值Custom Value",P44,0)),0) -> 0 | AG44: =IFERROR(IF($I44="預設值Default",ROUND(VLOOKUP($J44,'4.Default Emission Factor'!$D:$V,4,FALSE),10),IF($I44="自訂值Custom Value",Q44,0)),0) -> 0 | AH44: =IFERROR(IF($I44="預設值Default",ROUND(VLOOKUP($J44,'4.Default Emission Factor'!$D:$V,6,FALSE),10),IF($I44="自訂值Custom Value",R44,0)),0) -> 0 | AI44: =IFERROR(IF($I44="預設值Default",ROUND(VLOOKUP($J44,'4.Default Emission Factor'!$D:$V,8,FALSE),10),IF($I44="自訂值Custom Value",S44,0)),0) -> 0 | AJ44: =IFERROR(IF($I44="預設值Default",ROUND(VLOOKUP($J44,'4.Default Emission Factor'!$D:$V,10,FALSE),10),IF($I44="自訂值Custom Value",T44,0)),0) -> 0 | AK44: =IFERROR(IF($I44="預設值Default",ROUND(VLOOKUP($J44,'4.Default Emission Factor'!$D:$V,12,FALSE),10),IF($I44="自訂值Custom Value",U44,0)),0) -> 0 | AL44: =IFERROR(IF($I44="預設值Default",ROUND(VLOOKUP($J44,'4.Default Emission Factor'!$D:$V,14,FALSE),10),IF($I44="自訂值Custom Value",V44,0)),0) -> 0 | AM44: =IFERROR(IF(I44="預設值Default",VLOOKUP($J44,'4.Default Emission Factor'!$D:$V,17,FALSE),IF(I44="自訂值Custom Value",X44,"")),"") | AN44: =IF(Y44="V",1,0) -> 0 | AO44: =IF(Z44="V",IF('1.GHG Inventory Form'!$E$6="IPCC AR2 Report(1995)",'6.GWP'!$C$2,IF('1.GHG Inventory Form'!$E$6="IPCC AR3 Report(2001)",'6.GWP'!$D$2,IF('1.GHG Inventory Form'!$E$6="IPCC AR4 Report(2007)",'6.GWP'!$E$2,IF('1.GHG Inventory Form'!$E$6="IPCC AR5 Report(2013)",'6.GWP'!$F$2,IF('1.GHG Inventory Form'!$E$6="IPCC AR6 Report(2021)",'6.GWP'!$G$2,0))))),0) -> 0 | AP44: =IF(AA44="V",IF('1.GHG Inventory Form'!$E$6="IPCC AR2 Report(1995)",'6.GWP'!$C$3,IF('1.GHG Inventory Form'!$E$6="IPCC AR3 Report(2001)",'6.GWP'!$D$3,IF('1.GHG Inventory Form'!$E$6="IPCC AR4 Report(2007)",'6.GWP'!$E$3,IF('1.GHG Inventory Form'!$E$6="IPCC AR5 Report(2013)",'6.GWP'!$F$3,IF('1.GHG Inventory Form'!$E$6="IPCC AR6 Report(2021)",'6.GWP'!$G$3,0))))),0) -> 0 | AQ44: =IFERROR(IF(AND(AB44="V",$I44="預設值"),IF('1.GHG Inventory Form'!$E$6="IPCC AR2 Report(1995)",VLOOKUP($J44,'6.GWP'!$B$1:$G$173,2,FALSE),IF('1.GHG Inventory Form'!$E$6="IPCC AR3 Report(2001)",VLOOKUP($J44,'6.GWP'!$B$1:$G$173,3,FALSE),IF('1.GHG Inventory Form'!$E$6="IPCC AR4 Report(2007)",VLOOKUP($J44,'6.GWP'!$B$1:$G$173,4,FALSE),IF('1.GHG Inventory Form'!$E$6="IPCC AR5 Report(2013)",VLOOKUP($J44,'6.GWP'!$B$1:$G$173,5,FALSE),IF('1.GHG Inventory Form'!$E$6="IPCC AR6 Report(2021)",VLOOKUP($J44,'6.GWP'!$B$2:$G$173,6,FALSE),0))))),IF(AND(AB44="V",$I44="自訂值"),IF('1.GHG Inventory Form'!$E$6="IPCC AR2 Report(1995)",VLOOKUP($K44,'6.GWP'!$B$1:$G$173,2,FALSE),IF('1.GHG Inventory Form'!$E$6="IPCC AR3 Report(2001)",VLOOKUP($K44,'6.GWP'!$B$1:$G$173,3,FALSE),IF('1.GHG Inventory Form'!$E$6="IPCC AR4 Report(2007)",VLOOKUP($K44,'6.GWP'!$B$1:$G$173,4,FALSE),IF('1.GHG Inventory Form'!$E$6="IPCC AR5 Report(2013)",VLOOKUP($K44,'6.GWP'!$B$1:$G$173,5,FALSE),IF('1.GHG Inventory Form'!$E$6="IPCC AR6 Report(2021)",VLOOKUP($K44,'6.GWP'!$B$2:$G$173,6,FALSE),0))))),0)),0) -> 0 | AR44: =IFERROR(IF(AND(AC44="V",$I44="預設值"),IF('1.GHG Inventory Form'!$E$6="IPCC AR2 Report(1995)",VLOOKUP($J44,'6.GWP'!$B$1:$G$173,2,FALSE),IF('1.GHG Inventory Form'!$E$6="IPCC AR3 Report(2001)",VLOOKUP($J44,'6.GWP'!$B$1:$G$173,3,FALSE),IF('1.GHG Inventory Form'!$E$6="IPCC AR4 Report(2007)",VLOOKUP($J44,'6.GWP'!$B$1:$G$173,4,FALSE),IF('1.GHG Inventory Form'!$E$6="IPCC AR5 Report(2013)",VLOOKUP($J44,'6.GWP'!$B$1:$G$173,5,FALSE),IF('1.GHG Inventory Form'!$E$6="IPCC AR6 Report(2021)",VLOOKUP($J44,'6.GWP'!$B$2:$G$173,6,FALSE),0))))),IF(AND(AC44="V",$I44="自訂值"),IF('1.GHG Inventory Form'!$E$6="IPCC AR2 Report(1995)",VLOOKUP($K44,'6.GWP'!$B$1:$G$173,2,FALSE),IF('1.GHG Inventory Form'!$E$6="IPCC AR3 Report(2001)",VLOOKUP($K44,'6.GWP'!$B$1:$G$173,3,FALSE),IF('1.GHG Inventory Form'!$E$6="IPCC AR4 Report(2007)",VLOOKUP($K44,'6.GWP'!$B$1:$G$173,4,FALSE),IF('1.GHG Inventory Form'!$E$6="IPCC AR5 Report(2013)",VLOOKUP($K44,'6.GWP'!$B$1:$G$173,5,FALSE),IF('1.GHG Inventory Form'!$E$6="IPCC AR6 Report(2021)",VLOOKUP($K44,'6.GWP'!$B$2:$G$173,6,FALSE),0))))),0)),0) -> 0 | AS44: =IF(AD44="V",IF('1.GHG Inventory Form'!$E$6="IPCC AR2 Report(1995)",'6.GWP'!$C$5,IF('1.GHG Inventory Form'!$E$6="IPCC AR3 Report(2001)",'6.GWP'!$D$5,IF('1.GHG Inventory Form'!$E$6="IPCC AR4 Report(2007)",'6.GWP'!$E$5,IF('1.GHG Inventory Form'!$E$6="IPCC AR5 Report(2013)",'6.GWP'!$F$5,IF('1.GHG Inventory Form'!$E$6="IPCC AR6 Report(2021)",'6.GWP'!$G$5,0))))),0) -> 0 | AT44: =IF(AE44="V",IF('1.GHG Inventory Form'!$E$6="IPCC AR2 Report(1995)",'6.GWP'!$C$4,IF('1.GHG Inventory Form'!$E$6="IPCC AR3 Report(2001)",'6.GWP'!$D$4,IF('1.GHG Inventory Form'!$E$6="IPCC AR4 Report(2007)",'6.GWP'!$E$4,IF('1.GHG Inventory Form'!$E$6="IPCC AR5 Report(2013)",'6.GWP'!$F$4,IF('1.GHG Inventory Form'!$E$6="IPCC AR6 Report(2021)",'6.GWP'!$G$4,0))))),0) -> 0 | AU44: =IFERROR($L44*AF44*AN44,"") -> 0 | AV44: =IFERROR($L44*AG44*AO44,"") -> 0 | AW44: =IFERROR($L44*AH44*AP44,"") -> 0 | AX44: =IFERROR($L44*AI44*AQ44,"") -> 0 | AY44: =IFERROR($L44*AJ44*AR44,"") -> 0 | AZ44: =IFERROR($L44*AK44*AS44,"") -> 0 | BA44: =IFERROR($L44*AL44*AT44,"") -> 0 | BB44: =ROUND(SUM(AU44:BA44),4) -> 0 | BC44: =BB44/SUM($BB$16:$BB$99) -> 0 | BD44: =BB44/$BB$169 -> 0 | BI44: =IF(H44="","",IF(I44="預設值Default",H44&J44,IF(I44="自訂值Custom Value",H44&K44,""))) | BJ44: =IF(H44="其它設備，請說明","",IF(O44=0,"",O44)) | BK44: =IF(H44="","",IF(I44="預設值Default",AM44,IF(I44="自訂值Custom Value",X44,"")))
M45: =IFERROR(IF(I45="預設值Default",VLOOKUP($J45,'4.Default Emission Factor'!$D:$V,16,FALSE),"請填寫自訂活動數據單位Please fill in Custom Unit"),"請選擇預設排放係數名稱Please Choose Default Fuel or Greenhouse Gas") -> 請填寫自訂活動數據單位Please fill in Custom Unit | Y45: =IF(AF45>0.0000000001,"V","") | Z45: =IF(AG45>0.0000000001,"V","") | AA45: =IF(AH45>0.0000000001,"V","") | AB45: =IF(AI45>0.0000000001,"V","") | AC45: =IF(AJ45>0.0000000001,"V","") | AD45: =IF(AK45>0.0000000001,"V","") | AE45: =IF(AL45>0.0000000001,"V","") | AF45: =IFERROR(IF($I45="預設值Default",ROUND(VLOOKUP($J45,'4.Default Emission Factor'!$D:$V,2,FALSE),10),IF($I45="自訂值Custom Value",P45,0)),0) -> 0 | AG45: =IFERROR(IF($I45="預設值Default",ROUND(VLOOKUP($J45,'4.Default Emission Factor'!$D:$V,4,FALSE),10),IF($I45="自訂值Custom Value",Q45,0)),0) -> 0 | AH45: =IFERROR(IF($I45="預設值Default",ROUND(VLOOKUP($J45,'4.Default Emission Factor'!$D:$V,6,FALSE),10),IF($I45="自訂值Custom Value",R45,0)),0) -> 0 | AI45: =IFERROR(IF($I45="預設值Default",ROUND(VLOOKUP($J45,'4.Default Emission Factor'!$D:$V,8,FALSE),10),IF($I45="自訂值Custom Value",S45,0)),0) -> 0 | AJ45: =IFERROR(IF($I45="預設值Default",ROUND(VLOOKUP($J45,'4.Default Emission Factor'!$D:$V,10,FALSE),10),IF($I45="自訂值Custom Value",T45,0)),0) -> 0 | AK45: =IFERROR(IF($I45="預設值Default",ROUND(VLOOKUP($J45,'4.Default Emission Factor'!$D:$V,12,FALSE),10),IF($I45="自訂值Custom Value",U45,0)),0) -> 0 | AL45: =IFERROR(IF($I45="預設值Default",ROUND(VLOOKUP($J45,'4.Default Emission Factor'!$D:$V,14,FALSE),10),IF($I45="自訂值Custom Value",V45,0)),0) -> 0 | AM45: =IFERROR(IF(I45="預設值Default",VLOOKUP($J45,'4.Default Emission Factor'!$D:$V,17,FALSE),IF(I45="自訂值Custom Value",X45,"")),"") | AN45: =IF(Y45="V",1,0) -> 0 | AO45: =IF(Z45="V",IF('1.GHG Inventory Form'!$E$6="IPCC AR2 Report(1995)",'6.GWP'!$C$2,IF('1.GHG Inventory Form'!$E$6="IPCC AR3 Report(2001)",'6.GWP'!$D$2,IF('1.GHG Inventory Form'!$E$6="IPCC AR4 Report(2007)",'6.GWP'!$E$2,IF('1.GHG Inventory Form'!$E$6="IPCC AR5 Report(2013)",'6.GWP'!$F$2,IF('1.GHG Inventory Form'!$E$6="IPCC AR6 Report(2021)",'6.GWP'!$G$2,0))))),0) -> 0 | AP45: =IF(AA45="V",IF('1.GHG Inventory Form'!$E$6="IPCC AR2 Report(1995)",'6.GWP'!$C$3,IF('1.GHG Inventory Form'!$E$6="IPCC AR3 Report(2001)",'6.GWP'!$D$3,IF('1.GHG Inventory Form'!$E$6="IPCC AR4 Report(2007)",'6.GWP'!$E$3,IF('1.GHG Inventory Form'!$E$6="IPCC AR5 Report(2013)",'6.GWP'!$F$3,IF('1.GHG Inventory Form'!$E$6="IPCC AR6 Report(2021)",'6.GWP'!$G$3,0))))),0) -> 0 | AQ45: =IFERROR(IF(AND(AB45="V",$I45="預設值"),IF('1.GHG Inventory Form'!$E$6="IPCC AR2 Report(1995)",VLOOKUP($J45,'6.GWP'!$B$1:$G$173,2,FALSE),IF('1.GHG Inventory Form'!$E$6="IPCC AR3 Report(2001)",VLOOKUP($J45,'6.GWP'!$B$1:$G$173,3,FALSE),IF('1.GHG Inventory Form'!$E$6="IPCC AR4 Report(2007)",VLOOKUP($J45,'6.GWP'!$B$1:$G$173,4,FALSE),IF('1.GHG Inventory Form'!$E$6="IPCC AR5 Report(2013)",VLOOKUP($J45,'6.GWP'!$B$1:$G$173,5,FALSE),IF('1.GHG Inventory Form'!$E$6="IPCC AR6 Report(2021)",VLOOKUP($J45,'6.GWP'!$B$2:$G$173,6,FALSE),0))))),IF(AND(AB45="V",$I45="自訂值"),IF('1.GHG Inventory Form'!$E$6="IPCC AR2 Report(1995)",VLOOKUP($K45,'6.GWP'!$B$1:$G$173,2,FALSE),IF('1.GHG Inventory Form'!$E$6="IPCC AR3 Report(2001)",VLOOKUP($K45,'6.GWP'!$B$1:$G$173,3,FALSE),IF('1.GHG Inventory Form'!$E$6="IPCC AR4 Report(2007)",VLOOKUP($K45,'6.GWP'!$B$1:$G$173,4,FALSE),IF('1.GHG Inventory Form'!$E$6="IPCC AR5 Report(2013)",VLOOKUP($K45,'6.GWP'!$B$1:$G$173,5,FALSE),IF('1.GHG Inventory Form'!$E$6="IPCC AR6 Report(2021)",VLOOKUP($K45,'6.GWP'!$B$2:$G$173,6,FALSE),0))))),0)),0) -> 0 | AR45: =IFERROR(IF(AND(AC45="V",$I45="預設值"),IF('1.GHG Inventory Form'!$E$6="IPCC AR2 Report(1995)",VLOOKUP($J45,'6.GWP'!$B$1:$G$173,2,FALSE),IF('1.GHG Inventory Form'!$E$6="IPCC AR3 Report(2001)",VLOOKUP($J45,'6.GWP'!$B$1:$G$173,3,FALSE),IF('1.GHG Inventory Form'!$E$6="IPCC AR4 Report(2007)",VLOOKUP($J45,'6.GWP'!$B$1:$G$173,4,FALSE),IF('1.GHG Inventory Form'!$E$6="IPCC AR5 Report(2013)",VLOOKUP($J45,'6.GWP'!$B$1:$G$173,5,FALSE),IF('1.GHG Inventory Form'!$E$6="IPCC AR6 Report(2021)",VLOOKUP($J45,'6.GWP'!$B$2:$G$173,6,FALSE),0))))),IF(AND(AC45="V",$I45="自訂值"),IF('1.GHG Inventory Form'!$E$6="IPCC AR2 Report(1995)",VLOOKUP($K45,'6.GWP'!$B$1:$G$173,2,FALSE),IF('1.GHG Inventory Form'!$E$6="IPCC AR3 Report(2001)",VLOOKUP($K45,'6.GWP'!$B$1:$G$173,3,FALSE),IF('1.GHG Inventory Form'!$E$6="IPCC AR4 Report(2007)",VLOOKUP($K45,'6.GWP'!$B$1:$G$173,4,FALSE),IF('1.GHG Inventory Form'!$E$6="IPCC AR5 Report(2013)",VLOOKUP($K45,'6.GWP'!$B$1:$G$173,5,FALSE),IF('1.GHG Inventory Form'!$E$6="IPCC AR6 Report(2021)",VLOOKUP($K45,'6.GWP'!$B$2:$G$173,6,FALSE),0))))),0)),0) -> 0 | AS45: =IF(AD45="V",IF('1.GHG Inventory Form'!$E$6="IPCC AR2 Report(1995)",'6.GWP'!$C$5,IF('1.GHG Inventory Form'!$E$6="IPCC AR3 Report(2001)",'6.GWP'!$D$5,IF('1.GHG Inventory Form'!$E$6="IPCC AR4 Report(2007)",'6.GWP'!$E$5,IF('1.GHG Inventory Form'!$E$6="IPCC AR5 Report(2013)",'6.GWP'!$F$5,IF('1.GHG Inventory Form'!$E$6="IPCC AR6 Report(2021)",'6.GWP'!$G$5,0))))),0) -> 0 | AT45: =IF(AE45="V",IF('1.GHG Inventory Form'!$E$6="IPCC AR2 Report(1995)",'6.GWP'!$C$4,IF('1.GHG Inventory Form'!$E$6="IPCC AR3 Report(2001)",'6.GWP'!$D$4,IF('1.GHG Inventory Form'!$E$6="IPCC AR4 Report(2007)",'6.GWP'!$E$4,IF('1.GHG Inventory Form'!$E$6="IPCC AR5 Report(2013)",'6.GWP'!$F$4,IF('1.GHG Inventory Form'!$E$6="IPCC AR6 Report(2021)",'6.GWP'!$G$4,0))))),0) -> 0 | AU45: =IFERROR($L45*AF45*AN45,"") -> 0 | AV45: =IFERROR($L45*AG45*AO45,"") -> 0 | AW45: =IFERROR($L45*AH45*AP45,"") -> 0 | AX45: =IFERROR($L45*AI45*AQ45,"") -> 0 | AY45: =IFERROR($L45*AJ45*AR45,"") -> 0 | AZ45: =IFERROR($L45*AK45*AS45,"") -> 0 | BA45: =IFERROR($L45*AL45*AT45,"") -> 0 | BB45: =ROUND(SUM(AU45:BA45),4) -> 0 | BC45: =BB45/SUM($BB$16:$BB$99) -> 0 | BD45: =BB45/$BB$169 -> 0 | BI45: =IF(H45="","",IF(I45="預設值Default",H45&J45,IF(I45="自訂值Custom Value",H45&K45,""))) | BJ45: =IF(H45="其它設備，請說明","",IF(O45=0,"",O45)) | BK45: =IF(H45="","",IF(I45="預設值Default",AM45,IF(I45="自訂值Custom Value",X45,"")))
M46: =IFERROR(IF(I46="預設值Default",VLOOKUP($J46,'4.Default Emission Factor'!$D:$V,16,FALSE),"請填寫自訂活動數據單位Please fill in Custom Unit"),"請選擇預設排放係數名稱Please Choose Default Fuel or Greenhouse Gas") -> 請填寫自訂活動數據單位Please fill in Custom Unit | Y46: =IF(AF46>0.0000000001,"V","") | Z46: =IF(AG46>0.0000000001,"V","") | AA46: =IF(AH46>0.0000000001,"V","") | AB46: =IF(AI46>0.0000000001,"V","") | AC46: =IF(AJ46>0.0000000001,"V","") | AD46: =IF(AK46>0.0000000001,"V","") | AE46: =IF(AL46>0.0000000001,"V","") | AF46: =IFERROR(IF($I46="預設值Default",ROUND(VLOOKUP($J46,'4.Default Emission Factor'!$D:$V,2,FALSE),10),IF($I46="自訂值Custom Value",P46,0)),0) -> 0 | AG46: =IFERROR(IF($I46="預設值Default",ROUND(VLOOKUP($J46,'4.Default Emission Factor'!$D:$V,4,FALSE),10),IF($I46="自訂值Custom Value",Q46,0)),0) -> 0 | AH46: =IFERROR(IF($I46="預設值Default",ROUND(VLOOKUP($J46,'4.Default Emission Factor'!$D:$V,6,FALSE),10),IF($I46="自訂值Custom Value",R46,0)),0) -> 0 | AI46: =IFERROR(IF($I46="預設值Default",ROUND(VLOOKUP($J46,'4.Default Emission Factor'!$D:$V,8,FALSE),10),IF($I46="自訂值Custom Value",S46,0)),0) -> 0 | AJ46: =IFERROR(IF($I46="預設值Default",ROUND(VLOOKUP($J46,'4.Default Emission Factor'!$D:$V,10,FALSE),10),IF($I46="自訂值Custom Value",T46,0)),0) -> 0 | AK46: =IFERROR(IF($I46="預設值Default",ROUND(VLOOKUP($J46,'4.Default Emission Factor'!$D:$V,12,FALSE),10),IF($I46="自訂值Custom Value",U46,0)),0) -> 0 | AL46: =IFERROR(IF($I46="預設值Default",ROUND(VLOOKUP($J46,'4.Default Emission Factor'!$D:$V,14,FALSE),10),IF($I46="自訂值Custom Value",V46,0)),0) -> 0 | AM46: =IFERROR(IF(I46="預設值Default",VLOOKUP($J46,'4.Default Emission Factor'!$D:$V,17,FALSE),IF(I46="自訂值Custom Value",X46,"")),"") | AN46: =IF(Y46="V",1,0) -> 0 | AO46: =IF(Z46="V",IF('1.GHG Inventory Form'!$E$6="IPCC AR2 Report(1995)",'6.GWP'!$C$2,IF('1.GHG Inventory Form'!$E$6="IPCC AR3 Report(2001)",'6.GWP'!$D$2,IF('1.GHG Inventory Form'!$E$6="IPCC AR4 Report(2007)",'6.GWP'!$E$2,IF('1.GHG Inventory Form'!$E$6="IPCC AR5 Report(2013)",'6.GWP'!$F$2,IF('1.GHG Inventory Form'!$E$6="IPCC AR6 Report(2021)",'6.GWP'!$G$2,0))))),0) -> 0 | AP46: =IF(AA46="V",IF('1.GHG Inventory Form'!$E$6="IPCC AR2 Report(1995)",'6.GWP'!$C$3,IF('1.GHG Inventory Form'!$E$6="IPCC AR3 Report(2001)",'6.GWP'!$D$3,IF('1.GHG Inventory Form'!$E$6="IPCC AR4 Report(2007)",'6.GWP'!$E$3,IF('1.GHG Inventory Form'!$E$6="IPCC AR5 Report(2013)",'6.GWP'!$F$3,IF('1.GHG Inventory Form'!$E$6="IPCC AR6 Report(2021)",'6.GWP'!$G$3,0))))),0) -> 0 | AQ46: =IFERROR(IF(AND(AB46="V",$I46="預設值"),IF('1.GHG Inventory Form'!$E$6="IPCC AR2 Report(1995)",VLOOKUP($J46,'6.GWP'!$B$1:$G$173,2,FALSE),IF('1.GHG Inventory Form'!$E$6="IPCC AR3 Report(2001)",VLOOKUP($J46,'6.GWP'!$B$1:$G$173,3,FALSE),IF('1.GHG Inventory Form'!$E$6="IPCC AR4 Report(2007)",VLOOKUP($J46,'6.GWP'!$B$1:$G$173,4,FALSE),IF('1.GHG Inventory Form'!$E$6="IPCC AR5 Report(2013)",VLOOKUP($J46,'6.GWP'!$B$1:$G$173,5,FALSE),IF('1.GHG Inventory Form'!$E$6="IPCC AR6 Report(2021)",VLOOKUP($J46,'6.GWP'!$B$2:$G$173,6,FALSE),0))))),IF(AND(AB46="V",$I46="自訂值"),IF('1.GHG Inventory Form'!$E$6="IPCC AR2 Report(1995)",VLOOKUP($K46,'6.GWP'!$B$1:$G$173,2,FALSE),IF('1.GHG Inventory Form'!$E$6="IPCC AR3 Report(2001)",VLOOKUP($K46,'6.GWP'!$B$1:$G$173,3,FALSE),IF('1.GHG Inventory Form'!$E$6="IPCC AR4 Report(2007)",VLOOKUP($K46,'6.GWP'!$B$1:$G$173,4,FALSE),IF('1.GHG Inventory Form'!$E$6="IPCC AR5 Report(2013)",VLOOKUP($K46,'6.GWP'!$B$1:$G$173,5,FALSE),IF('1.GHG Inventory Form'!$E$6="IPCC AR6 Report(2021)",VLOOKUP($K46,'6.GWP'!$B$2:$G$173,6,FALSE),0))))),0)),0) -> 0 | AR46: =IFERROR(IF(AND(AC46="V",$I46="預設值"),IF('1.GHG Inventory Form'!$E$6="IPCC AR2 Report(1995)",VLOOKUP($J46,'6.GWP'!$B$1:$G$173,2,FALSE),IF('1.GHG Inventory Form'!$E$6="IPCC AR3 Report(2001)",VLOOKUP($J46,'6.GWP'!$B$1:$G$173,3,FALSE),IF('1.GHG Inventory Form'!$E$6="IPCC AR4 Report(2007)",VLOOKUP($J46,'6.GWP'!$B$1:$G$173,4,FALSE),IF('1.GHG Inventory Form'!$E$6="IPCC AR5 Report(2013)",VLOOKUP($J46,'6.GWP'!$B$1:$G$173,5,FALSE),IF('1.GHG Inventory Form'!$E$6="IPCC AR6 Report(2021)",VLOOKUP($J46,'6.GWP'!$B$2:$G$173,6,FALSE),0))))),IF(AND(AC46="V",$I46="自訂值"),IF('1.GHG Inventory Form'!$E$6="IPCC AR2 Report(1995)",VLOOKUP($K46,'6.GWP'!$B$1:$G$173,2,FALSE),IF('1.GHG Inventory Form'!$E$6="IPCC AR3 Report(2001)",VLOOKUP($K46,'6.GWP'!$B$1:$G$173,3,FALSE),IF('1.GHG Inventory Form'!$E$6="IPCC AR4 Report(2007)",VLOOKUP($K46,'6.GWP'!$B$1:$G$173,4,FALSE),IF('1.GHG Inventory Form'!$E$6="IPCC AR5 Report(2013)",VLOOKUP($K46,'6.GWP'!$B$1:$G$173,5,FALSE),IF('1.GHG Inventory Form'!$E$6="IPCC AR6 Report(2021)",VLOOKUP($K46,'6.GWP'!$B$2:$G$173,6,FALSE),0))))),0)),0) -> 0 | AS46: =IF(AD46="V",IF('1.GHG Inventory Form'!$E$6="IPCC AR2 Report(1995)",'6.GWP'!$C$5,IF('1.GHG Inventory Form'!$E$6="IPCC AR3 Report(2001)",'6.GWP'!$D$5,IF('1.GHG Inventory Form'!$E$6="IPCC AR4 Report(2007)",'6.GWP'!$E$5,IF('1.GHG Inventory Form'!$E$6="IPCC AR5 Report(2013)",'6.GWP'!$F$5,IF('1.GHG Inventory Form'!$E$6="IPCC AR6 Report(2021)",'6.GWP'!$G$5,0))))),0) -> 0 | AT46: =IF(AE46="V",IF('1.GHG Inventory Form'!$E$6="IPCC AR2 Report(1995)",'6.GWP'!$C$4,IF('1.GHG Inventory Form'!$E$6="IPCC AR3 Report(2001)",'6.GWP'!$D$4,IF('1.GHG Inventory Form'!$E$6="IPCC AR4 Report(2007)",'6.GWP'!$E$4,IF('1.GHG Inventory Form'!$E$6="IPCC AR5 Report(2013)",'6.GWP'!$F$4,IF('1.GHG Inventory Form'!$E$6="IPCC AR6 Report(2021)",'6.GWP'!$G$4,0))))),0) -> 0 | AU46: =IFERROR($L46*AF46*AN46,"") -> 0 | AV46: =IFERROR($L46*AG46*AO46,"") -> 0 | AW46: =IFERROR($L46*AH46*AP46,"") -> 0 | AX46: =IFERROR($L46*AI46*AQ46,"") -> 0 | AY46: =IFERROR($L46*AJ46*AR46,"") -> 0 | AZ46: =IFERROR($L46*AK46*AS46,"") -> 0 | BA46: =IFERROR($L46*AL46*AT46,"") -> 0 | BB46: =ROUND(SUM(AU46:BA46),4) -> 0 | BC46: =BB46/SUM($BB$16:$BB$99) -> 0 | BD46: =BB46/$BB$169 -> 0 | BI46: =IF(H46="","",IF(I46="預設值Default",H46&J46,IF(I46="自訂值Custom Value",H46&K46,""))) | BJ46: =IF(H46="其它設備，請說明","",IF(O46=0,"",O46)) | BK46: =IF(H46="","",IF(I46="預設值Default",AM46,IF(I46="自訂值Custom Value",X46,"")))
M47: =IFERROR(IF(I47="預設值Default",VLOOKUP($J47,'4.Default Emission Factor'!$D:$V,16,FALSE),"請填寫自訂活動數據單位Please fill in Custom Unit"),"請選擇預設排放係數名稱Please Choose Default Fuel or Greenhouse Gas") -> 請填寫自訂活動數據單位Please fill in Custom Unit | Y47: =IF(AF47>0.0000000001,"V","") | Z47: =IF(AG47>0.0000000001,"V","") | AA47: =IF(AH47>0.0000000001,"V","") | AB47: =IF(AI47>0.0000000001,"V","") | AC47: =IF(AJ47>0.0000000001,"V","") | AD47: =IF(AK47>0.0000000001,"V","") | AE47: =IF(AL47>0.0000000001,"V","") | AF47: =IFERROR(IF($I47="預設值Default",ROUND(VLOOKUP($J47,'4.Default Emission Factor'!$D:$V,2,FALSE),10),IF($I47="自訂值Custom Value",P47,0)),0) -> 0 | AG47: =IFERROR(IF($I47="預設值Default",ROUND(VLOOKUP($J47,'4.Default Emission Factor'!$D:$V,4,FALSE),10),IF($I47="自訂值Custom Value",Q47,0)),0) -> 0 | AH47: =IFERROR(IF($I47="預設值Default",ROUND(VLOOKUP($J47,'4.Default Emission Factor'!$D:$V,6,FALSE),10),IF($I47="自訂值Custom Value",R47,0)),0) -> 0 | AI47: =IFERROR(IF($I47="預設值Default",ROUND(VLOOKUP($J47,'4.Default Emission Factor'!$D:$V,8,FALSE),10),IF($I47="自訂值Custom Value",S47,0)),0) -> 0 | AJ47: =IFERROR(IF($I47="預設值Default",ROUND(VLOOKUP($J47,'4.Default Emission Factor'!$D:$V,10,FALSE),10),IF($I47="自訂值Custom Value",T47,0)),0) -> 0 | AK47: =IFERROR(IF($I47="預設值Default",ROUND(VLOOKUP($J47,'4.Default Emission Factor'!$D:$V,12,FALSE),10),IF($I47="自訂值Custom Value",U47,0)),0) -> 0 | AL47: =IFERROR(IF($I47="預設值Default",ROUND(VLOOKUP($J47,'4.Default Emission Factor'!$D:$V,14,FALSE),10),IF($I47="自訂值Custom Value",V47,0)),0) -> 0 | AM47: =IFERROR(IF(I47="預設值Default",VLOOKUP($J47,'4.Default Emission Factor'!$D:$V,17,FALSE),IF(I47="自訂值Custom Value",X47,"")),"") | AN47: =IF(Y47="V",1,0) -> 0 | AO47: =IF(Z47="V",IF('1.GHG Inventory Form'!$E$6="IPCC AR2 Report(1995)",'6.GWP'!$C$2,IF('1.GHG Inventory Form'!$E$6="IPCC AR3 Report(2001)",'6.GWP'!$D$2,IF('1.GHG Inventory Form'!$E$6="IPCC AR4 Report(2007)",'6.GWP'!$E$2,IF('1.GHG Inventory Form'!$E$6="IPCC AR5 Report(2013)",'6.GWP'!$F$2,IF('1.GHG Inventory Form'!$E$6="IPCC AR6 Report(2021)",'6.GWP'!$G$2,0))))),0) -> 0 | AP47: =IF(AA47="V",IF('1.GHG Inventory Form'!$E$6="IPCC AR2 Report(1995)",'6.GWP'!$C$3,IF('1.GHG Inventory Form'!$E$6="IPCC AR3 Report(2001)",'6.GWP'!$D$3,IF('1.GHG Inventory Form'!$E$6="IPCC AR4 Report(2007)",'6.GWP'!$E$3,IF('1.GHG Inventory Form'!$E$6="IPCC AR5 Report(2013)",'6.GWP'!$F$3,IF('1.GHG Inventory Form'!$E$6="IPCC AR6 Report(2021)",'6.GWP'!$G$3,0))))),0) -> 0 | AQ47: =IFERROR(IF(AND(AB47="V",$I47="預設值"),IF('1.GHG Inventory Form'!$E$6="IPCC AR2 Report(1995)",VLOOKUP($J47,'6.GWP'!$B$1:$G$173,2,FALSE),IF('1.GHG Inventory Form'!$E$6="IPCC AR3 Report(2001)",VLOOKUP($J47,'6.GWP'!$B$1:$G$173,3,FALSE),IF('1.GHG Inventory Form'!$E$6="IPCC AR4 Report(2007)",VLOOKUP($J47,'6.GWP'!$B$1:$G$173,4,FALSE),IF('1.GHG Inventory Form'!$E$6="IPCC AR5 Report(2013)",VLOOKUP($J47,'6.GWP'!$B$1:$G$173,5,FALSE),IF('1.GHG Inventory Form'!$E$6="IPCC AR6 Report(2021)",VLOOKUP($J47,'6.GWP'!$B$2:$G$173,6,FALSE),0))))),IF(AND(AB47="V",$I47="自訂值"),IF('1.GHG Inventory Form'!$E$6="IPCC AR2 Report(1995)",VLOOKUP($K47,'6.GWP'!$B$1:$G$173,2,FALSE),IF('1.GHG Inventory Form'!$E$6="IPCC AR3 Report(2001)",VLOOKUP($K47,'6.GWP'!$B$1:$G$173,3,FALSE),IF('1.GHG Inventory Form'!$E$6="IPCC AR4 Report(2007)",VLOOKUP($K47,'6.GWP'!$B$1:$G$173,4,FALSE),IF('1.GHG Inventory Form'!$E$6="IPCC AR5 Report(2013)",VLOOKUP($K47,'6.GWP'!$B$1:$G$173,5,FALSE),IF('1.GHG Inventory Form'!$E$6="IPCC AR6 Report(2021)",VLOOKUP($K47,'6.GWP'!$B$2:$G$173,6,FALSE),0))))),0)),0) -> 0 | AR47: =IFERROR(IF(AND(AC47="V",$I47="預設值"),IF('1.GHG Inventory Form'!$E$6="IPCC AR2 Report(1995)",VLOOKUP($J47,'6.GWP'!$B$1:$G$173,2,FALSE),IF('1.GHG Inventory Form'!$E$6="IPCC AR3 Report(2001)",VLOOKUP($J47,'6.GWP'!$B$1:$G$173,3,FALSE),IF('1.GHG Inventory Form'!$E$6="IPCC AR4 Report(2007)",VLOOKUP($J47,'6.GWP'!$B$1:$G$173,4,FALSE),IF('1.GHG Inventory Form'!$E$6="IPCC AR5 Report(2013)",VLOOKUP($J47,'6.GWP'!$B$1:$G$173,5,FALSE),IF('1.GHG Inventory Form'!$E$6="IPCC AR6 Report(2021)",VLOOKUP($J47,'6.GWP'!$B$2:$G$173,6,FALSE),0))))),IF(AND(AC47="V",$I47="自訂值"),IF('1.GHG Inventory Form'!$E$6="IPCC AR2 Report(1995)",VLOOKUP($K47,'6.GWP'!$B$1:$G$173,2,FALSE),IF('1.GHG Inventory Form'!$E$6="IPCC AR3 Report(2001)",VLOOKUP($K47,'6.GWP'!$B$1:$G$173,3,FALSE),IF('1.GHG Inventory Form'!$E$6="IPCC AR4 Report(2007)",VLOOKUP($K47,'6.GWP'!$B$1:$G$173,4,FALSE),IF('1.GHG Inventory Form'!$E$6="IPCC AR5 Report(2013)",VLOOKUP($K47,'6.GWP'!$B$1:$G$173,5,FALSE),IF('1.GHG Inventory Form'!$E$6="IPCC AR6 Report(2021)",VLOOKUP($K47,'6.GWP'!$B$2:$G$173,6,FALSE),0))))),0)),0) -> 0 | AS47: =IF(AD47="V",IF('1.GHG Inventory Form'!$E$6="IPCC AR2 Report(1995)",'6.GWP'!$C$5,IF('1.GHG Inventory Form'!$E$6="IPCC AR3 Report(2001)",'6.GWP'!$D$5,IF('1.GHG Inventory Form'!$E$6="IPCC AR4 Report(2007)",'6.GWP'!$E$5,IF('1.GHG Inventory Form'!$E$6="IPCC AR5 Report(2013)",'6.GWP'!$F$5,IF('1.GHG Inventory Form'!$E$6="IPCC AR6 Report(2021)",'6.GWP'!$G$5,0))))),0) -> 0 | AT47: =IF(AE47="V",IF('1.GHG Inventory Form'!$E$6="IPCC AR2 Report(1995)",'6.GWP'!$C$4,IF('1.GHG Inventory Form'!$E$6="IPCC AR3 Report(2001)",'6.GWP'!$D$4,IF('1.GHG Inventory Form'!$E$6="IPCC AR4 Report(2007)",'6.GWP'!$E$4,IF('1.GHG Inventory Form'!$E$6="IPCC AR5 Report(2013)",'6.GWP'!$F$4,IF('1.GHG Inventory Form'!$E$6="IPCC AR6 Report(2021)",'6.GWP'!$G$4,0))))),0) -> 0 | AU47: =IFERROR($L47*AF47*AN47,"") -> 0 | AV47: =IFERROR($L47*AG47*AO47,"") -> 0 | AW47: =IFERROR($L47*AH47*AP47,"") -> 0 | AX47: =IFERROR($L47*AI47*AQ47,"") -> 0 | AY47: =IFERROR($L47*AJ47*AR47,"") -> 0 | AZ47: =IFERROR($L47*AK47*AS47,"") -> 0 | BA47: =IFERROR($L47*AL47*AT47,"") -> 0 | BB47: =ROUND(SUM(AU47:BA47),4) -> 0 | BC47: =BB47/SUM($BB$16:$BB$99) -> 0 | BD47: =BB47/$BB$169 -> 0 | BI47: =IF(H47="","",IF(I47="預設值Default",H47&J47,IF(I47="自訂值Custom Value",H47&K47,""))) | BJ47: =IF(H47="其它設備，請說明","",IF(O47=0,"",O47)) | BK47: =IF(H47="","",IF(I47="預設值Default",AM47,IF(I47="自訂值Custom Value",X47,"")))
